Workbook
Name FID_1: [1]AGR_Fuels!$A$2
Name GWhtoPJ: 1/277.778
Name hydro_temp: #REF!
Name hydro_temp: #REF!
Name hydro_temp: #REF!
Name input_05: #REF!
Name input_05: #REF!
Name input_05: #REF!
Name last: #REF!
Name last: #REF!
Name last: #REF!
Name latest_year: '[2]MACRO ECONOMIC DATA'!$D$133
Name March_Years: OFFSET('[3]Demand - MY'!$A$11,0,0,COUNTA('[3]Demand - MY'!$A$11:$A$799),1)
Name MWhtoPJ: 0.0000036
Name Net_generation: [4]StationID!$N$3:$Q$153
Name NZ_HES_description: #REF!
Name NZ_HES_description: #REF!
Name NZ_HES_description: #REF!
Name PJfromGWh: 277.778
Name Print_it: [5]!Print_it
Name Print_it: [5]!Print_it
Name Quarters: OFFSET('[3]Primary Energy - Q'!$A$11,0,0,COUNTA('[3]Primary Energy - Q'!$A$11:$A$793),1)
Name Technical_Notes_...: #REF!
Name Technical_Notes_...: #REF!
Name Technical_Notes_...: #REF!
Name temp: #REF!
Name temp: #REF!
Name temp: #REF!
Name TWhtoPJ: 3.6
Name Years: OFFSET('[3]Demand - DY'!$A$11,0,0,COUNTA('[3]Demand - DY'!$A$11:$A$98),1)

Sheet Documentation
A1: Workbook: South Island Other Sector Base Year
A2: PROC_COM_AGR: Agriculture sector technology and enduse commodity definitions
A3: AGR_fuels: Agriculture sector fuel commodity and process definitions
A4: AGR: Agriculture process data
A5: RES_techs_coms: Residential sector technology and enduse commodity definitions
A6: RES_fuel_dem: Residential sector fuel commodity and process definitions
A7: RES: Agriculture process data
A8: COM_techs: Commercial sector technology and enduse commodity definitions
A9: COM_fuels: Commercial sector fuel commodity and process definitions
A10: COM: Commercial sector process data
A11: Emi: Agriculture, residential, and commercial fuel emissions

Sheet EB1
B3: Regional Energy End Use by Fuel Type - Delivered Energy for the Calendar Year 2012 (Terajoules)
B5: Island | C5: Region | D5: Aviation Fuel/Kerosene | E5: Biogas | F5: Black Liquor | G5: Coal | H5: Diesel | I5: Electricity | J5: Fuel Oil | K5: Geothermal | L5: LPG | M5: Natural Gas | N5: Petrol | O5: Solar | P5: Wood | Q5: Grand Total
B6: NI | C6: Auckland Region | D6: 5.0760698 | E6: 0 | F6: 0 | G6: 4.7040854 | H6: 30.353856 | I6: 35.581102 | J6: 1.884448 | K6: 0.058266818 | L6: 2.0048567 | M6: 13.929684 | N6: 38.135748 | O6: 0.12148232 | P6: 9.5274125 | Q6: 141.37701
B7: NI | C7: Bay of Plenty Region | D7: 0.13260687 | E7: 0.024054983 | F7: 9.9478626 | G7: 1.1435761 | H7: 7.0120437 | I7: 9.3897224 | J7: 0.45823449 | K7: 6.5921802 | L7: 0.16889858 | M7: 3.6873565 | N7: 4.9873045 | O7: 0.022977498 | P7: 5.0932435 | Q7: 48.660062
B8: SI | C8: Canterbury Region | D8: 2.6526415 | E8: 0.079513141 | F8: 0 | G8: 4.0231409 | H8: 16.404213 | I8: 18.836871 | J8: 1.036763 | K8: 0.072148549 | L8: 1.8615094 | M8: 0 | N8: 15.441666 | O8: 0.04629407 | P8: 4.8733045 | Q8: 65.328065
B9: NI | C9: Gisborne Region | D9: 0.03361648 | E9: 0 | F9: 0 | G9: 0.24963516 | H9: 1.3037124 | I9: 1.0610033 | J9: 0.089820541 | K9: 0.00013996155 | L9: 0.025363381 | M9: 0.4074518 | N9: 0.75035922 | O9: 0.0037462948 | P9: 0.48418477 | Q9: 4.4090333
B10: NI | C10: Hawke's Bay Region | D10: 0.072715335 | E10: 0 | F10: 0 | G10: 0.77956338 | H10: 4.176743 | I10: 7.1955041 | J10: 0.24770723 | K10: 0.0027630291 | L10: 0.072958221 | M10: 1.9565645 | N10: 2.8167154 | O10: 0.012974162 | P10: 1.8602814 | Q10: 19.19449
B11: NI | C11: Manawatu-Wanganui Region | D11: 0.10916047 | E11: 0 | F11: 0 | G11: 1.7535831 | H11: 5.342402 | I11: 5.0873241 | J11: 0.25885927 | K11: 0 | L11: 0.21271586 | M11: 3.7049107 | N11: 4.6520994 | O11: 0.019109425 | P11: 1.7945471 | Q11: 22.934711
B12: SI | C12: Marlborough Region | D12: 0.062092936 | E12: 0 | F12: 0 | G12: 0.19982417 | H12: 1.976048 | I12: 1.3702089 | J12: 0.20108326 | K12: 0.0012872251 | L12: 0.046250881 | M12: 0 | N12: 0.82225439 | O12: 0.0037259555 | P12: 0.37086394 | Q12: 5.0536397
B13: SI | C13: Nelson Region | D13: 0.35519589 | E13: 0.01443299 | F13: 0 | G13: 0.17115603 | H13: 1.4389495 | I13: 2.2799314 | J13: 0.27337411 | K13: 0 | L13: 0.026859046 | M13: 0 | N13: 0.9061577 | O13: 0.0039852173 | P13: 0.63873611 | Q13: 6.108778
B14: NI | C14: Northland Region | D14: 0.057808582 | E14: 0 | F14: 0 | G14: 1.0708962 | H14: 3.8956292 | I14: 4.7860156 | J14: 0.26735772 | K14: 0.0060928919 | L14: 0.44892452 | M14: 6.2790527 | N14: 3.2058461 | O14: 0.01301793 | P14: 1.7913011 | Q14: 21.821943
B15: SI | C15: Otago Region | D15: 0.34279866 | E15: 0 | F15: 0 | G15: 1.0977015 | H15: 5.7433185 | I15: 4.935668 | J15: 0.33985624 | K15: 0.0051489002 | L15: 1.4892075 | M15: 0 | N15: 6.3539985 | O15: 0.017375949 | P15: 1.5058923 | Q15: 21.830966
B16: SI | C16: Southland Region | D16: 0.06792124 | E16: 0 | F16: 0 | G16: 1.3148228 | H16: 3.675672 | I16: 21.561643 | J16: 0.46876303 | K16: 0 | L16: 0.17159346 | M16: 0 | N16: 2.4737966 | O16: 0.0080103408 | P16: 1.014882 | Q16: 30.757104
B17: NI | C17: Taranaki Region | D17: 0.05206173 | E17: 0 | F17: 0 | G17: 2.1805581 | H17: 4.3243678 | I17: 3.2469849 | J17: 0.16234414 | K17: 0.00010754655 | L17: 0.060911662 | M17: 20.957884 | N17: 2.2789301 | O17: 0.0094065443 | P17: 0.95135167 | Q17: 34.224908
... B21: SI | C21: West Coast Region | D21: 0.022245431 | E21: 0 | F21: 0 | G21: 0.62618635 | H21: 1.9635327 | I21: 1.2607232 | J21: 0.13779825 | K21: 0.012311064 | L21: 0.014712835 | M21: 0 | N21: 0.76520285 | O21: 0.0027589372 | P21: 0.43574307 | Q21: 5.2412146
C22: Grand Total | D22: 11.958228 | E22: 0.33026164 | F22: 16.754295 | G22: 24.58967 | H22: 112.09078 | I22: 140.82561 | J22: 7.2693078 | K22: 9.8455428 | L22: 7.3393583 | M22: 60.585677 | N22: 106.42212 | O22: 0.364 | P22: 38.585738 | Q22: 536.96058
C26: Region | D26: Aviation Fuel/Kerosene | E26: Biogas | F26: Black Liquor | G26: Coal | H26: Diesel | I26: Electricity | J26: Fuel Oil | K26: Geothermal | L26: LPG | M26: Natural Gas | N26: Petrol | O26: Solar | P26: Wood
C27: NI | D27: =SUMIF($B$6:$B$21,$C$27,D6:D21) -> 8.4257065 | E27: =SUMIF($B$6:$B$21,$C$27,E6:E21) -> 0.23631551 | F27: =SUMIF($B$6:$B$21,$C$27,F6:F21) -> 16.754295 | G27: =SUMIF($B$6:$B$21,$C$27,G6:G21) -> 16.780356 | H27: =SUMIF($B$6:$B$21,$C$27,H6:H21) -> 78.813686 | I27: =SUMIF($B$6:$B$21,$C$27,I6:I21) -> 90.014367 | J27: =SUMIF($B$6:$B$21,$C$27,J6:J21) -> 4.5398035 | K27: =SUMIF($B$6:$B$21,$C$27,K6:K21) -> 9.754647 | ... Q27: =SUMIF($B$6:$B$21,$C$27,Q6:Q21) -> 397.51675
C28: SI | D28: =SUMIF($B$6:$B$21,$C$28,D6:D21) -> 3.5325217 | E28: =SUMIF($B$6:$B$21,$C$28,E6:E21) -> 0.093946131 | F28: =SUMIF($B$6:$B$21,$C$28,F6:F21) -> 0 | G28: =SUMIF($B$6:$B$21,$C$28,G6:G21) -> 7.8093141 | H28: =SUMIF($B$6:$B$21,$C$28,H6:H21) -> 33.277091 | I28: =SUMIF($B$6:$B$21,$C$28,I6:I21) -> 50.81124 | J28: =SUMIF($B$6:$B$21,$C$28,J6:J21) -> 2.7295043 | K28: =SUMIF($B$6:$B$21,$C$28,K6:K21) -> 0.090895738 | ... Q28: =SUMIF($B$6:$B$21,$C$28,Q6:Q21) -> 139.44383
C31: Complete New Zealand (TJ) | S31: Share of SI
C32: Sector ANZSIC 2006* | D32: Aviation Fuel/Kerosene | E32: Biogas | F32: Black Liquor | G32: Coal | H32: Diesel | I32: Electricity | J32: Fuel Oil | K32: Geothermal | L32: LPG | M32: Natural Gas | N32: Petrol | O32: Solar | P32: Wood | Q32: Grand Total | S32: Sector ANZSIC 2006* | T32: Aviation Fuel/Kerosene | U32: Biogas | V32: Black Liquor | W32: Coal | X32: Diesel | Y32: Electricity | Z32: Fuel Oil | AA32: Geothermal | AB32: LPG | AC32: Natural Gas | AD32: Petrol | AE32: Solar | AF32: Wood | AG32: Grand Total
C34: Agriculture | D34: 0 | E34: 7.348193 | F34: 0 | G34: 1680.8781 | H34: 22796.672 | I34: 9784.377 | J34: 2323.2179 | K34: 731.7896 | L34: 67.994451 | M34: 1631.7637 | N34: 3844.6756 | O34: 0 | P34: 0 | Q34: 42868.716 | S34: Agriculture
C35: Dairy Cattle Farming | E35: 7.348193 | H35: 5234.9647 | I35: 7091.2888 | N35: 2200.1873 | Q35: 14533.789 | T35: 0.5 | U35: 0.5 | V35: 0.5 | W35: 0.5 | X35: 0.5 | Y35: 0.5 | Z35: 0.5 | AA35: 0.5 | AB35: 0.5 | AC35: 0.5 | AD35: 0.5 | AE35: 0.5 | AF35: 0.5
C36: Fishing, Hunting and Trapping | H36: 2902.9716 | I36: 182.41272 | J36: 2323.2179 | N36: 203.55389 | Q36: 5612.1561 | T36: 0.5 | U36: 0.5 | V36: 0.5 | W36: 0.5 | X36: 0.5 | Y36: 0.5 | Z36: 0.5 | AA36: 0.5 | AB36: 0.5 | AC36: 0.5 | AD36: 0.5 | AE36: 0.5 | AF36: 0.5
C37: Forestry and Logging | G37: 0.64772262 | H37: 2864.0066 | I37: 641.45471 | M37: 0.009674 | N37: 74.529936 | Q37: 3580.6486 | T37: 0.5 | U37: 0.5 | V37: 0.5 | W37: 0.5 | X37: 0.5 | Y37: 0.5 | Z37: 0.5 | AA37: 0.5 | AB37: 0.5 | AC37: 0.5 | AD37: 0.5 | AE37: 0.5 | AF37: 0.5
C38: Indoor Cropping | G38: 1680.2303 | H38: 223.31057 | I38: 33.769723 | K38: 527.18544 | M38: 1631.754 | Q38: 4096.2501 | T38: 0.5 | U38: 0.5 | V38: 0.5 | W38: 0.5 | X38: 0.5 | Y38: 0.5 | Z38: 0.5 | AA38: 0.5 | AB38: 0.5 | AC38: 0.5 | AD38: 0.5 | AE38: 0.5 | AF38: 0.5
C39: Non-Dairy Agriculture | H39: 11571.418 | I39: 1835.4511 | K39: 204.60417 | L39: 67.994451 | N39: 1366.4044 | Q39: 15045.872 | T39: 0.5 | U39: 0.5 | V39: 0.5 | W39: 0.5 | X39: 0.5 | Y39: 0.5 | Z39: 0.5 | AA39: 0.5 | AB39: 0.5 | AC39: 0.5 | AD39: 0.5 | AE39: 0.5 | AF39: 0.5
C40: Commerce | D40: 0 | E40: 280 | F40: 0 | G40: 1128.7058 | H40: 18898.856 | I40: 33673.33 | J40: 4.6744072 | K40: 2251.7423 | L40: 1253.8726 | M40: 8714.2551 | N40: 17028.203 | O40: 0 | P40: 0 | Q40: 83233.639 | S40: Commerce
C41: Accommodation and Food Services | G41: 10.258235 | H41: 324.6865 | I41: 3038.8157 | J41: 0.62127059 | K41: 366.88619 | L41: 230.95187 | M41: 702.91834 | N41: 685.88207 | Q41: 5361.0202 | T41: 0.5 | U41: 0.5 | V41: 0.5 | W41: 0.5 | X41: 0.5 | Y41: 0.5 | Z41: 0.5 | AA41: 0.5 | AB41: 0.5 | AC41: 0.5 | AD41: 0.5 | AE41: 0.5 | AF41: 0.5
C42: Arts, Recreational and Other Services | G42: 36.67147 | H42: 1701.9264 | I42: 2091.2729 | J42: 0.16551393 | K42: 1695.7099 | M42: 343.71567 | N42: 1936.3635 | Q42: 7805.8253 | T42: 0.5 | U42: 0.5 | V42: 0.5 | W42: 0.5 | X42: 0.5 | Y42: 0.5 | Z42: 0.5 | AA42: 0.5 | AB42: 0.5 | AC42: 0.5 | AD42: 0.5 | AE42: 0.5 | AF42: 0.5
C43: Building Cleaning, Pest Control and Other Support Services | H43: 696.33884 | I43: 78.99173 | N43: 737.16655 | Q43: 1512.4971 | T43: 0.5 | U43: 0.5 | V43: 0.5 | W43: 0.5 | X43: 0.5 | Y43: 0.5 | Z43: 0.5 | AA43: 0.5 | AB43: 0.5 | AC43: 0.5 | AD43: 0.5 | AE43: 0.5 | AF43: 0.5
C44: Central Government Administration | G44: 7.6757246 | H44: 64.420543 | I44: 720.67252 | J44: 0.047366043 | M44: 202.11046 | N44: 103.83171 | Q44: 1098.7583 | T44: 0.5 | U44: 0.5 | V44: 0.5 | W44: 0.5 | X44: 0.5 | Y44: 0.5 | Z44: 0.5 | AA44: 0.5 | AB44: 0.5 | AC44: 0.5 | AD44: 0.5 | AE44: 0.5 | AF44: 0.5
C45: Defence | G45: 151.62888 | H45: 1149.7576 | I45: 389.61033 | J45: 2.5587471 | M45: 117.99222 | N45: 1095.7877 | Q45: 2907.3355 | T45: 0.5 | U45: 0.5 | V45: 0.5 | W45: 0.5 | X45: 0.5 | Y45: 0.5 | Z45: 0.5 | AA45: 0.5 | AB45: 0.5 | AC45: 0.5 | AD45: 0.5 | AE45: 0.5 | AF45: 0.5
C46: Education and Training: Pre-School, Primary and Secondary | G46: 17.697647 | H46: 248.19487 | I46: 1670.1537 | J46: 0.11637646 | K46: 27.079541 | M46: 1560.7124 | N46: 165.27072 | Q46: 3689.2252 | T46: 0.5 | U46: 0.5 | V46: 0.5 | W46: 0.5 | X46: 0.5 | Y46: 0.5 | Z46: 0.5 | AA46: 0.5 | AB46: 0.5 | AC46: 0.5 | AD46: 0.5 | AE46: 0.5 | AF46: 0.5
C47: Education and Training: Tertiary Education and Other Education | G47: 10.650218 | H47: 243.69131 | I47: 991.27629 | J47: 0.056303273 | K47: 9.2677689 | M47: 1031.7932 | N47: 390.34371 | Q47: 2677.0788 | T47: 0.5 | U47: 0.5 | V47: 0.5 | W47: 0.5 | X47: 0.5 | Y47: 0.5 | Z47: 0.5 | AA47: 0.5 | AB47: 0.5 | AC47: 0.5 | AD47: 0.5 | AE47: 0.5 | AF47: 0.5
C48: Financing, Insurance, Real Estate and Business Services | G48: 39.233887 | H48: 6683.2682 | I48: 6160.4346 | J48: 0.94776683 | K48: 73.687953 | M48: 718.02145 | N48: 6477.6683 | Q48: 20153.262 | T48: 0.5 | U48: 0.5 | V48: 0.5 | W48: 0.5 | X48: 0.5 | Y48: 0.5 | Z48: 0.5 | AA48: 0.5 | AB48: 0.5 | AC48: 0.5 | AD48: 0.5 | AE48: 0.5 | AF48: 0.5
C49: Health Care and Social Assistance | G49: 142.59675 | H49: 295.38329 | I49: 2305.1493 | J49: 0.070875605 | K49: 79.110938 | M49: 2534.6751 | N49: 555.03984 | Q49: 5912.0261 | T49: 0.5 | U49: 0.5 | V49: 0.5 | W49: 0.5 | X49: 0.5 | Y49: 0.5 | Z49: 0.5 | AA49: 0.5 | AB49: 0.5 | AC49: 0.5 | AD49: 0.5 | AE49: 0.5 | AF49: 0.5
C50: Information Media and Telecommunications | H50: 233.45872 | I50: 2618.0532 | L50: 11.057191 | M50: 3.1739903 | N50: 553.04556 | Q50: 3418.7887 | T50: 0.5 | U50: 0.5 | V50: 0.5 | W50: 0.5 | X50: 0.5 | Y50: 0.5 | Z50: 0.5 | AA50: 0.5 | AB50: 0.5 | AC50: 0.5 | AD50: 0.5 | AE50: 0.5 | AF50: 0.5
C51: Local Government Administration | E51: 280 | G51: 64.731089 | H51: 499.45274 | I51: 1023.2845 | M51: 260.55119 | N51: 479.9172 | Q51: 2607.9367 | T51: 0.5 | U51: 0.5 | V51: 0.5 | W51: 0.5 | X51: 0.5 | Y51: 0.5 | Z51: 0.5 | AA51: 0.5 | AB51: 0.5 | AC51: 0.5 | AD51: 0.5 | AE51: 0.5 | AF51: 0.5
C52: Public Administration and Safety | H52: 2200.2603 | N52: 17.592884 | Q52: 2217.8532 | T52: 0.5 | U52: 0.5 | V52: 0.5 | W52: 0.5 | X52: 0.5 | Y52: 0.5 | Z52: 0.5 | AA52: 0.5 | AB52: 0.5 | AC52: 0.5 | AD52: 0.5 | AE52: 0.5 | AF52: 0.5
C53: Retail Trade - Food | G53: 46.435697 | H53: 95.643447 | I53: 6128.4782 | J53: 0.011415224 | L53: 543.93402 | M53: 612.7016 | N53: 150.69836 | Q53: 7577.9028 | T53: 0.5 | U53: 0.5 | V53: 0.5 | W53: 0.5 | X53: 0.5 | Y53: 0.5 | Z53: 0.5 | AA53: 0.5 | AB53: 0.5 | AC53: 0.5 | AD53: 0.5 | AE53: 0.5 | AF53: 0.5
C54: Transport, Postal and Warehousing (Commercial - Non-Transport) | I54: 2434.6134 | Q54: 2434.6134 | T54: 0.5 | U54: 0.5 | V54: 0.5 | W54: 0.5 | X54: 0.5 | Y54: 0.5 | Z54: 0.5 | AA54: 0.5 | AB54: 0.5 | AC54: 0.5 | AD54: 0.5 | AE54: 0.5 | AF54: 0.5
C55: Wholesale and Retail Trade - Non Food | G55: 596.42137 | H55: 2911.2881 | I55: 3489.6968 | J55: 0.070796869 | L55: 465.42668 | M55: 601.40494 | N55: 3258.049 | Q55: 11322.358 | T55: 0.5 | U55: 0.5 | V55: 0.5 | W55: 0.5 | X55: 0.5 | Y55: 0.5 | Z55: 0.5 | AA55: 0.5 | AB55: 0.5 | AC55: 0.5 | AD55: 0.5 | AE55: 0.5 | AF55: 0.5
C56: Wholesale Trade - Food | G56: 4.7048569 | H56: 1551.0847 | I56: 532.82634 | J56: 0.0079752585 | L56: 2.5028743 | M56: 24.484687 | N56: 421.54626 | Q56: 2537.1577 | T56: 0.5 | U56: 0.5 | V56: 0.5 | W56: 0.5 | X56: 0.5 | Y56: 0.5 | Z56: 0.5 | AA56: 0.5 | AB56: 0.5 | AC56: 0.5 | AD56: 0.5 | AE56: 0.5 | AF56: 0.5
C57: Household | D57: 0 | E57: 0 | F57: 0 | G57: 367.2801 | H57: 14747.316 | I57: 44547.14 | J57: 0 | K57: 296.63123 | L57: 2857.4143 | M57: 6557.3777 | N57: 76810.804 | O57: 364 | P57: 7336.6436 | Q57: 153884.61 | S57: Household
C58: Household | G58: 367.2801 | H58: 100.90842 | I58: 44547.14 | K58: 296.63123 | L58: 2857.4143 | M58: 6557.1375 | O58: 364 | P58: 7336.6436 | Q58: 62427.155 | T58: 0.5 | U58: 0.5 | V58: 0.5 | W58: 0.5 | X58: 0.5 | Y58: 0.5 | Z58: 0.5 | AA58: 0.5 | AB58: 0.5 | AC58: 0.5 | AD58: 0.5 | AE58: 0.5 | AF58: 0.5
C59: Household (Private Transport) | H59: 14646.408 | M59: 0.24023969 | N59: 76810.804 | Q59: 91457.452 | T59: 0.5 | U59: 0.5 | V59: 0.5 | W59: 0.5 | X59: 0.5 | Y59: 0.5 | Z59: 0.5 | AA59: 0.5 | AB59: 0.5 | AC59: 0.5 | AD59: 0.5 | AE59: 0.5 | AF59: 0.5
C60: Industry | D60: 0 | E60: 42.913447 | F60: 17736.792 | G60: 23760.875 | H60: 34893.828 | I60: 52927.823 | J60: 954.61206 | K60: 8380.8674 | L60: 3035.2435 | M60: 68035.988 | N60: 7650.9502 | O60: 0 | P60: 28147.186 | Q60: 245567.08 | S60: Industry
C61: Construction | G61: 0.15265043 | H61: 17156.221 | I61: 1256.1188 | J61: 22.656352 | L61: 246.6635 | M61: 445.82558 | N61: 5184.3768 | Q61: 24312.015 | T61: 0.5 | U61: 0.5 | V61: 0.5 | W61: 0.5 | X61: 0.5 | Y61: 0.5 | Z61: 0.5 | AA61: 0.5 | AB61: 0.5 | AC61: 0.5 | AD61: 0.5 | AE61: 0.5 | AF61: 0.5
C62: Dairy Product Manufacturing | E62: 42.913447 | G62: 13319.402 | H62: 2257.2545 | I62: 4769.4361 | J62: 15.818533 | K62: 448.2837 | L62: 35.320053 | M62: 10219.245 | N62: 70.457125 | Q62: 31178.131 | T62: 0.5 | U62: 0.5 | V62: 0.5 | W62: 0.5 | X62: 0.5 | Y62: 0.5 | Z62: 0.5 | AA62: 0.5 | AB62: 0.5 | AC62: 0.5 | AD62: 0.5 | AE62: 0.5 | AF62: 0.5
C63: Electricity, Gas, Water and Waste Services | H63: 2926.069 | I63: 1434.6631 | K63: 0.058705241 | N63: 151.82786 | Q63: 4512.6186 | T63: 0.5 | U63: 0.5 | V63: 0.5 | W63: 0.5 | X63: 0.5 | Y63: 0.5 | Z63: 0.5 | AA63: 0.5 | AB63: 0.5 | AC63: 0.5 | AD63: 0.5 | AE63: 0.5 | AF63: 0.5
C64: Fabricated Metal Product, Transport Equipment, Machinery and Equipment Manufacturing | G64: 5.095418 | H64: 665.08073 | I64: 563.26015 | J64: 90.322642 | L64: 382.35292 | M64: 729.61378 | N64: 400.45547 | Q64: 2836.1811 | T64: 0.5 | U64: 0.5 | V64: 0.5 | W64: 0.5 | X64: 0.5 | Y64: 0.5 | Z64: 0.5 | AA64: 0.5 | AB64: 0.5 | AC64: 0.5 | AD64: 0.5 | AE64: 0.5 | AF64: 0.5
C65: Furniture and Other Manufacturing | H65: 31.509776 | I65: 976.24546 | N65: 84.969638 | Q65: 1092.7249 | T65: 0.5 | U65: 0.5 | V65: 0.5 | W65: 0.5 | X65: 0.5 | Y65: 0.5 | Z65: 0.5 | AA65: 0.5 | AB65: 0.5 | AC65: 0.5 | AD65: 0.5 | AE65: 0.5 | AF65: 0.5
C66: Furniture and Other Manufacturing and Electricity, Gas, Water and Waste Services | G66: 1870.5141 | J66: 0.39331521 | L66: 5.4700293 | M66: 168.87487 | Q66: 2045.2523 | T66: 0.5 | U66: 0.5 | V66: 0.5 | W66: 0.5 | X66: 0.5 | Y66: 0.5 | Z66: 0.5 | AA66: 0.5 | AB66: 0.5 | AC66: 0.5 | AD66: 0.5 | AE66: 0.5 | AF66: 0.5
C67: Meat and Meat Product Manufacturing and Seafood | G67: 2080.0751 | H67: 192.46495 | I67: 2344.9586 | J67: 5.4644768 | L67: 377.27563 | M67: 3150.6548 | N67: 3.5415875 | Q67: 8154.4352 | T67: 0.5 | U67: 0.5 | V67: 0.5 | W67: 0.5 | X67: 0.5 | Y67: 0.5 | Z67: 0.5 | AA67: 0.5 | AB67: 0.5 | AC67: 0.5 | AD67: 0.5 | AE67: 0.5 | AF67: 0.5
C68: Mining | H68: 3734.9844 | I68: 1611.7718 | M68: 56.964526 | N68: 53.688798 | Q68: 5457.4095 | T68: 0.5 | U68: 0.5 | V68: 0.5 | W68: 0.5 | X68: 0.5 | Y68: 0.5 | Z68: 0.5 | AA68: 0.5 | AB68: 0.5 | AC68: 0.5 | AD68: 0.5 | AE68: 0.5 | AF68: 0.5
C69: Non-Metallic Mineral Product Manufacturing | G69: 4994.0869 | H69: 2171.4505 | I69: 1448.9132 | J69: 37.285824 | L69: 607.04446 | M69: 1665.0003 | N69: 38.336745 | P69: 255.74764 | Q69: 11217.866 | T69: 0.5 | U69: 0.5 | V69: 0.5 | W69: 0.5 | X69: 0.5 | Y69: 0.5 | Z69: 0.5 | AA69: 0.5 | AB69: 0.5 | AC69: 0.5 | AD69: 0.5 | AE69: 0.5 | AF69: 0.5
C70: Other Food Product Manufacturing | G70: 807.70766 | H70: 2571.6385 | I70: 2284.307 | J70: 27.090733 | K70: 17.9224 | L70: 427.74082 | M70: 2474.0853 | N70: 472.85716 | Q70: 9083.3495 | T70: 0.5 | U70: 0.5 | V70: 0.5 | W70: 0.5 | X70: 0.5 | Y70: 0.5 | Z70: 0.5 | AA70: 0.5 | AB70: 0.5 | AC70: 0.5 | AD70: 0.5 | AE70: 0.5 | AF70: 0.5
C71: Petroleum, Basic Chemical and Rubber Product Manufacturing | G71: 2.8542977 | H71: 1167.8493 | I71: 2664.1924 | J71: 151.70308 | L71: 123.56563 | M71: 40003.485 | N71: 726.05937 | Q71: 44839.709 | T71: 0.5 | U71: 0.5 | V71: 0.5 | W71: 0.5 | X71: 0.5 | Y71: 0.5 | Z71: 0.5 | AA71: 0.5 | AB71: 0.5 | AC71: 0.5 | AD71: 0.5 | AE71: 0.5 | AF71: 0.5
C72: Primary Metal and Metal Product Manufacturing | H72: 500.17713 | I72: 23722.804 | J72: 354.50914 | L72: 151.46238 | M72: 3440.0338 | N72: 27.336784 | Q72: 28196.323 | T72: 0.5 | U72: 0.5 | V72: 0.5 | W72: 0.5 | X72: 0.5 | Y72: 0.5 | Z72: 0.5 | AA72: 0.5 | AB72: 0.5 | AC72: 0.5 | AD72: 0.5 | AE72: 0.5 | AF72: 0.5
C73: Printing | H73: 19.234005 | I73: 213.18061 | J73: 0.091348143 | M73: 83.235369 | N73: 84.851155 | Q73: 400.59248 | T73: 0.5 | U73: 0.5 | V73: 0.5 | W73: 0.5 | X73: 0.5 | Y73: 0.5 | Z73: 0.5 | AA73: 0.5 | AB73: 0.5 | AC73: 0.5 | AD73: 0.5 | AE73: 0.5 | AF73: 0.5
C74: Pulp, Paper and Converted Paper Product Manufacturing | F74: 17736.792 | H74: 150.82502 | I74: 4371.1034 | J74: 119.67294 | K74: 6965.8927 | M74: 3593.8098 | N74: 22.299272 | P74: 8223.8498 | Q74: 41184.245 | T74: 0.5 | U74: 0.5 | V74: 0.5 | W74: 0.5 | X74: 0.5 | Y74: 0.5 | Z74: 0.5 | AA74: 0.5 | AB74: 0.5 | AC74: 0.5 | AD74: 0.5 | AE74: 0.5 | AF74: 0.5
C75: Textile, Leather, Clothing and Footwear Manufacturing | G75: 69.047231 | H75: 92.903962 | I75: 369.82862 | J75: 54.853192 | L75: 16.114386 | M75: 557.56304 | N75: 34.790297 | Q75: 1195.1007 | T75: 0.5 | U75: 0.5 | V75: 0.5 | W75: 0.5 | X75: 0.5 | Y75: 0.5 | Z75: 0.5 | AA75: 0.5 | AB75: 0.5 | AC75: 0.5 | AD75: 0.5 | AE75: 0.5 | AF75: 0.5
C76: Wood Product Manufacturing | G76: 611.93932 | H76: 1256.1647 | I76: 4897.0399 | J76: 74.750484 | K76: 948.70989 | L76: 662.23367 | M76: 1447.5965 | N76: 295.10212 | P76: 19667.588 | Q76: 29861.125 | T76: 0.5 | U76: 0.5 | V76: 0.5 | W76: 0.5 | X76: 0.5 | Y76: 0.5 | Z76: 0.5 | AA76: 0.5 | AB76: 0.5 | AC76: 0.5 | AD76: 0.5 | AE76: 0.5 | AF76: 0.5
C77: Transport | D77: 12384.126 | E77: 0 | F77: 0 | G77: 15.434666 | H77: 28994.37 | I77: 298.2986 | J77: 4337.8989 | K77: 0 | L77: 309.33453 | M77: 4.261184 | N77: 883.91431 | O77: 0 | P77: 0 | Q77: 47227.638 | S77: Transport
C78: Transport, Postal and Warehousing** | D78: 12384.126 | G78: 15.434666 | H78: 28994.37 | I78: 298.2986 | J78: 4337.8989 | L78: 309.33453 | M78: 4.261184 | N78: 883.91431 | Q78: 47227.638 | T78: 0.5 | U78: 0.5 | V78: 0.5 | W78: 0.5 | X78: 0.5 | Y78: 0.5 | Z78: 0.5 | AA78: 0.5 | AB78: 0.5 | AC78: 0.5 | AD78: 0.5 | AE78: 0.5 | AF78: 0.5
C80: Grand Total | D80: 12384.126 | E80: 330.26164 | F80: 17736.792 | G80: 26953.173 | H80: 120331.04 | I80: 141230.97 | J80: 7620.4033 | K80: 11661.031 | L80: 7523.8594 | M80: 84943.646 | N80: 106218.55 | O80: 364 | P80: 35483.829 | Q80: 572781.68
C83: Demand of SI (PJ) | F83: Assume: Bioliquid | G83: Assume: Sum of all coals
C84: Sector ANZSIC 2006* | D84: Aviation Fuel/Kerosene | E84: Biogas | F84: Black Liquor | G84: Coal | H84: Diesel | I84: Electricity | J84: Fuel Oil | K84: Geothermal | L84: LPG | M84: Natural Gas | N84: Petrol | O84: Solar | P84: Wood | Q84: Grand Total
C86: Agriculture | D86: =SUM(D87:D91) -> 0 | E86: =SUM(E87:E91) -> 0.0036740965 | F86: =SUM(F87:F91) -> 0 | G86: =SUM(G87:G91) -> 0.84043903 | H86: =SUM(H87:H91) -> 11.398336 | I86: =SUM(I87:I91) -> 4.8921885 | J86: =SUM(J87:J91) -> 1.161609 | K86: =SUM(K87:K91) -> 0.3658948 | ... Q86: =SUM(Q87:Q91) -> 21.434358
C87: Dairy Cattle Farming | D87: =D35*T35/1000 -> 0 | E87: =E35*U35/1000 -> 0.0036740965 | F87: =F35*V35/1000 -> 0 | G87: =G35*W35/1000 -> 0 | H87: =H35*X35/1000 -> 2.6174824 | I87: =I35*Y35/1000 -> 3.5456444 | J87: =J35*Z35/1000 -> 0 | K87: =K35*AA35/1000 -> 0 | ... P87: =P35*AF35/1000 -> 0 | Q87: =SUM(D87:P87) -> 7.2668945
C88: Fishing, Hunting and Trapping | D88: =D36*T36/1000 -> 0 | E88: =E36*U36/1000 -> 0 | F88: =F36*V36/1000 -> 0 | G88: =G36*W36/1000 -> 0 | H88: =H36*X36/1000 -> 1.4514858 | I88: =I36*Y36/1000 -> 0.091206359 | J88: =J36*Z36/1000 -> 1.161609 | K88: =K36*AA36/1000 -> 0 | ... P88: =P36*AF36/1000 -> 0 | Q88: =SUM(D88:P88) -> 2.806078
C89: Forestry and Logging | D89: =D37*T37/1000 -> 0 | E89: =E37*U37/1000 -> 0 | F89: =F37*V37/1000 -> 0 | G89: =G37*W37/1000 -> 0.00032386131 | H89: =H37*X37/1000 -> 1.4320033 | I89: =I37*Y37/1000 -> 0.32072736 | J89: =J37*Z37/1000 -> 0 | K89: =K37*AA37/1000 -> 0 | ... P89: =P37*AF37/1000 -> 0 | Q89: =SUM(D89:P89) -> 1.7903243
C90: Indoor Cropping | D90: =D38*T38/1000 -> 0 | E90: =E38*U38/1000 -> 0 | F90: =F38*V38/1000 -> 0 | G90: =G38*W38/1000 -> 0.84011517 | H90: =H38*X38/1000 -> 0.11165528 | I90: =I38*Y38/1000 -> 0.016884862 | J90: =J38*Z38/1000 -> 0 | K90: =K38*AA38/1000 -> 0.26359272 | ... P90: =P38*AF38/1000 -> 0 | Q90: =SUM(D90:P90) -> 2.048125
C91: Non-Dairy Agriculture | D91: =D39*T39/1000 -> 0 | E91: =E39*U39/1000 -> 0 | F91: =F39*V39/1000 -> 0 | G91: =G39*W39/1000 -> 0 | H91: =H39*X39/1000 -> 5.7857091 | I91: =I39*Y39/1000 -> 0.91772553 | J91: =J39*Z39/1000 -> 0 | K91: =K39*AA39/1000 -> 0.10230208 | ... P91: =P39*AF39/1000 -> 0 | Q91: =SUM(D91:P91) -> 7.5229362
C92: Commerce | D92: =SUM(D93:D108) -> 0 | E92: =SUM(E93:E108) -> 0.14 | F92: =SUM(F93:F108) -> 0 | G92: =SUM(G93:G108) -> 0.56435291 | H92: =SUM(H93:H108) -> 9.4494278 | I92: =SUM(I93:I108) -> 16.836665 | J92: =SUM(J93:J108) -> 0.0023372036 | K92: =SUM(K93:K108) -> 1.1258711 | ... Q92: =SUM(Q93:Q108) -> 41.616819
C93: Accommodation and Food Services | D93: =D41*T41/1000 -> 0 | E93: =E41*U41/1000 -> 0 | F93: =F41*V41/1000 -> 0 | G93: =G41*W41/1000 -> 0.0051291177 | H93: =H41*X41/1000 -> 0.16234325 | I93: =I41*Y41/1000 -> 1.5194079 | J93: =J41*Z41/1000 -> 0.0003106353 | K93: =K41*AA41/1000 -> 0.1834431 | ... P93: =P41*AF41/1000 -> 0 | Q93: =SUM(D93:P93) -> 2.6805101
C94: Arts, Recreational and Other Services | D94: =D42*T42/1000 -> 0 | E94: =E42*U42/1000 -> 0 | F94: =F42*V42/1000 -> 0 | G94: =G42*W42/1000 -> 0.018335735 | H94: =H42*X42/1000 -> 0.85096319 | I94: =I42*Y42/1000 -> 1.0456365 | J94: =J42*Z42/1000 -> 8.2756965e-05 | K94: =K42*AA42/1000 -> 0.84785495 | ... P94: =P42*AF42/1000 -> 0 | Q94: =SUM(D94:P94) -> 3.9029127
C95: Building Cleaning, Pest Control and Other Support Services | D95: =D43*T43/1000 -> 0 | E95: =E43*U43/1000 -> 0 | F95: =F43*V43/1000 -> 0 | G95: =G43*W43/1000 -> 0 | H95: =H43*X43/1000 -> 0.34816942 | I95: =I43*Y43/1000 -> 0.039495865 | J95: =J43*Z43/1000 -> 0 | K95: =K43*AA43/1000 -> 0 | ... P95: =P43*AF43/1000 -> 0 | Q95: =SUM(D95:P95) -> 0.75624856
C96: Central Government Administration | D96: =D44*T44/1000 -> 0 | E96: =E44*U44/1000 -> 0 | F96: =F44*V44/1000 -> 0 | G96: =G44*W44/1000 -> 0.0038378623 | H96: =H44*X44/1000 -> 0.032210271 | I96: =I44*Y44/1000 -> 0.36033626 | J96: =J44*Z44/1000 -> 2.3683021e-05 | K96: =K44*AA44/1000 -> 0 | ... P96: =P44*AF44/1000 -> 0 | Q96: =SUM(D96:P96) -> 0.54937916
C97: Defence | D97: =D45*T45/1000 -> 0 | E97: =E45*U45/1000 -> 0 | F97: =F45*V45/1000 -> 0 | G97: =G45*W45/1000 -> 0.075814442 | H97: =H45*X45/1000 -> 0.57487881 | I97: =I45*Y45/1000 -> 0.19480516 | J97: =J45*Z45/1000 -> 0.0012793736 | K97: =K45*AA45/1000 -> 0 | ... P97: =P45*AF45/1000 -> 0 | Q97: =SUM(D97:P97) -> 1.4536677
C98: Education and Training: Pre-School, Primary and Secondary | D98: =D46*T46/1000 -> 0 | E98: =E46*U46/1000 -> 0 | F98: =F46*V46/1000 -> 0 | G98: =G46*W46/1000 -> 0.0088488233 | H98: =H46*X46/1000 -> 0.12409743 | I98: =I46*Y46/1000 -> 0.83507687 | J98: =J46*Z46/1000 -> 5.818823e-05 | K98: =K46*AA46/1000 -> 0.01353977 | ... P98: =P46*AF46/1000 -> 0 | Q98: =SUM(D98:P98) -> 1.8446126
C99: Education and Training: Tertiary Education and Other Education | D99: =D47*T47/1000 -> 0 | E99: =E47*U47/1000 -> 0 | F99: =F47*V47/1000 -> 0 | G99: =G47*W47/1000 -> 0.0053251091 | H99: =H47*X47/1000 -> 0.12184565 | I99: =I47*Y47/1000 -> 0.49563815 | J99: =J47*Z47/1000 -> 2.8151636e-05 | K99: =K47*AA47/1000 -> 0.0046338845 | ... P99: =P47*AF47/1000 -> 0 | Q99: =SUM(D99:P99) -> 1.3385394
C100: Financing, Insurance, Real Estate and Business Services | D100: =D48*T48/1000 -> 0 | E100: =E48*U48/1000 -> 0 | F100: =F48*V48/1000 -> 0 | G100: =G48*W48/1000 -> 0.019616944 | H100: =H48*X48/1000 -> 3.3416341 | I100: =I48*Y48/1000 -> 3.0802173 | J100: =J48*Z48/1000 -> 0.00047388342 | K100: =K48*AA48/1000 -> 0.036843977 | ... P100: =P48*AF48/1000 -> 0 | Q100: =SUM(D100:P100) -> 10.076631
C101: Health Care and Social Assistance | D101: =D49*T49/1000 -> 0 | E101: =E49*U49/1000 -> 0 | F101: =F49*V49/1000 -> 0 | G101: =G49*W49/1000 -> 0.071298374 | H101: =H49*X49/1000 -> 0.14769165 | I101: =I49*Y49/1000 -> 1.1525746 | J101: =J49*Z49/1000 -> 3.5437803e-05 | K101: =K49*AA49/1000 -> 0.039555469 | ... P101: =P49*AF49/1000 -> 0 | Q101: =SUM(D101:P101) -> 2.956013
C102: Information Media and Telecommunications | D102: =D50*T50/1000 -> 0 | E102: =E50*U50/1000 -> 0 | F102: =F50*V50/1000 -> 0 | G102: =G50*W50/1000 -> 0 | H102: =H50*X50/1000 -> 0.11672936 | I102: =I50*Y50/1000 -> 1.3090266 | J102: =J50*Z50/1000 -> 0 | K102: =K50*AA50/1000 -> 0 | ... P102: =P50*AF50/1000 -> 0 | Q102: =SUM(D102:P102) -> 1.7093943
C103: Local Government Administration | D103: =D51*T51/1000 -> 0 | E103: =E51*U51/1000 -> 0.14 | F103: =F51*V51/1000 -> 0 | G103: =G51*W51/1000 -> 0.032365545 | H103: =H51*X51/1000 -> 0.24972637 | I103: =I51*Y51/1000 -> 0.51164226 | J103: =J51*Z51/1000 -> 0 | K103: =K51*AA51/1000 -> 0 | ... P103: =P51*AF51/1000 -> 0 | Q103: =SUM(D103:P103) -> 1.3039684
C104: Public Administration and Safety | D104: =D52*T52/1000 -> 0 | E104: =E52*U52/1000 -> 0 | F104: =F52*V52/1000 -> 0 | G104: =G52*W52/1000 -> 0 | H104: =H52*X52/1000 -> 1.1001301 | I104: =I52*Y52/1000 -> 0 | J104: =J52*Z52/1000 -> 0 | K104: =K52*AA52/1000 -> 0 | ... P104: =P52*AF52/1000 -> 0 | Q104: =SUM(D104:P104) -> 1.1089266
... C108: Wholesale Trade - Food | D108: =D56*T56/1000 -> 0 | E108: =E56*U56/1000 -> 0 | F108: =F56*V56/1000 -> 0 | G108: =G56*W56/1000 -> 0.0023524285 | H108: =H56*X56/1000 -> 0.77554236 | I108: =I56*Y56/1000 -> 0.26641317 | J108: =J56*Z56/1000 -> 3.9876293e-06 | K108: =K56*AA56/1000 -> 0 | ... P108: =P56*AF56/1000 -> 0 | Q108: =SUM(D108:P108) -> 1.2685789
C109: Household | D109: =SUM(D110:D111) -> 0 | E109: =SUM(E110:E111) -> 0 | F109: =SUM(F110:F111) -> 0 | G109: =SUM(G110:G111) -> 0.18364005 | H109: =SUM(H110:H111) -> 7.3736581 | I109: =SUM(I110:I111) -> 22.27357 | J109: =SUM(J110:J111) -> 0 | K109: =SUM(K110:K111) -> 0.14831562 | ... Q109: =SUM(Q110:Q111) -> 76.942304
C110: Household | D110: =D58*T58/1000 -> 0 | E110: =E58*U58/1000 -> 0 | F110: =F58*V58/1000 -> 0 | G110: =G58*W58/1000 -> 0.18364005 | H110: =H58*X58/1000 -> 0.050454211 | I110: =I58*Y58/1000 -> 22.27357 | J110: =J58*Z58/1000 -> 0 | K110: =K58*AA58/1000 -> 0.14831562 | ... P110: =P58*AF58/1000 -> 3.6683218 | Q110: =SUM(D110:P110) -> 31.213577
C111: Household (Private Transport) | D111: =D59*T59/1000 -> 0 | E111: =E59*U59/1000 -> 0 | F111: =F59*V59/1000 -> 0 | G111: =G59*W59/1000 -> 0 | H111: =H59*X59/1000 -> 7.3232039 | I111: =I59*Y59/1000 -> 0 | J111: =J59*Z59/1000 -> 0 | K111: =K59*AA59/1000 -> 0 | ... P111: =P59*AF59/1000 -> 0 | Q111: =SUM(D111:P111) -> 45.728726
C112: Industry | D112: =SUM(D113:D128) -> 0 | E112: =SUM(E113:E128) -> 0.021456724 | F112: =SUM(F113:F128) -> 8.8683962 | G112: =SUM(G113:G128) -> 11.880437 | H112: =SUM(H113:H128) -> 17.446914 | I112: =SUM(I113:I128) -> 26.463912 | J112: =SUM(J113:J128) -> 0.47730603 | K112: =SUM(K113:K128) -> 4.1904337 | ... Q112: =SUM(Q113:Q128) -> 122.78354
C113: Construction | D113: =D61*T61/1000 -> 0 | E113: =E61*U61/1000 -> 0 | F113: =F61*V61/1000 -> 0 | G113: =G61*W61/1000 -> 7.6325214e-05 | H113: =H61*X61/1000 -> 8.5781106 | I113: =I61*Y61/1000 -> 0.62805939 | J113: =J61*Z61/1000 -> 0.011328176 | K113: =K61*AA61/1000 -> 0 | ... P113: =P61*AF61/1000 -> 0 | Q113: =SUM(D113:P113) -> 12.156007
C114: Dairy Product Manufacturing | D114: =D62*T62/1000 -> 0 | E114: =E62*U62/1000 -> 0.021456724 | F114: =F62*V62/1000 -> 0 | G114: =G62*W62/1000 -> 6.659701 | H114: =H62*X62/1000 -> 1.1286272 | I114: =I62*Y62/1000 -> 2.384718 | J114: =J62*Z62/1000 -> 0.0079092663 | K114: =K62*AA62/1000 -> 0.22414185 | ... P114: =P62*AF62/1000 -> 0 | Q114: =SUM(D114:P114) -> 15.589065
C115: Electricity, Gas, Water and Waste Services | D115: =D63*T63/1000 -> 0 | E115: =E63*U63/1000 -> 0 | F115: =F63*V63/1000 -> 0 | G115: =G63*W63/1000 -> 0 | H115: =H63*X63/1000 -> 1.4630345 | I115: =I63*Y63/1000 -> 0.71733155 | J115: =J63*Z63/1000 -> 0 | K115: =K63*AA63/1000 -> 2.9352621e-05 | ... P115: =P63*AF63/1000 -> 0 | Q115: =SUM(D115:P115) -> 2.2563093
C116: Fabricated Metal Product, Transport Equipment, Machinery and Equipment Manufacturing | D116: =D64*T64/1000 -> 0 | E116: =E64*U64/1000 -> 0 | F116: =F64*V64/1000 -> 0 | G116: =G64*W64/1000 -> 0.002547709 | H116: =H64*X64/1000 -> 0.33254036 | I116: =I64*Y64/1000 -> 0.28163008 | J116: =J64*Z64/1000 -> 0.045161321 | K116: =K64*AA64/1000 -> 0 | ... P116: =P64*AF64/1000 -> 0 | Q116: =SUM(D116:P116) -> 1.4180906
C117: Furniture and Other Manufacturing | D117: =D65*T65/1000 -> 0 | E117: =E65*U65/1000 -> 0 | F117: =F65*V65/1000 -> 0 | G117: =G65*W65/1000 -> 0 | H117: =H65*X65/1000 -> 0.015754888 | I117: =I65*Y65/1000 -> 0.48812273 | J117: =J65*Z65/1000 -> 0 | K117: =K65*AA65/1000 -> 0 | ... P117: =P65*AF65/1000 -> 0 | Q117: =SUM(D117:P117) -> 0.54636244
C118: Furniture and Other Manufacturing and Electricity, Gas, Water and Waste Services | D118: =D66*T66/1000 -> 0 | E118: =E66*U66/1000 -> 0 | F118: =F66*V66/1000 -> 0 | G118: =G66*W66/1000 -> 0.93525703 | H118: =H66*X66/1000 -> 0 | I118: =I66*Y66/1000 -> 0 | J118: =J66*Z66/1000 -> 0.00019665761 | K118: =K66*AA66/1000 -> 0 | ... P118: =P66*AF66/1000 -> 0 | Q118: =SUM(D118:P118) -> 1.0226261
C119: Meat and Meat Product Manufacturing and Seafood | D119: =D67*T67/1000 -> 0 | E119: =E67*U67/1000 -> 0 | F119: =F67*V67/1000 -> 0 | G119: =G67*W67/1000 -> 1.0400376 | H119: =H67*X67/1000 -> 0.096232477 | I119: =I67*Y67/1000 -> 1.1724793 | J119: =J67*Z67/1000 -> 0.0027322384 | K119: =K67*AA67/1000 -> 0 | ... P119: =P67*AF67/1000 -> 0 | Q119: =SUM(D119:P119) -> 4.0772176
...

Sheet PROC_COM_AGR
B4: ~FI_Comm | Q4: ~FI_Process
B5: Csets | C5: Region | D5: CommName | E5: * Fuel | F5: * Enduse | G5: CommDesc | H5: * OLD CommDesc | I5: Unit | J5: LimType | K5: CTSLvl | L5: PeakTS | M5: Ctype | Q5: Sets | R5: Region | S5: TechName | T5: * Sector | U5: * Subsector | V5: * Technology | W5: * Fuel | X5: TechDesc | Y5: * OLD TechDesc | Z5: Tact | AA5: Tcap | AB5: Tslvl | AC5: PrimaryCG | AD5: Vintage
B6: *Commodity Set Membership | C6: Region Name | D6: Commodity Name | H6: Commodity Description | I6: Unit | J6: Sense of the Balance EQN. | K6: Timeslice Level | L6: Peak Monitoring | M6: Electricity Indicator | Q6: *Process Set Membership | R6: Region Name | S6: Technology Name | Y6: Technology Description | Z6: Activity Unit | AA6: Capacity Unit | AB6: TimeSlice level of Process Activity | AC6: Primary Commodity Group | AD6: Vintage Tracking
B7: DEM | D7: ADCF-MoTP-Stat | F7: Milking Machine | G7: =_xlfn.CONCAT(E7, " -:- ", F7) -> -:- Milking Machine | H7: Dairy Cattle Farming Motive Power, Stationary | I7: PJ | Q7: *
B8: DEM | D8: ADCF-IRG | F8: Irrigation | G8: =_xlfn.CONCAT(E8, " -:- ", F8) -> -:- Irrigation | H8: Dairy Cattle Farming Irrigation | I8: PJ | Q8: DMD | S8: ADCF-MoTP-Stat-VacP_ELC00 | T8: Agriculture | U8: Dairy Cattle Farming | V8: Vacuum Pump | W8: Electricity | X8: =_xlfn.CONCAT( T8, " -:- ", U8, " -:- ", V8, " -:- ", W8) -> Agriculture -:- Dairy Cattle Farming -:- Vacuum Pump -:- Electricity | Y8: Dairy Cattle Farming-Vacuum Pump | Z8: PJ | AA8: GW
B9: DEM | D9: ADCF-WH | F9: Water Heating | G9: =_xlfn.CONCAT(E9, " -:- ", F9) -> -:- Water Heating | H9: Dairy Cattle Farming Low Temperature Heat (<100 C), Water Heating | I9: PJ | Q9: DMD | S9: ADCF-MoTP-Stat-VPVSD_ELC00 | T9: Agriculture | U9: Dairy Cattle Farming | V9: Vacuum Pump with VSD | W9: Electricity | X9: =_xlfn.CONCAT( T9, " -:- ", U9, " -:- ", V9, " -:- ", W9) -> Agriculture -:- Dairy Cattle Farming -:- Vacuum Pump with VSD -:- Electricity | Y9: Dairy Cattle Farming-Vacuum pump with VSD | Z9: PJ | AA9: GW
B10: DEM | D10: ADCF-MoTP-Mob-Trac | F10: Tractor Services | G10: =_xlfn.CONCAT(E10, " -:- ", F10) -> -:- Tractor Services | H10: Dairy Cattle Farming Motive Power, Mobile | I10: PJ | Q10: DMD | S10: ADCF-IRG-Irg_ELC00 | T10: Agriculture | U10: Dairy Cattle Farming | V10: Irrigator | W10: Electricity | X10: =_xlfn.CONCAT( T10, " -:- ", U10, " -:- ", V10, " -:- ", W10) -> Agriculture -:- Dairy Cattle Farming -:- Irrigator -:- Electricity | Y10: Dairy Cattle Farming-Irrigation | Z10: PJ | AA10: GW
B11: DEM | D11: ADCF-MoTP-Mob-MTr | F11: Truck Services | G11: =_xlfn.CONCAT(E11, " -:- ", F11) -> -:- Truck Services | H11: Dairy Cattle Farming Motive Power, Mobile | I11: PJ | Q11: DMD | S11: ADCF-IRG-IrgVSD_ELC00 | T11: Agriculture | U11: Dairy Cattle Farming | V11: Irrigator with VSD | W11: Electricity | X11: =_xlfn.CONCAT( T11, " -:- ", U11, " -:- ", V11, " -:- ", W11) -> Agriculture -:- Dairy Cattle Farming -:- Irrigator with VSD -:- Electricity | Y11: Dairy Cattle Farming-Irrigation with VSD | Z11: PJ | AA11: GW
B12: DEM | D12: ADCF-MoTP-Mob-Uti | F12: Farm Vehicle | G12: =_xlfn.CONCAT(E12, " -:- ", F12) -> -:- Farm Vehicle | H12: Dairy Cattle Farming Motive Power, Mobile | I12: PJ | Q12: DMD | S12: ADCF-WH-Cylinder_ELC00 | T12: Agriculture | U12: Dairy Cattle Farming | V12: Hot Water Cylinder | W12: Electricity | X12: =_xlfn.CONCAT( T12, " -:- ", U12, " -:- ", V12, " -:- ", W12) -> Agriculture -:- Dairy Cattle Farming -:- Hot Water Cylinder -:- Electricity | Y12: Dairy Cattle Farming-Hot Water Cylinder | Z12: PJ | AA12: GW
B13: DEM | D13: ADCF-MoTP-Mob-Bike | F13: Off-road Motorbike Use | G13: =_xlfn.CONCAT(E13, " -:- ", F13) -> -:- Off-road Motorbike Use | H13: Dairy Cattle Farming Motive Power, Mobile | I13: PJ | Q13: DMD | S13: ADCF-WH-Hreco_ELC00 | T13: Agriculture | U13: Dairy Cattle Farming | V13: Heat Recovery System (Heating) | W13: Electricity | X13: =_xlfn.CONCAT( T13, " -:- ", U13, " -:- ", V13, " -:- ", W13) -> Agriculture -:- Dairy Cattle Farming -:- Heat Recovery System (Heating) -:- Electricity | Y13: Dairy Cattle Farming-Heat Recovery & Heat Pump | Z13: PJ | AA13: GW
B14: DEM | D14: ADCF-PUMP | F14: Pumping | G14: =_xlfn.CONCAT(E14, " -:- ", F14) -> -:- Pumping | H14: Dairy Cattle Farming Pumping | I14: PJ | Q14: DMD | S14: ADCF-MoTP-Mob-Trac-_DSL00 | T14: Agriculture | U14: Dairy Cattle Farming | V14: Tractor (Agricultural) | W14: Diesel | X14: =_xlfn.CONCAT( T14, " -:- ", U14, " -:- ", V14, " -:- ", W14) -> Agriculture -:- Dairy Cattle Farming -:- Tractor (Agricultural) -:- Diesel | Y14: Dairy Cattle Farming-Tractor | Z14: PJ | AA14: GW
B15: DEM | D15: ADCF-RFGR | F15: Refrigeration | G15: =_xlfn.CONCAT(E15, " -:- ", F15) -> -:- Refrigeration | H15: Dairy Cattle Farming Refrigeration | I15: PJ | Q15: DMD | S15: ADCF-MoTP-Mob-MTr-_DSL00 | T15: Agriculture | U15: Dairy Cattle Farming | V15: Truck (Agricultural) | W15: Diesel | X15: =_xlfn.CONCAT( T15, " -:- ", U15, " -:- ", V15, " -:- ", W15) -> Agriculture -:- Dairy Cattle Farming -:- Truck (Agricultural) -:- Diesel | Y15: Dairy Cattle Farming-Medium Truck | Z15: PJ | AA15: GW
B16: DEM | D16: ADCF-LIG | F16: Lighting | G16: =_xlfn.CONCAT(E16, " -:- ", F16) -> -:- Lighting | H16: Dairy Cattle Farming Lighting | I16: PJ | Q16: DMD | S16: ADCF-MoTP-Mob-Uti-_DSL00 | T16: Agriculture | U16: Dairy Cattle Farming | V16: Utility Vehicle (Agricultural) | W16: Diesel | X16: =_xlfn.CONCAT( T16, " -:- ", U16, " -:- ", V16, " -:- ", W16) -> Agriculture -:- Dairy Cattle Farming -:- Utility Vehicle (Agricultural) -:- Diesel | Y16: Dairy Cattle Farming-Utility | Z16: PJ | AA16: GW
B17: DEM | D17: ALIVE-IRG | F17: Irrigation | G17: =_xlfn.CONCAT(E17, " -:- ", F17) -> -:- Irrigation | H17: Livestock Farming Irrigation | I17: PJ | Q17: DMD | S17: ADCF-MoTP-Mob-Bike-_PET00 | T17: Agriculture | U17: Dairy Cattle Farming | V17: Farm Bike | W17: Petrol | X17: =_xlfn.CONCAT( T17, " -:- ", U17, " -:- ", V17, " -:- ", W17) -> Agriculture -:- Dairy Cattle Farming -:- Farm Bike -:- Petrol | Y17: Dairy Cattle Farming-Motorbike/side by side | Z17: PJ | AA17: GW
B18: DEM | D18: ALIVE-MoTP-Mob-Trac | F18: Tractor Services | G18: =_xlfn.CONCAT(E18, " -:- ", F18) -> -:- Tractor Services | H18: Livestock Farming Motive Power, Mobile | I18: PJ | Q18: DMD | S18: ADCF-PUMP-Pump_ELC00 | T18: Agriculture | U18: Dairy Cattle Farming | V18: Transfer Pump | W18: Electricity | X18: =_xlfn.CONCAT( T18, " -:- ", U18, " -:- ", V18, " -:- ", W18) -> Agriculture -:- Dairy Cattle Farming -:- Transfer Pump -:- Electricity | Y18: Dairy Cattle Farming-Transfer Pumps etc | Z18: PJ | AA18: GW
B19: DEM | D19: ALIVE-MoTP-Mob-MTr | F19: Truck Services | G19: =_xlfn.CONCAT(E19, " -:- ", F19) -> -:- Truck Services | H19: Livestock Farming Motive Power, Mobile | I19: PJ | Q19: DMD | S19: ADCF-RFGR-RF_ELC00 | T19: Agriculture | U19: Dairy Cattle Farming | V19: Refrigerator | W19: Electricity | X19: =_xlfn.CONCAT( T19, " -:- ", U19, " -:- ", V19, " -:- ", W19) -> Agriculture -:- Dairy Cattle Farming -:- Refrigerator -:- Electricity | Y19: Dairy Cattle Farming-Refrigeration | Z19: PJ | AA19: GW
... B41: DEM | D41: AOTH-PET | F41: Other | G41: =_xlfn.CONCAT(E41, " -:- ", F41) -> -:- Other | H41: Other Other - Petrol | I41: PJ | Q41: DMD | S41: AFORE-MoTP-Mob-GB-_DSL00 | T41: Agriculture | U41: Forestry | V41: Skidder (Forestry) | W41: Diesel | X41: =_xlfn.CONCAT( T41, " -:- ", U41, " -:- ", V41, " -:- ", W41) -> Agriculture -:- Forestry -:- Skidder (Forestry) -:- Diesel | Y41: Forestry and Logging-Ground Based | Z41: PJ | AA41: GW
Q42: DMD | S42: AFORE-MoTP-Mob-CY-_DSL00 | T42: Agriculture | U42: Forestry | V42: Cable Yarder (Forestry) | W42: Diesel | X42: =_xlfn.CONCAT( T42, " -:- ", U42, " -:- ", V42, " -:- ", W42) -> Agriculture -:- Forestry -:- Cable Yarder (Forestry) -:- Diesel | Y42: Forestry and Logging-Cable Yarding | Z42: PJ | AA42: GW
Q43: DMD | S43: AFORE-LIG-LT_ELC00 | T43: Agriculture | U43: Forestry | V43: Lights (General) | W43: Electricity | X43: =_xlfn.CONCAT( T43, " -:- ", U43, " -:- ", V43, " -:- ", W43) -> Agriculture -:- Forestry -:- Lights (General) -:- Electricity | Y43: Forestry and Logging-Light | Z43: PJ | AA43: GW
Q44: DMD | S44: AFISH-BOAT-Boat_DSL00 | T44: Agriculture | U44: Fishing | V44: Fishing Boat (Non-Hybrid) | W44: Diesel | X44: =_xlfn.CONCAT( T44, " -:- ", U44, " -:- ", V44, " -:- ", W44) -> Agriculture -:- Fishing -:- Fishing Boat (Non-Hybrid) -:- Diesel | Y44: Fishing, Hunting and Trapping-Boat | Z44: PJ | AA44: GW
Q45: DMD | S45: AFISH-BOAT-Boat_FOL00 | T45: Agriculture | U45: Fishing | V45: Fishing Boat (Non-Hybrid) | W45: Fuel Oil | X45: =_xlfn.CONCAT( T45, " -:- ", U45, " -:- ", V45, " -:- ", W45) -> Agriculture -:- Fishing -:- Fishing Boat (Non-Hybrid) -:- Fuel Oil | Y45: Fishing, Hunting and Trapping-Boat | Z45: PJ | AA45: GW
Q46: DMD | S46: AFISH-RFGR-RF_ELC00 | T46: Agriculture | U46: Fishing | V46: Refrigerator | W46: Electricity | X46: =_xlfn.CONCAT( T46, " -:- ", U46, " -:- ", V46, " -:- ", W46) -> Agriculture -:- Fishing -:- Refrigerator -:- Electricity | Y46: Fishing, Hunting and Trapping-Refrigeration | Z46: PJ | AA46: GW
Q47: DMD | S47: AFISH-LIG-LT_ELC00 | T47: Agriculture | U47: Fishing | V47: Lights (General) | W47: Electricity | X47: =_xlfn.CONCAT( T47, " -:- ", U47, " -:- ", V47, " -:- ", W47) -> Agriculture -:- Fishing -:- Lights (General) -:- Electricity | Y47: Fishing, Hunting and Trapping-Light | Z47: PJ | AA47: GW
Q48: DMD | S48: AOTH-ELC-_ELC00 | T48: Agriculture | U48: Other (Agriculture) | V48: Other | W48: Electricity | X48: =_xlfn.CONCAT( T48, " -:- ", U48, " -:- ", V48, " -:- ", W48) -> Agriculture -:- Other (Agriculture) -:- Other -:- Electricity | Y48: Other-Electricity | Z48: PJ | AA48: Pja
Q49: DMD | S49: AOTH-FOL-_FOL00 | T49: Agriculture | U49: Other (Agriculture) | V49: Other | W49: Fuel Oil | X49: =_xlfn.CONCAT( T49, " -:- ", U49, " -:- ", V49, " -:- ", W49) -> Agriculture -:- Other (Agriculture) -:- Other -:- Fuel Oil | Y49: Other-Fuel Oil | Z49: PJ | AA49: Pja
Q50: DMD | S50: AOTH-LPG-_LPG00 | T50: Agriculture | U50: Other (Agriculture) | V50: Other | W50: LPG | X50: =_xlfn.CONCAT( T50, " -:- ", U50, " -:- ", V50, " -:- ", W50) -> Agriculture -:- Other (Agriculture) -:- Other -:- LPG | Y50: Other-LPG | Z50: PJ | AA50: Pja
Q51: DMD | S51: AOTH-PET-_PET00 | T51: Agriculture | U51: Other (Agriculture) | V51: Other | W51: Petrol | X51: =_xlfn.CONCAT( T51, " -:- ", U51, " -:- ", V51, " -:- ", W51) -> Agriculture -:- Other (Agriculture) -:- Other -:- Petrol | Y51: Other-Petrol | Z51: PJ | AA51: Pja

Sheet AGR_fuels
B1: Sector Name | C1: Commodity | D1: Description | E1: Deafult unit | F1: Currency | G1: Existing
B2: AGR | C2: Agriculture | D2: Sector Fuel | E2: PJ | F2: Million NZD (2015) | G2: E
B4: ~FI_Comm | Q4: ~FI_Process
B5: Csets | C5: Region | D5: CommName | E5: * Fuel | F5: * Enduse | G5: CommDesc | H5: * OLD CommDesc | I5: Unit | J5: LimType | K5: CTSLvl | L5: PeakTS | M5: Ctype | Q5: Sets | R5: Region | S5: TechName | T5: * Sector | U5: * Subsector | V5: * Technology | W5: * Fuel | X5: TechDesc | Y5: * OLD TechDesc | Z5: Tact | AA5: Tcap | AB5: Tslvl | AC5: PrimaryCG | AD5: Vintage
B6: *Commodity Set Membership | C6: Region Name | D6: Commodity Name | H6: Commodity Description | I6: Unit | J6: Sense of the Balance EQN. | K6: Timeslice Level | L6: Peak Monitoring | M6: Electricity Indicator | Q6: *Process Set Membership | R6: Region Name | S6: Technology Name | Y6: Technology Description | Z6: Activity Unit | AA6: Capacity Unit | AB6: TimeSlice level of Process Activity | AC6: Primary Commodity Group | AD6: Vintage Tracking
B7: NRG | D7: AGRCOA | E7: Coal | G7: =_xlfn.CONCAT(E7, " -:- ", F7 ) -> Coal -:- | H7: Agriculture Coal | I7: PJ | J7: FX | K7: ANNUAL | Q7: *
B8: NRG | D8: AGRDSL | E8: Diesel | G8: =_xlfn.CONCAT(E8, " -:- ", F8 ) -> Diesel -:- | H8: Agriculture diesel oil | I8: PJ | J8: FX | K8: ANNUAL | Q8: PRE | S8: FTE_AGRCOA | T8: Agriculture | W8: Coal | X8: =_xlfn.CONCAT( T8, " -:- ", U8, " -:- ", V8, " -:- ", W8) -> Agriculture -:- -:- -:- Coal | Y8: Sector Fuel Technology Existing Coal | Z8: PJ | AA8: PJa | AB8: ANNUAL
B9: NRG | D9: AGRPET | E9: Petrol | G9: =_xlfn.CONCAT(E9, " -:- ", F9 ) -> Petrol -:- | H9: Agriculture petroleum | I9: PJ | J9: FX | K9: ANNUAL | Q9: PRE | S9: =+B23 -> FTE_AGRDSL | T9: Agriculture | W9: Diesel | X9: =_xlfn.CONCAT( T9, " -:- ", U9, " -:- ", V9, " -:- ", W9) -> Agriculture -:- -:- -:- Diesel | Y9: =+"Sector Fuel Supply - "&H8 -> Sector Fuel Supply - Agriculture diesel oil | Z9: PJ | AA9: PJa | AB9: ANNUAL
B10: NRG | D10: AGRFOL | E10: Fuel Oil | G10: =_xlfn.CONCAT(E10, " -:- ", F10 ) -> Fuel Oil -:- | H10: Agriculture fuel oil | I10: PJ | J10: FX | K10: ANNUAL | Q10: PRE | S10: =+B25 -> FTE_AGRPET | T10: Agriculture | W10: Petrol | X10: =_xlfn.CONCAT( T10, " -:- ", U10, " -:- ", V10, " -:- ", W10) -> Agriculture -:- -:- -:- Petrol | Y10: =+"Sector Fuel Supply - "&H9 -> Sector Fuel Supply - Agriculture petroleum | Z10: PJ | AA10: PJa | AB10: ANNUAL
B11: NRG | D11: AGRLPG | E11: LPG | G11: =_xlfn.CONCAT(E11, " -:- ", F11 ) -> LPG -:- | H11: Agriculture LPG | I11: PJ | J11: FX | K11: ANNUAL | Q11: PRE | S11: =+B26 -> FTE_AGRFOL | T11: Agriculture | W11: Fuel Oil | X11: =_xlfn.CONCAT( T11, " -:- ", U11, " -:- ", V11, " -:- ", W11) -> Agriculture -:- -:- -:- Fuel Oil | Y11: =+"Sector Fuel Supply - "&H10 -> Sector Fuel Supply - Agriculture fuel oil | Z11: PJ | AA11: PJa | AB11: ANNUAL
B12: NRG | D12: AGRWOD | E12: Wood | G12: =_xlfn.CONCAT(E12, " -:- ", F12 ) -> Wood -:- | H12: Agriculture wood | I12: PJ | J12: FX | K12: ANNUAL | Q12: PRE | S12: =+B27 -> FTE_AGRLPG | T12: Agriculture | W12: LPG | X12: =_xlfn.CONCAT( T12, " -:- ", U12, " -:- ", V12, " -:- ", W12) -> Agriculture -:- -:- -:- LPG | Y12: =+"Sector Fuel Supply - "&H11 -> Sector Fuel Supply - Agriculture LPG | Z12: PJ | AA12: PJa | AB12: ANNUAL
B13: NRG | D13: AGRPLT | E13: Pellet | G13: =_xlfn.CONCAT(E13, " -:- ", F13 ) -> Pellet -:- | H13: Agriculture pellet | I13: PJ | J13: FX | K13: ANNUAL | Q13: PRE | S13: =+B28 -> FTE_AGRWOD | T13: Agriculture | W13: Wood | X13: =_xlfn.CONCAT( T13, " -:- ", U13, " -:- ", V13, " -:- ", W13) -> Agriculture -:- -:- -:- Wood | Y13: =+"Sector Fuel Supply - "&H12 -> Sector Fuel Supply - Agriculture wood | Z13: PJ | AA13: PJa | AB13: ANNUAL
B14: ENV | D14: AGRCO2 | G14: =_xlfn.CONCAT(E14, " -:- ", F14 ) -> -:- | H14: Agriculture emissions | I14: kt | Q14: PRE | S14: =+B29 -> FTE_AGRPLT | T14: Agriculture | W14: Pellet | X14: =_xlfn.CONCAT( T14, " -:- ", U14, " -:- ", V14, " -:- ", W14) -> Agriculture -:- -:- -:- Pellet | Y14: =+"Sector Fuel Supply - "&H13 -> Sector Fuel Supply - Agriculture pellet | Z14: PJ | AA14: PJa | AB14: ANNUAL
D17: ~FI_T
B18: TechName | C18: Comm-IN | D18: Comm-OUT | E18: Share-I~UP | F18: Share-I~UP~2025 | G18: *Share-I~UP~2060 | H18: Share-I~UP~0 | I18: EFF | J18: LIFE | K18: EFF~2021 | L18: EFF~2025 | M18: EFF~2040 | N18: EFF~2060 | O18: EFF~0 | P18: INVCOST | Q18: FIXOM | R18: VAROM | S18: FLO_DELIV
B19: *Technology Name | C19: Input Commodity | D19: Output Commodity | E19: Input Share | F19: Input Share | G19: Input Share | H19: Input Share | I19: Efficiency | J19: Lifetime | P19: Capital costs | Q19: Fixed O&M | R19: Variable O&M
B20: *Units | J20: Years | P20: MNZD/Pja | Q20: MNZD/Pja | R20: MNZD/PJ
B21: FTE_AGRCOA | C21: COA | D21: AGRCOA | E21: 1 | F21: 1 | H21: 5 | I21: 1 | J21: 100
C22: COL | E22: 0.05 | F22: =+E22 -> 0.05
B23: =+"FTE_AGR"&C23 -> FTE_AGRDSL | C23: =+RIGHT(D23,3) -> DSL | D23: =+D8 -> AGRDSL | E23: 1 | F23: 1 | I23: 1 | J23: 100 | R23: 0.92
C24: DID | E24: 1 | F24: 1 | S24: 2.4
B25: =+"FTE_AGR"&C25 -> FTE_AGRPET | C25: =+RIGHT(D25,3) -> PET | D25: =+D9 -> AGRPET | I25: 1 | J25: 100 | R25: 0.92
B26: =+"FTE_AGR"&C26 -> FTE_AGRFOL | C26: =+RIGHT(D26,3) -> FOL | D26: =+D10 -> AGRFOL | I26: 1 | J26: 100
B27: =+"FTE_AGR"&C27 -> FTE_AGRLPG | C27: =+RIGHT(D27,3) -> LPG | D27: =+D11 -> AGRLPG | I27: 1 | J27: 100
B28: =+"FTE_AGR"&C28 -> FTE_AGRWOD | C28: WOD | D28: =+D12 -> AGRWOD | I28: 1 | J28: 100
B29: =+"FTE_AGR"&C29 -> FTE_AGRPLT | C29: PLT | D29: =+D13 -> AGRPLT | I29: 1 | J29: 100

Sheet AGR
E2: ~FI_T
C3: TechName | D3: Comm-IN | E3: Comm-OUT | F3: PRC_RESID | G3: *Delivered energy 2018 | H3: EFF | I3: LIFE | J3: INVCOST | K3: FIXOM | L3: CAP2ACT | M3: ACT_BND | N3: AFA
C4: *Technology Name | D4: Input Commodity | E4: Output Commodity | F4: Existing Installed Capacity | G4: *Energy from EEUD | H4: Efficiency | I4: Lifetime | J4: CAPEX | K4: FIXED O&M | L4: Capacity to activity factor | M4: Actual end-use in 2018 | N4: Annual utilisation factor
C5: *Units | F5: GW | G5: *PJ | H5: % | I5: Years | J5: NZD/kW | K5: NZD/kW/yr | M5: End-use PJ | N5: %
C6: ADCF-MoTP-Stat-VacP_ELC00 | D6: AGRELC | E6: ADCF-MoTP-Stat | F6: 0.022523372 | G6: 0.19110074 | H6: 0.84 | I6: 25 | J6: 410.6135 | K6: 14.445557 | L6: 31.536 | M6: 0.16052462 | N6: 0.22599646
C7: ADCF-MoTP-Stat-VPVSD_ELC00 | D7: AGRELC | E7: ADCF-MoTP-Stat | F7: 0.035345118 | G7: 0.26390102 | H7: 0.95454545 | I7: 25 | J7: 643.4135 | K7: 14.445557 | L7: 31.536 | M7: 0.25190552 | N7: 0.22599646
C8: ADCF-IRG-Irg_ELC00 | D8: AGRELC | E8: ADCF-IRG | F8: 0.1305891 | G8: 0.95782043 | H8: 0.7 | I8: 20 | J8: 6000 | K8: 917.19323 | L8: 31.536 | M8: 0.6704743 | N8: 0.16280532
C9: ADCF-IRG-IrgVSD_ELC00 | D9: AGRELC | E9: ADCF-IRG | F9: 0.051691521 | G9: 0.31927348 | H9: 0.83125 | I9: 20 | J9: 6257.143 | K9: 917.19323 | L9: 31.536 | M9: 0.26539608 | N9: 0.16280532
C10: ADCF-WH-Cylinder_ELC00 | D10: AGRELC | E10: ADCF-WH | F10: 0.032996602 | G10: 0.2828747 | H10: 0.83134897 | I10: 20 | J10: 518.5169 | K10: 18.241644 | L10: 31.536 | M10: 0.23516759 | N10: 0.22599646
C11: ADCF-WH-Hreco_ELC00 | D11: AGRELC | E11: ADCF-WH | F11: 0.085142384 | G11: 0.17337481 | H11: 3.5 | I11: 20 | J11: 1525.072 | K11: 53.652675 | L11: 31.536 | M11: 0.60681185 | N11: 0.22599646
C12: ADCF-MoTP-Mob-Trac-_DSL00 | D12: AGRDSL | E12: ADCF-MoTP-Mob-Trac | F12: 1.703984 | G12: 1.4005348 | H12: 0.11111111 | I12: 15 | J12: 965.2941 | K12: 38.611763 | L12: 1 | M12: 0.15561497 | N12: 0.091324201
C13: ADCF-MoTP-Mob-MTr-_DSL00 | D13: AGRDSL | E13: ADCF-MoTP-Mob-MTr | F13: 2.1936931 | G13: 0.40015279 | H13: 0.12516299 | I13: 22 | J13: 264.043 | K13: 70.396142 | L13: 1 | M13: 0.050084318 | N13: 0.02283105
C14: ADCF-MoTP-Mob-Uti-_DSL00 | D14: AGRDSL | E14: ADCF-MoTP-Mob-Uti | F14: 0.5038924 | G14: 0.20007639 | H14: 0.23 | I14: 22 | J14: 1851.867 | K14: 11.879812 | L14: 1 | M14: 0.046017571 | N14: 0.091324201
C15: ADCF-MoTP-Mob-Bike-_PET00 | D15: AGRPET | E15: ADCF-MoTP-Mob-Bike | F15: 0.11484717 | G15: 0.28711793 | H15: 0.1 | I15: 10 | J15: 363.4258 | K15: 34.750457 | L15: 1 | M15: 0.028711793 | N15: 0.25
C16: ADCF-PUMP-Pump_ELC00 | D16: AGRELC | E16: ADCF-PUMP | F16: 0.050877907 | G16: 0.51801155 | H16: 0.7 | I16: 25 | J16: 886.9063 | K16: 31.201736 | L16: 31.536 | M16: 0.36260808 | N16: 0.22599646
C17: ADCF-RFGR-RF_ELC00 | D17: AGRELC | E17: ADCF-RFGR | F17: 0.087844423 | G17: 0.2121123 | H17: 2.9515937 | I17: 15 | J17: 1637.346 | K17: 57.602515 | L17: 31.536 | M17: 0.62606934 | N17: 0.22599646
... C45: AFISH-LIG-LT_ELC00 | D45: AGRELC | E45: AFISH-LIG | F45: 0.0002762151 | G45: 0.0082024655 | H45: 0.24 | I45: 3.4246575 | J45: 365.1304 | K45: 0 | L45: 31.536 | M45: 0.0019685917 | N45: 0.22599646
C46: AOTH-ELC-_ELC00 | D46: AGRELC | E46: AOTH-ELC | G46: 0.011645478 | H46: 1 | L46: 1 | M46: =+G46 -> 0.011645478 | N46: 1
C47: AOTH-FOL-_FOL00 | D47: AGRFOL | E47: AOTH-FOL | G47: 0.015942326 | H47: 1 | L47: 1 | M47: =+G47 -> 0.015942326 | N47: 1
C48: AOTH-LPG-_LPG00 | D48: AGRLPG | E48: AOTH-LPG | G48: 0.055427963 | H48: 1 | L48: 1 | M48: =+G48 -> 0.055427963 | N48: 1
C49: AOTH-PET-_PET00 | D49: AGRPET | E49: AOTH-PET | G49: 0.0069424525 | H49: 1 | L49: 1 | M49: =+G49 -> 0.0069424525 | N49: 1
C55: ~FI_T
C56: CommName | D56: Demand~2018
C57: ADCF-MoTP-Stat | D57: =+ROUNDDOWN(SUMIF($E$6:$E$49,C57,$M$6:$M$49),3) -> 0.412
C58: ADCF-IRG | D58: =+ROUNDDOWN(SUMIF($E$6:$E$49,C58,$M$6:$M$49),3) -> 0.935
C59: ADCF-WH | D59: =+ROUNDDOWN(SUMIF($E$6:$E$49,C59,$M$6:$M$49),3) -> 0.841
C60: ADCF-MoTP-Mob-Trac | D60: =+ROUNDDOWN(SUMIF($E$6:$E$49,C60,$M$6:$M$49),3) -> 0.155
C61: ADCF-MoTP-Mob-MTr | D61: =+ROUNDDOWN(SUMIF($E$6:$E$49,C61,$M$6:$M$49),3) -> 0.05
C62: ADCF-MoTP-Mob-Uti | D62: =+ROUNDDOWN(SUMIF($E$6:$E$49,C62,$M$6:$M$49),3) -> 0.046
C63: ADCF-MoTP-Mob-Bike | D63: =+ROUNDDOWN(SUMIF($E$6:$E$49,C63,$M$6:$M$49),3) -> 0.028
C64: ADCF-PUMP | D64: =+ROUNDDOWN(SUMIF($E$6:$E$49,C64,$M$6:$M$49),3) -> 0.362
C65: ADCF-RFGR | D65: =+ROUNDDOWN(SUMIF($E$6:$E$49,C65,$M$6:$M$49),3) -> 1.368
C66: ADCF-LIG | D66: =+ROUNDDOWN(SUMIF($E$6:$E$49,C66,$M$6:$M$49),3) -> 0.004
C67: ALIVE-IRG | D67: =+ROUNDDOWN(SUMIF($E$6:$E$49,C67,$M$6:$M$49),3) -> 0.48
C68: ALIVE-MoTP-Mob-Trac | D68: =+ROUNDDOWN(SUMIF($E$6:$E$49,C68,$M$6:$M$49),3) -> 0.115
... C91: AOTH-PET | D91: =+ROUNDDOWN(SUMIF($E$6:$E$49,C91,$M$6:$M$49),3) -> 0.006

Sheet RES_techs_coms
B1: Residential sector commodity and process descriptions
B6: ~FI_Comm | P6: ~FI_Process
B7: Csets | C7: CommName | D7: * Fuel | E7: * Enduse | F7: CommDesc | G7: * OLD CommDesc | H7: Unit | I7: LimType | J7: CTSLvl | K7: PeakTS | L7: Ctype | P7: Sets | Q7: TechName | R7: * Sector | S7: * Subsector | T7: * Technology | U7: * Fuel | V7: TechDesc | W7: * OLD TechDesc | X7: Tact | Y7: Tcap | Z7: Tslvl | AA7: PrimaryCG | AB7: Vintage
B8: NRG | C8: RESCOA | D8: Coal | F8: =_xlfn.CONCAT(D8, " -:- ", E8) -> Coal -:- | G8: Residential Coal | H8: PJ | I8: FX | P8: PRE | Q8: ="FTE_"&C8&"_00" -> FTE_RESCOA_00 | R8: Residential | U8: Coal | V8: =_xlfn.CONCAT( R8, " -:- ", S8, " -:- ", T8, " -:- ", U8) -> Residential -:- -:- -:- Coal | W8: ="Distribution network for "&G8 -> Distribution network for Residential Coal | X8: PJ | Y8: PJ_a
B9: NRG | C9: RESNGA | D9: Natural Gas | F9: =_xlfn.CONCAT(D9, " -:- ", E9) -> Natural Gas -:- | G9: Residential Natural gas | H9: PJ | I9: FX | P9: PRE | Q9: ="FTE_"&C9&"_00" -> FTE_RESNGA_00 | R9: Residential | U9: Natural Gas | V9: =_xlfn.CONCAT( R9, " -:- ", S9, " -:- ", T9, " -:- ", U9) -> Residential -:- -:- -:- Natural Gas | W9: ="Distribution network for "&G9 -> Distribution network for Residential Natural gas | X9: PJ | Y9: PJ_a
B10: NRG | C10: RESLPG | D10: LPG | F10: =_xlfn.CONCAT(D10, " -:- ", E10) -> LPG -:- | G10: Residential LPG | H10: PJ | I10: FX | P10: PRE | Q10: ="FTE_"&C10&"_00" -> FTE_RESLPG_00 | R10: Residential | U10: LPG | V10: =_xlfn.CONCAT( R10, " -:- ", S10, " -:- ", T10, " -:- ", U10) -> Residential -:- -:- -:- LPG | W10: ="Distribution network for "&G10 -> Distribution network for Residential LPG | X10: PJ | Y10: PJ_a
B11: NRG | C11: RESDSL | D11: Diesel | F11: =_xlfn.CONCAT(D11, " -:- ", E11) -> Diesel -:- | G11: Residential Diesel | H11: PJ | I11: FX | P11: PRE | Q11: ="FTE_"&C11&"_00" -> FTE_RESDSL_00 | R11: Residential | U11: Diesel | V11: =_xlfn.CONCAT( R11, " -:- ", S11, " -:- ", T11, " -:- ", U11) -> Residential -:- -:- -:- Diesel | W11: ="Distribution network for "&G11 -> Distribution network for Residential Diesel | X11: PJ | Y11: PJ_a
B12: NRG | C12: RESWOD | D12: Wood | F12: =_xlfn.CONCAT(D12, " -:- ", E12) -> Wood -:- | G12: Residential Firewood | H12: PJ | I12: FX | P12: PRE | Q12: ="FTE_"&C12&"_00" -> FTE_RESWOD_00 | R12: Residential | U12: Wood | V12: =_xlfn.CONCAT( R12, " -:- ", S12, " -:- ", T12, " -:- ", U12) -> Residential -:- -:- -:- Wood | W12: ="Distribution network for "&G12 -> Distribution network for Residential Firewood | X12: PJ | Y12: PJ_a
B13: NRG | C13: RESGEO | D13: Geothermal | F13: =_xlfn.CONCAT(D13, " -:- ", E13) -> Geothermal -:- | G13: Residential Geothermal | H13: PJ | I13: FX | P13: PRE | Q13: ="FTE_"&C13&"_00" -> FTE_RESGEO_00 | R13: Residential | U13: Geothermal | V13: =_xlfn.CONCAT( R13, " -:- ", S13, " -:- ", T13, " -:- ", U13) -> Residential -:- -:- -:- Geothermal | W13: ="Distribution network for "&G13 -> Distribution network for Residential Geothermal | X13: PJ | Y13: PJ_a
B14: NRG | C14: RESSOL | D14: Solar | F14: =_xlfn.CONCAT(D14, " -:- ", E14) -> Solar -:- | G14: Residential Solar energy | H14: PJ | I14: FX | P14: PRE | Q14: ="FTE_"&C14&"_00" -> FTE_RESSOL_00 | R14: Residential | U14: Solar | V14: =_xlfn.CONCAT( R14, " -:- ", S14, " -:- ", T14, " -:- ", U14) -> Residential -:- -:- -:- Solar | W14: ="Distribution network for "&G14 -> Distribution network for Residential Solar energy | X14: PJ | Y14: PJ_a
B15: NRG | C15: RESPET | D15: Petrol | F15: =_xlfn.CONCAT(D15, " -:- ", E15) -> Petrol -:- | G15: Residential petroleum | H15: PJ | I15: FX | P15: PRE | Q15: ="FTE_"&C15&"_00" -> FTE_RESPET_00 | R15: Residential | U15: Petrol | V15: =_xlfn.CONCAT( R15, " -:- ", S15, " -:- ", T15, " -:- ", U15) -> Residential -:- -:- -:- Petrol | W15: ="Distribution network for "&G15 -> Distribution network for Residential petroleum | X15: PJ | Y15: PJ_a
B16: ENV | C16: RESCO2 | F16: =_xlfn.CONCAT(D16, " -:- ", E16) -> -:- | G16: Residential CO2 emissions | H16: kt | P16: DMD | Q16: =+RES!C7 -> R_DDW-SH_Burner-WOD00 | R16: Residential | S16: Detached Dwellings | T16: Burner | U16: Wood | V16: =_xlfn.CONCAT( R16, " -:- ", S16, " -:- ", T16, " -:- ", U16) -> Residential -:- Detached Dwellings -:- Burner -:- Wood | W16: =+RES!D7 -> Detached dwellings - Heat/Cooling Devices - Burner (Direct Heat) | X16: PJ | Y16: GW
B17: DEM | C17: R_DDW-SH | E17: Space Heating | F17: =_xlfn.CONCAT(D17, " -:- ", E17) -> -:- Space Heating | G17: Detached dwellings - Low Temperature Heat (<100 C), Space Heating | H17: PJ | P17: DMD | Q17: =+RES!C8 -> R_DDW-SH_Burner-LPG00 | R17: Residential | S17: Detached Dwellings | T17: Burner | U17: LPG | V17: =_xlfn.CONCAT( R17, " -:- ", S17, " -:- ", T17, " -:- ", U17) -> Residential -:- Detached Dwellings -:- Burner -:- LPG | W17: =+RES!D8 -> Detached dwellings - Heat/Cooling Devices - Burner (Direct Heat) | X17: PJ | Y17: GW
B18: DEM | C18: R_DDW-WH | E18: Water Heating | F18: =_xlfn.CONCAT(D18, " -:- ", E18) -> -:- Water Heating | G18: Detached dwellings - Low Temperature Heat (<100 C), Water Heating | H18: PJ | P18: DMD | Q18: =+RES!C9 -> R_DDW-SH_Burner-DSL00 | R18: Residential | S18: Detached Dwellings | T18: Burner | U18: Diesel | V18: =_xlfn.CONCAT( R18, " -:- ", S18, " -:- ", T18, " -:- ", U18) -> Residential -:- Detached Dwellings -:- Burner -:- Diesel | W18: =+RES!D9 -> Detached dwellings - Heat/Cooling Devices - Burner (Direct Heat) | X18: PJ | Y18: GW
B19: DEM | C19: R_DDW-CK | E19: Cooking | F19: =_xlfn.CONCAT(D19, " -:- ", E19) -> -:- Cooking | G19: Detached dwellings - Intermediate Heat (100-300 C), Cooking | H19: PJ | P19: DMD | Q19: =+RES!C10 -> R_DDW-SH_Burner-COA00 | R19: Residential | S19: Detached Dwellings | T19: Burner | U19: Coal | V19: =_xlfn.CONCAT( R19, " -:- ", S19, " -:- ", T19, " -:- ", U19) -> Residential -:- Detached Dwellings -:- Burner -:- Coal | W19: =+RES!D10 -> Detached dwellings - Heat/Cooling Devices - Burner (Direct Heat) | X19: PJ | Y19: GW
B20: DEM | C20: R_DDW-RF | E20: Refrigeration | F20: =_xlfn.CONCAT(D20, " -:- ", E20) -> -:- Refrigeration | G20: Detached dwellings - Refrigeration | H20: PJ | P20: DMD | Q20: =+RES!C11 -> R_DDW-SH_OF-WOD00 | R20: Residential | S20: Detached Dwellings | T20: Open Fire | U20: Wood | V20: =_xlfn.CONCAT( R20, " -:- ", S20, " -:- ", T20, " -:- ", U20) -> Residential -:- Detached Dwellings -:- Open Fire -:- Wood | W20: =+RES!D11 -> Detached dwellings - Heat/Cooling Devices - Open Fire | X20: PJ | Y20: GW
B21: DEM | C21: R_DDW-CD | E21: Clothes Drying | F21: =_xlfn.CONCAT(D21, " -:- ", E21) -> -:- Clothes Drying | G21: Detached dwellings - Low Temperature Heat (<100 C), Clothes Drying | H21: PJ | P21: DMD | Q21: =+RES!C12 -> R_DDW-SH_OF-COA00 | R21: Residential | S21: Detached Dwellings | T21: Open Fire | U21: Coal | V21: =_xlfn.CONCAT( R21, " -:- ", S21, " -:- ", T21, " -:- ", U21) -> Residential -:- Detached Dwellings -:- Open Fire -:- Coal | W21: =+RES!D12 -> Detached dwellings - Heat/Cooling Devices - Open Fire | X21: PJ | Y21: GW
B22: DEM | C22: R_DDW-SC | E22: Space Cooling | F22: =_xlfn.CONCAT(D22, " -:- ", E22) -> -:- Space Cooling | G22: Detached dwellings - Space Cooling | H22: PJ | P22: DMD | Q22: =+RES!C13 -> R_DDW-SH_OFWB-COA00 | R22: Residential | S22: Detached Dwellings | T22: Open Fire (with Wetback) | U22: Coal | V22: =_xlfn.CONCAT( R22, " -:- ", S22, " -:- ", T22, " -:- ", U22) -> Residential -:- Detached Dwellings -:- Open Fire (with Wetback) -:- Coal | W22: =+RES!D13 -> Detached dwellings - Heat/Cooling Devices - Open Fire, with Wetback | X22: PJ | Y22: GW
B23: DEM | C23: R_DDW-CW | E23: Clothes Washing | F23: =_xlfn.CONCAT(D23, " -:- ", E23) -> -:- Clothes Washing | G23: Detached dwellings - Low Temperature Heat (<100 C), Clothes Washing | H23: PJ | P23: DMD | Q23: =+RES!C14 -> R_DDW-SH_HP-ELC00 | R23: Residential | S23: Detached Dwellings | T23: Heat Pump | U23: Electricity | V23: =_xlfn.CONCAT( R23, " -:- ", S23, " -:- ", T23, " -:- ", U23) -> Residential -:- Detached Dwellings -:- Heat Pump -:- Electricity | W23: =+RES!D14 -> Detached dwellings - Heat/Cooling Devices - Heat Pump (for Heating) | X23: PJ | Y23: GW
B24: DEM | C24: R_DDW-DW | E24: Dishwashing | F24: =_xlfn.CONCAT(D24, " -:- ", E24) -> -:- Dishwashing | G24: Detached dwellings - Low Temperature Heat (< 100 C), Dishwashers | H24: PJ | P24: DMD | Q24: =+RES!C15 -> R_DDW-SH_RH-ELC00 | R24: Residential | S24: Detached Dwellings | T24: Resistance Heater | U24: Electricity | V24: =_xlfn.CONCAT( R24, " -:- ", S24, " -:- ", T24, " -:- ", U24) -> Residential -:- Detached Dwellings -:- Resistance Heater -:- Electricity | W24: =+RES!D15 -> Detached dwellings - Heat/Cooling Devices - Resistance Heater | X24: PJ | Y24: GW
B25: DEM | C25: R_DDW-LT | E25: Lighting | F25: =_xlfn.CONCAT(D25, " -:- ", E25) -> -:- Lighting | G25: Detached dwellings - Lighting | H25: PJ | P25: DMD | Q25: =+RES!C16 -> R_DDW-WH_OFWB-COA00 | R25: Residential | S25: Detached Dwellings | T25: Open Fire (with Wetback) | U25: Coal | V25: =_xlfn.CONCAT( R25, " -:- ", S25, " -:- ", T25, " -:- ", U25) -> Residential -:- Detached Dwellings -:- Open Fire (with Wetback) -:- Coal | W25: =+RES!D16 -> Detached dwellings - Heat/Cooling Devices - Open Fire, with Wetback | X25: PJ | Y25: GW
B26: DEM | C26: R_DDW-OTH | E26: Electronics and Other Appliances | F26: =_xlfn.CONCAT(D26, " -:- ", E26) -> -:- Electronics and Other Appliances | G26: Detached dwellings - Electronics and Other Electrical Uses | H26: PJ | P26: DMD | Q26: =+RES!C17 -> R_DDW-WH_HWC-SOL00 | R26: Residential | S26: Detached Dwellings | T26: Hot Water Cylinder | U26: Solar | V26: =_xlfn.CONCAT( R26, " -:- ", S26, " -:- ", T26, " -:- ", U26) -> Residential -:- Detached Dwellings -:- Hot Water Cylinder -:- Solar | W26: =+RES!D17 -> Detached dwellings - Heat/Cooling Devices - Hot Water Cylinder | X26: PJ | Y26: GW
B27: DEM | C27: R_DDW-MPS | E27: Motive Power, Stationary | F27: =_xlfn.CONCAT(D27, " -:- ", E27) -> -:- Motive Power, Stationary | G27: Detached dwellings - Motive Power, Stationary | H27: PJ | P27: DMD | Q27: =+RES!C18 -> R_DDW-WH_HWC-ELC00 | R27: Residential | S27: Detached Dwellings | T27: Hot Water Cylinder | U27: Electricity | V27: =_xlfn.CONCAT( R27, " -:- ", S27, " -:- ", T27, " -:- ", U27) -> Residential -:- Detached Dwellings -:- Hot Water Cylinder -:- Electricity | W27: =+RES!D18 -> Detached dwellings - Heat/Cooling Devices - Hot Water Cylinder | X27: PJ | Y27: GW
B28: DEM | C28: R_DDW-MPM | E28: Motive Power, Mobile | F28: =_xlfn.CONCAT(D28, " -:- ", E28) -> -:- Motive Power, Mobile | G28: Detached dwellings - Motive Power, Mobile | H28: PJ | P28: DMD | Q28: =+RES!C19 -> R_DDW-WH_Gasheat-LPG00 | R28: Residential | S28: Detached Dwellings | T28: Gas Heater | U28: LPG | V28: =_xlfn.CONCAT( R28, " -:- ", S28, " -:- ", T28, " -:- ", U28) -> Residential -:- Detached Dwellings -:- Gas Heater -:- LPG | W28: =+RES!D19 -> Detached dwellings - Heat/Cooling Devices - Gas Water Heater | X28: PJ | Y28: GW
... B40: DEM | C40: R_JDW-MPM | E40: Motive Power, Mobile | F40: =_xlfn.CONCAT(D40, " -:- ", E40) -> -:- Motive Power, Mobile | G40: Joined dwellings - Motive Power, Mobile | H40: PJ | P40: DMD | Q40: =+RES!C31 -> R_DDW-LT_CFL-ELC00 | R40: Residential | S40: Detached Dwellings | T40: Lights (Fluorescent) | U40: Electricity | V40: =_xlfn.CONCAT( R40, " -:- ", S40, " -:- ", T40, " -:- ", U40) -> Residential -:- Detached Dwellings -:- Lights (Fluorescent) -:- Electricity | W40: =+RES!D31 -> Detached dwellings - Electronics and Lights - Fluorescent | X40: PJ | Y40: GW
F41: =_xlfn.CONCAT(D41, " -:- ", E41) -> -:- | P41: DMD | Q41: =+RES!C32 -> R_DDW-OTH_Elec-ELC00 | R41: Residential | S41: Detached Dwellings | T41: Electronics and Other Appliances | U41: Electricity | V41: =_xlfn.CONCAT( R41, " -:- ", S41, " -:- ", T41, " -:- ", U41) -> Residential -:- Detached Dwellings -:- Electronics and Other Appliances -:- Electricity | W41: =+RES!D32 -> Detached dwellings - Electronics and Lights - Electronics | X41: PJ | Y41: GW
P42: DMD | Q42: =+RES!C33 -> R_DDW-MPS_Motor-ELC00 | R42: Residential | S42: Detached Dwellings | T42: Stationary Motor | U42: Electricity | V42: =_xlfn.CONCAT( R42, " -:- ", S42, " -:- ", T42, " -:- ", U42) -> Residential -:- Detached Dwellings -:- Stationary Motor -:- Electricity | W42: =+RES!D33 -> Detached dwellings - Stationary Motors - Electric Motor | X42: PJ | Y42: GW
P43: DMD | Q43: =+RES!C34 -> R_DDW-MPM_ICE-PET00 | R43: Residential | S43: Detached Dwellings | T43: Mobile Motor | U43: Petrol | V43: =_xlfn.CONCAT( R43, " -:- ", S43, " -:- ", T43, " -:- ", U43) -> Residential -:- Detached Dwellings -:- Mobile Motor -:- Petrol | W43: =+RES!D34 -> Detached dwellings - Stationary Motors - Internal Combustion (Domestic Use) | X43: PJ | Y43: GW
P44: DMD | Q44: =+RES!C35 -> R_JDW-SH_Burner-LPG00 | R44: Residential | S44: Joined Dwellings | T44: Burner | U44: LPG | V44: =_xlfn.CONCAT( R44, " -:- ", S44, " -:- ", T44, " -:- ", U44) -> Residential -:- Joined Dwellings -:- Burner -:- LPG | W44: =+RES!D35 -> Joined dwellings - Heat/Cooling Devices - Burner (Direct Heat) | X44: PJ | Y44: GW
P45: DMD | Q45: =+RES!C36 -> R_JDW-SH_Burner-DSL00 | R45: Residential | S45: Joined Dwellings | T45: Burner | U45: Diesel | V45: =_xlfn.CONCAT( R45, " -:- ", S45, " -:- ", T45, " -:- ", U45) -> Residential -:- Joined Dwellings -:- Burner -:- Diesel | W45: =+RES!D36 -> Joined dwellings - Heat/Cooling Devices - Burner (Direct Heat) | X45: PJ | Y45: GW
P46: DMD | Q46: =+RES!C37 -> R_JDW-SH_HP-ELC00 | R46: Residential | S46: Joined Dwellings | T46: Heat Pump | U46: Electricity | V46: =_xlfn.CONCAT( R46, " -:- ", S46, " -:- ", T46, " -:- ", U46) -> Residential -:- Joined Dwellings -:- Heat Pump -:- Electricity | W46: =+RES!D37 -> Joined dwellings - Heat/Cooling Devices - Heat Pump (for Heating) | X46: PJ | Y46: GW
P47: DMD | Q47: =+RES!C38 -> R_JDW-SH_RH-ELC00 | R47: Residential | S47: Joined Dwellings | T47: Resistance Heater | U47: Electricity | V47: =_xlfn.CONCAT( R47, " -:- ", S47, " -:- ", T47, " -:- ", U47) -> Residential -:- Joined Dwellings -:- Resistance Heater -:- Electricity | W47: =+RES!D38 -> Joined dwellings - Heat/Cooling Devices - Resistance Heater | X47: PJ | Y47: GW
P48: DMD | Q48: =+RES!C39 -> R_JDW-WH_HWC-SOL00 | R48: Residential | S48: Joined Dwellings | T48: Hot Water Cylinder | U48: Solar | V48: =_xlfn.CONCAT( R48, " -:- ", S48, " -:- ", T48, " -:- ", U48) -> Residential -:- Joined Dwellings -:- Hot Water Cylinder -:- Solar | W48: =+RES!D39 -> Joined dwellings - Heat/Cooling Devices - Hot Water Cylinder | X48: PJ | Y48: GW
P49: DMD | Q49: =+RES!C40 -> R_JDW-WH_HWC-ELC00 | R49: Residential | S49: Joined Dwellings | T49: Hot Water Cylinder | U49: Electricity | V49: =_xlfn.CONCAT( R49, " -:- ", S49, " -:- ", T49, " -:- ", U49) -> Residential -:- Joined Dwellings -:- Hot Water Cylinder -:- Electricity | W49: =+RES!D40 -> Joined dwellings - Heat/Cooling Devices - Hot Water Cylinder | X49: PJ | Y49: GW
P50: DMD | Q50: =+RES!C41 -> R_JDW-WH_Gasheat-LPG00 | R50: Residential | S50: Joined Dwellings | T50: Gas Heater | U50: LPG | V50: =_xlfn.CONCAT( R50, " -:- ", S50, " -:- ", T50, " -:- ", U50) -> Residential -:- Joined Dwellings -:- Gas Heater -:- LPG | W50: =+RES!D41 -> Joined dwellings - Heat/Cooling Devices - Gas Water Heater | X50: PJ | Y50: GW
P51: DMD | Q51: =+RES!C42 -> R_JDW-CK_Appl-ELC00 | R51: Residential | S51: Joined Dwellings | T51: Cooking Element | U51: Electricity | V51: =_xlfn.CONCAT( R51, " -:- ", S51, " -:- ", T51, " -:- ", U51) -> Residential -:- Joined Dwellings -:- Cooking Element -:- Electricity | W51: =+RES!D42 -> Joined dwellings - Heat/Cooling Devices - Cooking Appliances | X51: PJ | Y51: GW
P52: DMD | Q52: =+RES!C43 -> R_JDW-CK_Appl-LPG00 | R52: Residential | S52: Joined Dwellings | T52: Cooking Element | U52: LPG | V52: =_xlfn.CONCAT( R52, " -:- ", S52, " -:- ", T52, " -:- ", U52) -> Residential -:- Joined Dwellings -:- Cooking Element -:- LPG | W52: =+RES!D43 -> Joined dwellings - Heat/Cooling Devices - Cooking Appliances | X52: PJ | Y52: GW
P53: DMD | Q53: =+RES!C44 -> R_JDW-RF_Refriger-ELC00 | R53: Residential | S53: Joined Dwellings | T53: Refrigerator | U53: Electricity | V53: =_xlfn.CONCAT( R53, " -:- ", S53, " -:- ", T53, " -:- ", U53) -> Residential -:- Joined Dwellings -:- Refrigerator -:- Electricity | W53: =+RES!D44 -> Joined dwellings - Heat/Cooling Devices - Refrigeration systems | X53: PJ | Y53: GW
... P63: DMD | Q63: =+RES!C54 -> R_JDW-MPM_ICE-PET00 | R63: Residential | S63: Joined Dwellings | T63: Mobile Motor | U63: Petrol | V63: =_xlfn.CONCAT( R63, " -:- ", S63, " -:- ", T63, " -:- ", U63) -> Residential -:- Joined Dwellings -:- Mobile Motor -:- Petrol | W63: =+RES!D54 -> Joined dwellings - Stationary Motors - Internal Combustion (Domestic Use) | X63: PJ | Y63: GW

Sheet RES_fuel_dem
B1: Fuel supply to residential sector
E3: ~FI_T
C4: TechName | D4: Comm-IN | E4: Comm-OUT | F4: Share-I~UP | G4: STOCK | H4: EFF | I4: LIFE | J4: INVCOST | K4: FIXOM | L4: VAROM
C5: *Technology Name | D5: Input Commodity | E5: Output Commodity | F5: Input Share | G5: Existing Installed Capacity | H5: Efficiency | I5: Lifetime | J5: Capital costs | K5: Fixed O&M | L5: Variable O&M
C6: *Units | G6: PJa | I6: Years | J6: MNZD/Pja | K6: MNZD/Pja | L6: MNZD/PJ
C7: =RES_techs_coms!Q8 -> FTE_RESCOA_00 | D7: COA | E7: =MID(C7,5,6) -> RESCOA | F7: 1 | H7: 1 | I7: 100
D8: COL | F8: 1
C9: =RES_techs_coms!Q9 -> FTE_RESNGA_00 | D9: NGA | E9: =MID(C9,5,6) -> RESNGA | H9: 1 | I9: 100 | L9: 25
C10: =RES_techs_coms!Q10 -> FTE_RESLPG_00 | D10: LPG | E10: =MID(C10,5,6) -> RESLPG | H10: 1 | I10: 100
C11: =RES_techs_coms!Q11 -> FTE_RESDSL_00 | D11: DSL | E11: =MID(C11,5,6) -> RESDSL | H11: 1 | I11: 100 | L11: 0.92
C12: =RES_techs_coms!Q12 -> FTE_RESWOD_00 | D12: WOD | E12: =MID(C12,5,6) -> RESWOD | H12: 1 | I12: 100 | L12: 10
C13: =RES_techs_coms!Q13 -> FTE_RESGEO_00 | D13: GEO | E13: =MID(C13,5,6) -> RESGEO | H13: 1 | I13: 100
C14: =RES_techs_coms!Q14 -> FTE_RESSOL_00 | D14: SOL | E14: =MID(C14,5,6) -> RESSOL | H14: 1 | I14: 100
C15: =RES_techs_coms!Q15 -> FTE_RESPET_00 | D15: PET | E15: =MID(C15,5,6) -> RESPET | H15: 1 | I15: 100 | L15: 0.92
C18: ~FI_T
C19: CommName | D19: Demand~2018 | E19: Demand~2020 | F19: Demand~2025 | G19: Demand~2030 | H19: Demand~2040 | I19: Demand~2050 | J19: Demand~2060
C20: =RES_techs_coms!C17 -> R_DDW-SH | D20: =ROUNDDOWN(SUMIF(RES!$F$7:$F$62,C20,RES!$N$7:$N$62),3) -> 10.134 | E20: =+D20 -> 10.134 | F20: =+E20 -> 10.134 | G20: =+F20 -> 10.134 | H20: =+G20 -> 10.134 | I20: =+H20 -> 10.134 | J20: =+I20 -> 10.134
C21: =RES_techs_coms!C18 -> R_DDW-WH | D21: =ROUNDDOWN(SUMIF(RES!$F$7:$F$62,C21,RES!$N$7:$N$62),3) -> 3.324 | E21: =+D21 -> 3.324 | F21: =+E21 -> 3.324 | G21: =+F21 -> 3.324 | H21: =+G21 -> 3.324 | I21: =+H21 -> 3.324 | J21: =+I21 -> 3.324
C22: =RES_techs_coms!C19 -> R_DDW-CK | D22: =ROUNDDOWN(SUMIF(RES!$F$7:$F$62,C22,RES!$N$7:$N$62),3) -> 0.61 | E22: =+D22 -> 0.61 | F22: =+E22 -> 0.61 | G22: =+F22 -> 0.61 | H22: =+G22 -> 0.61 | I22: =+H22 -> 0.61 | J22: =+I22 -> 0.61
C23: =RES_techs_coms!C20 -> R_DDW-RF | D23: =ROUNDDOWN(SUMIF(RES!$F$7:$F$62,C23,RES!$N$7:$N$62),3) -> 1.801 | E23: =+D23 -> 1.801 | F23: =+E23 -> 1.801 | G23: =+F23 -> 1.801 | H23: =+G23 -> 1.801 | I23: =+H23 -> 1.801 | J23: =+I23 -> 1.801
C24: =RES_techs_coms!C21 -> R_DDW-CD | D24: =ROUNDDOWN(SUMIF(RES!$F$7:$F$62,C24,RES!$N$7:$N$62),3) -> 0.052 | E24: =+D24 -> 0.052 | F24: =+E24 -> 0.052 | G24: =+F24 -> 0.052 | H24: =+G24 -> 0.052 | I24: =+H24 -> 0.052 | J24: =+I24 -> 0.052
C25: =RES_techs_coms!C22 -> R_DDW-SC | D25: =ROUNDDOWN(SUMIF(RES!$F$7:$F$62,C25,RES!$N$7:$N$62),3) -> 0.371 | E25: =+D25 -> 0.371 | F25: =+E25 -> 0.371 | G25: =+F25 -> 0.371 | H25: =+G25 -> 0.371 | I25: =+H25 -> 0.371 | J25: =+I25 -> 0.371
C26: =RES_techs_coms!C23 -> R_DDW-CW | D26: =ROUNDDOWN(SUMIF(RES!$F$7:$F$62,C26,RES!$N$7:$N$62),3) -> 0.169 | E26: =+D26 -> 0.169 | F26: =+E26 -> 0.169 | G26: =+F26 -> 0.169 | H26: =+G26 -> 0.169 | I26: =+H26 -> 0.169 | J26: =+I26 -> 0.169
C27: =RES_techs_coms!C24 -> R_DDW-DW | D27: =ROUNDDOWN(SUMIF(RES!$F$7:$F$62,C27,RES!$N$7:$N$62),3) -> 0.056 | E27: =+D27 -> 0.056 | F27: =+E27 -> 0.056 | G27: =+F27 -> 0.056 | H27: =+G27 -> 0.056 | I27: =+H27 -> 0.056 | J27: =+I27 -> 0.056
C28: =RES_techs_coms!C25 -> R_DDW-LT | D28: =ROUNDDOWN(SUMIF(RES!$F$7:$F$62,C28,RES!$N$7:$N$62),3) -> 0.174 | E28: =+D28 -> 0.174 | F28: =+E28 -> 0.174 | G28: =+F28 -> 0.174 | H28: =+G28 -> 0.174 | I28: =+H28 -> 0.174 | J28: =+I28 -> 0.174
C29: =RES_techs_coms!C26 -> R_DDW-OTH | D29: =ROUNDDOWN(SUMIF(RES!$F$7:$F$62,C29,RES!$N$7:$N$62),3) -> 0.654 | E29: =+D29 -> 0.654 | F29: =+E29 -> 0.654 | G29: =+F29 -> 0.654 | H29: =+G29 -> 0.654 | I29: =+H29 -> 0.654 | J29: =+I29 -> 0.654
C30: =RES_techs_coms!C27 -> R_DDW-MPS | D30: =ROUNDDOWN(SUMIF(RES!$F$7:$F$62,C30,RES!$N$7:$N$62),3) -> 0.051 | E30: =+D30 -> 0.051 | F30: =+E30 -> 0.051 | G30: =+F30 -> 0.051 | H30: =+G30 -> 0.051 | I30: =+H30 -> 0.051 | J30: =+I30 -> 0.051
C31: =RES_techs_coms!C28 -> R_DDW-MPM | D31: =ROUNDDOWN(SUMIF(RES!$F$7:$F$62,C31,RES!$N$7:$N$62),3) -> 0 | E31: =+D31 -> 0 | F31: =+E31 -> 0 | G31: =+F31 -> 0 | H31: =+G31 -> 0 | I31: =+H31 -> 0 | J31: =+I31 -> 0
... C43: =RES_techs_coms!C40 -> R_JDW-MPM | D43: =ROUNDDOWN(SUMIF(RES!$F$7:$F$62,C43,RES!$N$7:$N$62),3) -> 0 | E43: =+D43 -> 0 | F43: =+E43 -> 0 | G43: =+F43 -> 0 | H43: =+G43 -> 0 | I43: =+H43 -> 0 | J43: =+I43 -> 0

Sheet RES
F4: ~FI_T
C5: TechName | D5: *TechDesc | E5: Comm-IN | F5: Comm-OUT | G5: EFF | H5: AFA | I5: AFA~LO | J5: NCAP_TLIFE | K5: CAP2ACT | L5: NCAP_PASTI | M5: *NCAP_PASTI | N5: ACT_BND | O5: INVCOST | P5: FIXOM | Q5: NCAP_BND | R5: NCAP_BND~0 | S5: FLO_MARK | T5: FLO_MARK~2030 | U5: FLO_MARK~2050 | V5: FLO_MARK~0
C6: \I: Technology Name | D6: Technology Description | E6: Input Commodity | F6: Output Commodity | G6: Efficiency | H6: Annual Availability Factor | I6: Annual Availability Factor | J6: Lifetime of Process | K6: Capacity to Activity Factor | L6: Existing Installed Capacity in Pja | N6: Bound on activity of a process | O6: Investment cost | P6: O&M costs
C7: =+[6]SI!J2 -> R_DDW-SH_Burner-WOD00 | D7: =+[6]SI!A2&" - "&[6]SI!C2&" - "&[6]SI!D2 -> Detached dwellings - Heat/Cooling Devices - Burner (Direct Heat) | E7: =+[6]SI!K2 -> RESWOD | F7: =+[6]SI!L2 -> R_DDW-SH | G7: =+[6]SI!O2 -> 0.6 | H7: =+[6]SI!Q2 -> 0.0821 | I7: =+IF(L7>0.01,H7*0.75,0) -> 0.061575 | J7: =+[6]SI!P2 -> 20 | K7: 31.536 | L7: =+N7/K7/H7 -> 0.63556873 | N7: 1.6455546 | O7: 373 | S7: =+N7/SUM(N7:N15) -> 0.16236589 | V7: 5
C8: =+[6]SI!J3 -> R_DDW-SH_Burner-LPG00 | D8: =+[6]SI!A3&" - "&[6]SI!C3&" - "&[6]SI!D3 -> Detached dwellings - Heat/Cooling Devices - Burner (Direct Heat) | E8: =+[6]SI!K3 -> RESLPG | F8: =+[6]SI!L3 -> R_DDW-SH | G8: =+[6]SI!O3 -> 0.8 | H8: =+[6]SI!Q3 -> 0.0821 | I8: =+IF(L8>0.01,H8*0.75,0) -> 0.061575 | J8: =+[6]SI!P3 -> 20 | K8: 31.536 | L8: =+N8/K8/H8 -> 0.12896287 | N8: 0.33389849 | O8: =+[6]SI!U3 -> 1260 | P8: =+[6]SI!V3 -> 150
C9: =+[6]SI!J4 -> R_DDW-SH_Burner-DSL00 | D9: =+[6]SI!A4&" - "&[6]SI!C4&" - "&[6]SI!D4 -> Detached dwellings - Heat/Cooling Devices - Burner (Direct Heat) | E9: =+[6]SI!K4 -> RESDSL | F9: =+[6]SI!L4 -> R_DDW-SH | G9: =+[6]SI!O4 -> 0.8 | H9: =+[6]SI!Q4 -> 0.0045 | I9: =+IF(L9>0.01,H9*0.75,0) -> 0.003375 | J9: 5 | K9: 31.536 | L9: =+N9/K9/H9 -> 0.21598682 | N9: 0.030651122 | Q9: 0 | R9: 5
C10: =+[6]SI!J5 -> R_DDW-SH_Burner-COA00 | D10: =+[6]SI!A5&" - "&[6]SI!C5&" - "&[6]SI!D5 -> Detached dwellings - Heat/Cooling Devices - Burner (Direct Heat) | E10: =+[6]SI!K5 -> RESCOA | F10: =+[6]SI!L5 -> R_DDW-SH | G10: =+[6]SI!O5 -> 0.6 | H10: =+[6]SI!Q5 -> 0.0045 | I10: =+IF(L10>0.01,H10*0.75,0) -> 0.003375 | J10: 5 | K10: 31.536 | L10: =+N10/K10/H10 -> 0.1414572 | N10: 0.020074474 | Q10: 0 | R10: 5
C11: =+[6]SI!J6 -> R_DDW-SH_OF-WOD00 | D11: =+[6]SI!A6&" - "&[6]SI!C6&" - "&[6]SI!D6 -> Detached dwellings - Heat/Cooling Devices - Open Fire | E11: =+[6]SI!K6 -> RESWOD | F11: =+[6]SI!L6 -> R_DDW-SH | G11: =+[6]SI!O6 -> 0.06 | H11: =+[6]SI!Q6 -> 0.0821 | I11: =+IF(L11>0.01,H11*0.75,0) -> 0 | J11: =+[6]SI!P6 -> 50 | K11: 31.536 | L11: =+N11/K11/H11 -> 0.0019528039 | N11: 0.0050560155 | Q11: 0 | R11: 5
C12: =+[6]SI!J7 -> R_DDW-SH_OF-COA00 | D12: =+[6]SI!A7&" - "&[6]SI!C7&" - "&[6]SI!D7 -> Detached dwellings - Heat/Cooling Devices - Open Fire | E12: =+[6]SI!K7 -> RESCOA | F12: =+[6]SI!L7 -> R_DDW-SH | G12: =+[6]SI!O7 -> 0.06 | H12: =+[6]SI!Q7 -> 0.0821 | I12: =+IF(L12>0.01,H12*0.75,0) -> 0 | J12: =+[6]SI!P7 -> 50 | K12: 31.536 | L12: =+N12/K12/H12 -> 0.0014953223 | N12: 0.0038715473 | Q12: 0 | R12: 5
C13: =+[6]SI!J8 -> R_DDW-SH_OFWB-COA00 | D13: =+[6]SI!A8&" - "&[6]SI!C8&" - "&[6]SI!D8 -> Detached dwellings - Heat/Cooling Devices - Open Fire, with Wetback | E13: =+[6]SI!K8 -> RESCOA | F13: =+[6]SI!L8 -> R_DDW-SH | G13: =+[6]SI!O8 -> 0.06 | H13: =+[6]SI!Q8 -> 0.0821 | I13: =+IF(L13>0.01,H13*0.75,0) -> 0 | J13: =+[6]SI!P8 -> 50 | K13: 31.536 | L13: =+N13/K13/H13 -> 0.00017711276 | N13: 0.00045856365 | Q13: 0 | R13: 5
C14: =+[6]SI!J9 -> R_DDW-SH_HP-ELC00 | D14: =+[6]SI!A9&" - "&[6]SI!C9&" - "&[6]SI!D9 -> Detached dwellings - Heat/Cooling Devices - Heat Pump (for Heating) | E14: =+[6]SI!K9 -> RESELC | F14: =+[6]SI!L9 -> R_DDW-SH | G14: =+[6]SI!O9 -> 3.75 | H14: =+[6]SI!Q9 -> 0.0821 | I14: =+IF(L14>0.01,H14*0.75,0) -> 0.061575 | J14: =+[6]SI!P9 -> 12 | K14: 31.536 | L14: =+N14/K14/H14 -> 2.5591375 | N14: 6.6258772 | O14: =+[6]SI!U9 -> 557.90698
C15: =+[6]SI!J10 -> R_DDW-SH_RH-ELC00 | D15: =+[6]SI!A10&" - "&[6]SI!C10&" - "&[6]SI!D10 -> Detached dwellings - Heat/Cooling Devices - Resistance Heater | E15: =+[6]SI!K10 -> RESELC | F15: =+[6]SI!L10 -> R_DDW-SH | G15: =+[6]SI!O10 -> 1 | H15: =+[6]SI!Q10 -> 0.0821 | I15: =+IF(L15>0.01,H15*0.75,0) -> 0.061575 | J15: =+[6]SI!P10 -> 5 | K15: 31.536 | L15: =+N15/K15/H15 -> 0.56753642 | N15: 1.4694117 | O15: =+[6]SI!U10 -> 24
C16: =+[6]SI!J11 -> R_DDW-WH_OFWB-COA00 | D16: =+[6]SI!A11&" - "&[6]SI!C11&" - "&[6]SI!D11 -> Detached dwellings - Heat/Cooling Devices - Open Fire, with Wetback | E16: =+[6]SI!K11 -> RESCOA | F16: =+[6]SI!L11 -> R_DDW-WH | G16: =+[6]SI!O11 -> 0.16 | H16: =+[6]SI!Q11 -> 0.1666 | I16: =+IF(L16>0.01,H16*0.75,0) -> 0 | J16: =+[6]SI!P11 -> 50 | K16: 31.536 | L16: =+N16/K16/H16 -> 0.00013277296 | N16: 0.00069757556 | Q16: 0 | R16: 5
C17: =+[6]SI!J12 -> R_DDW-WH_HWC-SOL00 | D17: =+[6]SI!A12&" - "&[6]SI!C12&" - "&[6]SI!D12 -> Detached dwellings - Heat/Cooling Devices - Hot Water Cylinder | E17: =+[6]SI!K12 -> RESSOL | F17: =+[6]SI!L12 -> R_DDW-WH | G17: =+[6]SI!O12 -> 0.6 | H17: 0.125 | J17: =+[6]SI!P12 -> 20 | K17: 31.536 | L17: =+N17/K17/H17 -> 0.0107135 | N17: 0.042232617 | O17: 2121 | Q17: 0 | R17: 5
C18: =+[6]SI!J13 -> R_DDW-WH_HWC-ELC00 | D18: =+[6]SI!A13&" - "&[6]SI!C13&" - "&[6]SI!D13 -> Detached dwellings - Heat/Cooling Devices - Hot Water Cylinder | E18: =+[6]SI!K13 -> RESELC | F18: =+[6]SI!L13 -> R_DDW-WH | G18: =+[6]SI!O13 -> 1 | H18: 0.125 | I18: =+IF(L18>0.01,H18*0.75,0) -> 0.09375 | J18: =+[6]SI!P13 -> 20 | K18: 31.536 | L18: =+N18/K18/H18 -> 0.74136203 | N18: 2.9224491 | O18: 757.6
C19: =+[6]SI!J14 -> R_DDW-WH_Gasheat-LPG00 | D19: =+[6]SI!A14&" - "&[6]SI!C14&" - "&[6]SI!D14 -> Detached dwellings - Heat/Cooling Devices - Gas Water Heater | E19: =+[6]SI!K14 -> RESLPG | F19: =+[6]SI!L14 -> R_DDW-WH | G19: =+[6]SI!O14 -> 0.8 | H19: 0.042 | I19: =+IF(L19>0.01,H19*0.75,0) -> 0.0315 | J19: =+[6]SI!P14 -> 20 | K19: 31.536 | L19: =+N19/K19/H19 -> 0.26867739 | N19: 0.35586642 | O19: 250 | P19: =+[6]SI!V14 -> 150
C20: =+[6]SI!J15 -> R_DDW-WH_BRNWB-WOD00 | D20: =+[6]SI!A15&" - "&[6]SI!C15&" - "&[6]SI!D15 -> Detached dwellings - Heat/Cooling Devices - Burner, with Wetback | E20: =+[6]SI!K15 -> RESWOD | F20: =+[6]SI!L15 -> R_DDW-WH | G20: =+[6]SI!O15 -> 0.16 | H20: =+[6]SI!Q15 -> 0.1666 | I20: =+IF(L20>0.01,H20*0.75,0) -> 0 | J20: =+[6]SI!P15 -> 20 | K20: 31.536 | L20: =+N20/K20/H20 -> 0.00060156564 | N20: 0.0031605643 | Q20: 0 | R20: 5
C21: =+[6]SI!J16 -> R_DDW-CK_Oven-COA00 | D21: =+[6]SI!A16&" - "&[6]SI!C16&" - "&[6]SI!D16 -> Detached dwellings - Heat/Cooling Devices - Cooking Ovens | E21: =+[6]SI!K16 -> RESCOA | F21: =+[6]SI!L16 -> R_DDW-CK | G21: =+[6]SI!O16 -> 0.15 | H21: 1 | I21: =+IF(L21>0.01,H21*0.75,0) -> 0 | J21: =+[6]SI!P16 -> 10 | K21: 31.536 | L21: =+N21/K21/H21 -> 2.0072912e-06 | N21: 6.3301936e-05 | Q21: 0 | R21: 5
C22: =+[6]SI!J17 -> R_DDW-CK_Appl-ELC00 | D22: =+[6]SI!A17&" - "&[6]SI!C17&" - "&[6]SI!D17 -> Detached dwellings - Heat/Cooling Devices - Cooking Appliances | E22: =+[6]SI!K17 -> RESELC | F22: =+[6]SI!L17 -> R_DDW-CK | G22: =+[6]SI!O17 -> 0.75 | H22: =+[6]SI!Q17 -> 0.0416 | I22: =+IF(L22>0.01,H22*0.75,0) -> 0.0312 | J22: =+[6]SI!P17 -> 13 | K22: 31.536 | L22: =+N22/K22/H22 -> 0.46216966 | N22: 0.60631927 | O22: =+[6]SI!U17 -> 450
C23: =+[6]SI!J18 -> R_DDW-CK_Appl-LPG00 | D23: =+[6]SI!A18&" - "&[6]SI!C18&" - "&[6]SI!D18 -> Detached dwellings - Heat/Cooling Devices - Cooking Appliances | E23: =+[6]SI!K18 -> RESLPG | F23: =+[6]SI!L18 -> R_DDW-CK | G23: =+[6]SI!O18 -> 0.4 | H23: =+[6]SI!Q18 -> 0.0416 | I23: =+IF(L23>0.01,H23*0.75,0) -> 0 | J23: =+[6]SI!P18 -> 13 | K23: 31.536 | L23: =+N23/K23/H23 -> 0.0032847737 | N23: 0.0043092868 | O23: =+[6]SI!U18 -> 350 | P23: =+[6]SI!V18 -> 150
C24: =+[6]SI!J19 -> R_DDW-RF_Refriger-ELC00 | D24: =+[6]SI!A19&" - "&[6]SI!C19&" - "&[6]SI!D19 -> Detached dwellings - Heat/Cooling Devices - Refrigeration systems | E24: =+[6]SI!K19 -> RESELC | F24: =+[6]SI!L19 -> R_DDW-RF | G24: =+[6]SI!O19 -> 1.8 | H24: =+[6]SI!Q19 -> 1 | I24: =+IF(L24>0.01,H24*0.75,0) -> 0.75 | J24: =+[6]SI!P19 -> 18 | K24: 31.536 | L24: =+N24/K24/H24 -> 0.057118833 | N24: 1.8012995 | O24: =+[6]SI!U19 -> 3280
C25: =+[6]SI!J20 -> R_DDW-CD_Dryer-ELC00 | D25: =+[6]SI!A20&" - "&[6]SI!C20&" - "&[6]SI!D20 -> Detached dwellings - Heat/Cooling Devices - Clothes Dryer | E25: =+[6]SI!K20 -> RESELC | F25: =+[6]SI!L20 -> R_DDW-CD | G25: =+[6]SI!O20 -> 0.25 | H25: =+[6]SI!Q20 -> 0.0059 | I25: =+IF(L25>0.01,H25*0.75,0) -> 0.004425 | J25: =+[6]SI!P20 -> 15 | K25: 31.536 | L25: =+N25/K25/H25 -> 0.28141489 | N25: 0.052360729 | O25: =+[6]SI!U20 -> 1665.3333
C26: =+[6]SI!J21 -> R_DDW-SC_HP-ELC00 | D26: =+[6]SI!A21&" - "&[6]SI!C21&" - "&[6]SI!D21 -> Detached dwellings - Heat/Cooling Devices - Heat Pump (for Cooling) | E26: =+[6]SI!K21 -> RESELC | F26: =+[6]SI!L21 -> R_DDW-SC | G26: =+[6]SI!O21 -> 3.45 | H26: =+[6]SI!Q21 -> 0.0114 | I26: =+IF(L26>0.01,H26*0.75,0) -> 0.00855 | J26: =+[6]SI!P21 -> 12 | K26: 31.536 | L26: =+N26/K26/H26 -> 1.0338071 | N26: 0.3716644 | O26: =+[6]SI!U21 -> 685.42857
C27: =+[6]SI!J22 -> R_DDW-CW_Washer-ELC00 | D27: =+[6]SI!A22&" - "&[6]SI!C22&" - "&[6]SI!D22 -> Detached dwellings - Heat/Cooling Devices - Clothes Washers | E27: =+[6]SI!K22 -> RESELC | F27: =+[6]SI!L22 -> R_DDW-CW | G27: =+[6]SI!O22 -> 0.25 | H27: =+[6]SI!Q22 -> 0.0416 | I27: =+IF(L27>0.01,H27*0.75,0) -> 0.0312 | J27: =+[6]SI!P22 -> 15 | K27: 31.536 | L27: =+N27/K27/H27 -> 0.12918113 | N27: 0.16947242 | O27: =+[6]SI!U22 -> 3994.6667
C28: =+[6]SI!J23 -> R_DDW-DW_Dwash-ELC00 | D28: =+[6]SI!A23&" - "&[6]SI!C23&" - "&[6]SI!D23 -> Detached dwellings - Heat/Cooling Devices - Dishwashers | E28: =+[6]SI!K23 -> RESELC | F28: =+[6]SI!L23 -> R_DDW-DW | G28: =+[6]SI!O23 -> 0.25 | H28: =+[6]SI!Q23 -> 0.0416 | I28: =+IF(L28>0.01,H28*0.75,0) -> 0.0312 | J28: =+[6]SI!P23 -> 15 | K28: 31.536 | L28: =+N28/K28/H28 -> 0.042902799 | N28: 0.056284079 | O28: =+[6]SI!U23 -> 2640
C29: =+[6]SI!J24 -> R_DDW-LT_LED-ELC00 | D29: =+[6]SI!A24&" - "&[6]SI!C24&" - "&[6]SI!D24 -> Detached dwellings - Electronics and Lights - LED | E29: =+[6]SI!K24 -> RESELC | F29: =+[6]SI!L24 -> R_DDW-LT | G29: =+[6]SI!O24 -> 0.9 | H29: =+[6]SI!Q24 -> 0.1666 | I29: =+IF(L29>0.01,H29*0.75,0) -> 0 | J29: =+[6]SI!P24 -> 14 | K29: 31.536 | L29: =+N29/K29/H29 -> 0.00089504257 | N29: 0.004702462 | O29: =+[6]SI!U24 -> 1148.3254
C30: =+[6]SI!J25 -> R_DDW-LT_Incan-ELC00 | D30: =+[6]SI!A25&" - "&[6]SI!C25&" - "&[6]SI!D25 -> Detached dwellings - Electronics and Lights - Incandescent | E30: =+[6]SI!K25 -> RESELC | F30: =+[6]SI!L25 -> R_DDW-LT | G30: =+[6]SI!O25 -> 0.1 | H30: =+[6]SI!Q25 -> 0.1666 | I30: =+IF(L30>0.01,H30*0.75,0) -> 0.12495 | J30: =+[6]SI!P25 -> 1 | K30: 31.536 | L30: =+N30/K30/H30 -> 0.016059045 | N30: 0.084372576 | O30: =+[6]SI!U25 -> 777.77778
C31: =+[6]SI!J26 -> R_DDW-LT_CFL-ELC00 | D31: =+[6]SI!A26&" - "&[6]SI!C26&" - "&[6]SI!D26 -> Detached dwellings - Electronics and Lights - Fluorescent | E31: =+[6]SI!K26 -> RESELC | F31: =+[6]SI!L26 -> R_DDW-LT | G31: =+[6]SI!O26 -> 0.8 | H31: =+[6]SI!Q26 -> 0.1666 | I31: =+IF(L31>0.01,H31*0.75,0) -> 0.12495 | J31: =+[6]SI!P26 -> 7 | K31: 31.536 | L31: =+N31/K31/H31 -> 0.016335394 | N31: 0.085824489 | O31: =+[6]SI!U26 -> 1176.4706
C32: =+[6]SI!J27 -> R_DDW-OTH_Elec-ELC00 | D32: =+[6]SI!A27&" - "&[6]SI!C27&" - "&[6]SI!D27 -> Detached dwellings - Electronics and Lights - Electronics | E32: =+[6]SI!K27 -> RESELC | F32: =+[6]SI!L27 -> R_DDW-OTH | G32: =+[6]SI!O27 -> 0.9 | H32: =+[6]SI!Q27 -> 0.1666 | I32: =+IF(L32>0.01,H32*0.75,0) -> 0.12495 | J32: =+[6]SI!P27 -> 5 | K32: 31.536 | L32: =+N32/K32/H32 -> 0.1245404 | N32: 0.65432253 | O32: =+[6]SI!U27 -> 733.33333
C33: =+[6]SI!J28 -> R_DDW-MPS_Motor-ELC00 | D33: =+[6]SI!A28&" - "&[6]SI!C28&" - "&[6]SI!D28 -> Detached dwellings - Stationary Motors - Electric Motor | E33: =+[6]SI!K28 -> RESELC | F33: =+[6]SI!L28 -> R_DDW-MPS | G33: =+[6]SI!O28 -> 0.75 | H33: =+[6]SI!Q28 -> 0.0029 | I33: =+IF(L33>0.01,H33*0.75,0) -> 0.002175 | J33: =+[6]SI!P28 -> 15 | K33: 31.536 | L33: =+N33/K33/H33 -> 0.56739312 | N33: 0.051890597 | O33: =+[6]SI!U28 -> 153.33333
C34: =+[6]SI!J29 -> R_DDW-MPM_ICE-PET00 | D34: =+[6]SI!A29&" - "&[6]SI!C29&" - "&[6]SI!D29 -> Detached dwellings - Stationary Motors - Internal Combustion (Domestic Use) | E34: =+[6]SI!K29 -> RESPET | F34: =+[6]SI!L29 -> R_DDW-MPM | G34: =+[6]SI!O29 -> 0.25 | H34: =+[6]SI!Q29 -> 0.0029 | I34: =+IF(L34>0.01,H34*0.75,0) -> 0 | J34: =+[6]SI!P29 -> 10 | K34: 31.536 | L34: =+N34/K34/H34 -> 0.00014231057 | N34: 1.3014928e-05 | O34: =+[6]SI!U29 -> 1466.6667
C35: =+[6]SI!J30 -> R_JDW-SH_Burner-LPG00 | D35: =+[6]SI!A30&" - "&[6]SI!C30&" - "&[6]SI!D30 -> Joined dwellings - Heat/Cooling Devices - Burner (Direct Heat) | E35: =+[6]SI!K30 -> RESLPG | F35: =+[6]SI!L30 -> R_JDW-SH | G35: =+[6]SI!O30 -> 0.8 | H35: =+[6]SI!Q30 -> 0.0821 | I35: =+IF(L35>0.01,H35*0.75,0) -> 0.061575 | J35: =+[6]SI!P30 -> 20 | K35: 31.536 | L35: =+N35/K35/H35 -> 0.02081979 | N35: 0.053904635 | O35: =+[6]SI!U30 -> 807.46269 | P35: =+[6]SI!V30 -> 150
C36: =+[6]SI!J31 -> R_JDW-SH_Burner-DSL00 | D36: =+[6]SI!A31&" - "&[6]SI!C31&" - "&[6]SI!D31 -> Joined dwellings - Heat/Cooling Devices - Burner (Direct Heat) | E36: =+[6]SI!K31 -> RESDSL | F36: =+[6]SI!L31 -> R_JDW-SH | G36: =+[6]SI!O31 -> 0.8 | H36: =+[6]SI!Q31 -> 0.0045 | I36: =+IF(L36>0.01,H36*0.75,0) -> 0.003375 | J36: 5 | K36: 31.536 | L36: =+N36/K36/H36 -> 0.034868953 | N36: 0.0049483229 | Q36: 0 | R36: 5
C37: =+[6]SI!J32 -> R_JDW-SH_HP-ELC00 | D37: =+[6]SI!A32&" - "&[6]SI!C32&" - "&[6]SI!D32 -> Joined dwellings - Heat/Cooling Devices - Heat Pump (for Heating) | E37: =+[6]SI!K32 -> RESELC | F37: =+[6]SI!L32 -> R_JDW-SH | G37: =+[6]SI!O32 -> 3.75 | H37: =+[6]SI!Q32 -> 0.0821 | I37: =+IF(L37>0.01,H37*0.75,0) -> 0.061575 | J37: =+[6]SI!P32 -> 12 | K37: 31.536 | L37: =+N37/K37/H37 -> 0.41314763 | N37: 1.0696829 | O37: =+[6]SI!U32 -> 702.8125
C38: =+[6]SI!J33 -> R_JDW-SH_RH-ELC00 | D38: =+[6]SI!A33&" - "&[6]SI!C33&" - "&[6]SI!D33 -> Joined dwellings - Heat/Cooling Devices - Resistance Heater | E38: =+[6]SI!K33 -> RESELC | F38: =+[6]SI!L33 -> R_JDW-SH | G38: =+[6]SI!O33 -> 1 | H38: =+[6]SI!Q33 -> 0.0821 | I38: =+IF(L38>0.01,H38*0.75,0) -> 0.061575 | J38: =+[6]SI!P33 -> 5 | K38: 31.536 | L38: =+N38/K38/H38 -> 0.091623185 | N38: 0.2372221 | O38: =+[6]SI!U33 -> 24
C39: =+[6]SI!J34 -> R_JDW-WH_HWC-SOL00 | D39: =+[6]SI!A34&" - "&[6]SI!C34&" - "&[6]SI!D34 -> Joined dwellings - Heat/Cooling Devices - Hot Water Cylinder | E39: =+[6]SI!K34 -> RESSOL | F39: =+[6]SI!L34 -> R_JDW-WH | G39: =+[6]SI!O34 -> 0.6 | H39: =+[6]SI!Q34 -> 0.0833 | J39: =+[6]SI!P34 -> 20 | K39: 31.536 | L39: =+N39/K39/H39 -> 0.0036927487 | N39: 0.0097006617 | O39: 2121 | Q39: 0 | R39: 5
C40: =+[6]SI!J35 -> R_JDW-WH_HWC-ELC00 | D40: =+[6]SI!A35&" - "&[6]SI!C35&" - "&[6]SI!D35 -> Joined dwellings - Heat/Cooling Devices - Hot Water Cylinder | E40: =+[6]SI!K35 -> RESELC | F40: =+[6]SI!L35 -> R_JDW-WH | G40: =+[6]SI!O35 -> 1 | H40: =+[6]SI!Q35 -> 0.0833 | I40: =+IF(L40>0.01,H40*0.75,0) -> 0.062475 | J40: =+[6]SI!P35 -> 20 | K40: 31.536 | L40: =+N40/K40/H40 -> 0.25553401 | N40: 0.67127477 | O40: 757.6
C41: =+[6]SI!J36 -> R_JDW-WH_Gasheat-LPG00 | D41: =+[6]SI!A36&" - "&[6]SI!C36&" - "&[6]SI!D36 -> Joined dwellings - Heat/Cooling Devices - Gas Water Heater | E41: =+[6]SI!K36 -> RESLPG | F41: =+[6]SI!L36 -> R_JDW-WH | G41: =+[6]SI!O36 -> 0.8 | H41: 0.028 | I41: =+IF(L41>0.01,H41*0.75,0) -> 0.021 | J41: =+[6]SI!P36 -> 20 | K41: 31.536 | L41: =+N41/K41/H41 -> 0.092571168 | N41: 0.081741082 | O41: 250 | P41: =+[6]SI!V36 -> 150
C42: =+[6]SI!J37 -> R_JDW-CK_Appl-ELC00 | D42: =+[6]SI!A37&" - "&[6]SI!C37&" - "&[6]SI!D37 -> Joined dwellings - Heat/Cooling Devices - Cooking Appliances | E42: =+[6]SI!K37 -> RESELC | F42: =+[6]SI!L37 -> R_JDW-CK | G42: =+[6]SI!O37 -> 0.75 | H42: =+[6]SI!Q37 -> 0.028 | I42: =+IF(L42>0.01,H42*0.75,0) -> 0.021 | J42: =+[6]SI!P37 -> 13 | K42: 31.536 | L42: =+N42/K42/H42 -> 0.1507285 | N42: 0.13309447 | O42: =+[6]SI!U37 -> 450
C43: =+[6]SI!J38 -> R_JDW-CK_Appl-LPG00 | D43: =+[6]SI!A38&" - "&[6]SI!C38&" - "&[6]SI!D38 -> Joined dwellings - Heat/Cooling Devices - Cooking Appliances | E43: =+[6]SI!K38 -> RESLPG | F43: =+[6]SI!L38 -> R_JDW-CK | G43: =+[6]SI!O38 -> 0.4 | H43: =+[6]SI!Q38 -> 0.028 | I43: =+IF(L43>0.01,H43*0.75,0) -> 0 | J43: =+[6]SI!P38 -> 13 | K43: 31.536 | L43: =+N43/K43/H43 -> 0.0010712712 | N43: 0.000945941 | O43: =+[6]SI!U38 -> 350 | P43: =+[6]SI!V38 -> 150
C44: =+[6]SI!J39 -> R_JDW-RF_Refriger-ELC00 | D44: =+[6]SI!A39&" - "&[6]SI!C39&" - "&[6]SI!D39 -> Joined dwellings - Heat/Cooling Devices - Refrigeration systems | E44: =+[6]SI!K39 -> RESELC | F44: =+[6]SI!L39 -> R_JDW-RF | G44: =+[6]SI!O39 -> 1.8 | H44: =+[6]SI!Q39 -> 1 | I44: =+IF(L44>0.01,H44*0.75,0) -> 0.75 | J44: =+[6]SI!P39 -> 18 | K44: 31.536 | L44: =+N44/K44/H44 -> 0.01253828 | N44: 0.39540721 | O44: =+[6]SI!U39 -> 3280
C45: =+[6]SI!J40 -> R_JDW-CD_Dryer-ELC00 | D45: =+[6]SI!A40&" - "&[6]SI!C40&" - "&[6]SI!D40 -> Joined dwellings - Heat/Cooling Devices - Clothes Dryer | E45: =+[6]SI!K40 -> RESELC | F45: =+[6]SI!L40 -> R_JDW-CD | G45: =+[6]SI!O40 -> 0.25 | H45: =+[6]SI!Q40 -> 0.0059 | I45: =+IF(L45>0.01,H45*0.75,0) -> 0.004425 | J45: =+[6]SI!P40 -> 15 | K45: 31.536 | L45: =+N45/K45/H45 -> 0.061774 | N45: 0.011493819 | O45: =+[6]SI!U40 -> 1665.3333
C46: =+[6]SI!J41 -> R_JDW-SC_HP-ELC00 | D46: =+[6]SI!A41&" - "&[6]SI!C41&" - "&[6]SI!D41 -> Joined dwellings - Heat/Cooling Devices - Heat Pump (for Cooling) | E46: =+[6]SI!K41 -> RESELC | F46: =+[6]SI!L41 -> R_JDW-SC | G46: =+[6]SI!O41 -> 3.45 | H46: =+[6]SI!Q41 -> 0.0114 | I46: =+IF(L46>0.01,H46*0.75,0) -> 0.00855 | J46: =+[6]SI!P41 -> 12 | K46: 31.536 | L46: =+N46/K46/H46 -> 0.22693327 | N46: 0.081584869 | O46: =+[6]SI!U41 -> 899.6
C47: =+[6]SI!J42 -> R_JDW-CW_Washer-ELC00 | D47: =+[6]SI!A42&" - "&[6]SI!C42&" - "&[6]SI!D42 -> Joined dwellings - Heat/Cooling Devices - Clothes Washers | E47: =+[6]SI!K42 -> RESELC | F47: =+[6]SI!L42 -> R_JDW-CW | G47: =+[6]SI!O42 -> 0.25 | H47: =+[6]SI!Q42 -> 0.0416 | I47: =+IF(L47>0.01,H47*0.75,0) -> 0.0312 | J47: =+[6]SI!P42 -> 15 | K47: 31.536 | L47: =+N47/K47/H47 -> 0.028356834 | N47: 0.037201263 | O47: =+[6]SI!U42 -> 3994.6667
C48: =+[6]SI!J43 -> R_JDW-DW_Dwash-ELC00 | D48: =+[6]SI!A43&" - "&[6]SI!C43&" - "&[6]SI!D43 -> Joined dwellings - Heat/Cooling Devices - Dishwashers | E48: =+[6]SI!K43 -> RESELC | F48: =+[6]SI!L43 -> R_JDW-DW | G48: =+[6]SI!O43 -> 0.25 | H48: =+[6]SI!Q43 -> 0.0416 | I48: =+IF(L48>0.01,H48*0.75,0) -> 0 | J48: =+[6]SI!P43 -> 15 | K48: 31.536 | L48: =+N48/K48/H48 -> 0.0094176875 | N48: 0.012355042 | O48: =+[6]SI!U43 -> 2640
C49: =+[6]SI!J44 -> R_JDW-LT_LED-ELC00 | D49: =+[6]SI!A44&" - "&[6]SI!C44&" - "&[6]SI!D44 -> Joined dwellings - Electronics and Lights - LED | E49: =+[6]SI!K44 -> RESELC | F49: =+[6]SI!L44 -> R_JDW-LT | G49: =+[6]SI!O44 -> 0.9 | H49: =+[6]SI!Q44 -> 0.1666 | I49: =+IF(L49>0.01,H49*0.75,0) -> 0 | J49: =+[6]SI!P44 -> 14 | K49: 31.536 | L49: =+N49/K49/H49 -> 0.00018613209 | N49: 0.00097791893 | O49: =+[6]SI!U44 -> 1148.3254
C50: =+[6]SI!J45 -> R_JDW-LT_Incan-ELC00 | D50: =+[6]SI!A45&" - "&[6]SI!C45&" - "&[6]SI!D45 -> Joined dwellings - Electronics and Lights - Incandescent | E50: =+[6]SI!K45 -> RESELC | F50: =+[6]SI!L45 -> R_JDW-LT | G50: =+[6]SI!O45 -> 0.1 | H50: =+[6]SI!Q45 -> 0.1666 | I50: =+IF(L50>0.01,H50*0.75,0) -> 0 | J50: =+[6]SI!P45 -> 1 | K50: 31.536 | L50: =+N50/K50/H50 -> 0.0023501041 | N50: 0.012347206 | O50: =+[6]SI!U45 -> 777.77778
C51: =+[6]SI!J46 -> R_JDW-LT_CFL-ELC00 | D51: =+[6]SI!A46&" - "&[6]SI!C46&" - "&[6]SI!D46 -> Joined dwellings - Electronics and Lights - Fluorescent | E51: =+[6]SI!K46 -> RESELC | F51: =+[6]SI!L46 -> R_JDW-LT | G51: =+[6]SI!O46 -> 0.8 | H51: =+[6]SI!Q46 -> 0.1666 | I51: =+IF(L51>0.01,H51*0.75,0) -> 0 | J51: =+[6]SI!P46 -> 7 | K51: 31.536 | L51: =+N51/K51/H51 -> 0.0042186097 | N51: 0.022164143 | O51: =+[6]SI!U46 -> 1176.4706
C52: =+[6]SI!J47 -> R_JDW-OTH_Elec-ELC00 | D52: =+[6]SI!A47&" - "&[6]SI!C47&" - "&[6]SI!D47 -> Joined dwellings - Electronics and Lights - Electronics | E52: =+[6]SI!K47 -> RESELC | F52: =+[6]SI!L47 -> R_JDW-OTH | G52: =+[6]SI!O47 -> 0.9 | H52: =+[6]SI!Q47 -> 0.1666 | I52: =+IF(L52>0.01,H52*0.75,0) -> 0.12495 | J52: =+[6]SI!P47 -> 5 | K52: 31.536 | L52: =+N52/K52/H52 -> 0.027338137 | N52: 0.14363177 | O52: =+[6]SI!U47 -> 733.33333
C53: =+[6]SI!J48 -> R_JDW-MPS_Motor-ELC00 | D53: =+[6]SI!A48&" - "&[6]SI!C48&" - "&[6]SI!D48 -> Joined dwellings - Stationary Motors - Electric Motor | E53: =+[6]SI!K48 -> RESELC | F53: =+[6]SI!L48 -> R_JDW-MPS | G53: =+[6]SI!O48 -> 0.75 | H53: =+[6]SI!Q48 -> 0.0029 | I53: =+IF(L53>0.01,H53*0.75,0) -> 0.002175 | J53: =+[6]SI!P48 -> 15 | K53: 31.536 | L53: =+N53/K53/H53 -> 0.12454971 | N53: 0.011390619 | O53: =+[6]SI!U48 -> 153.33333
C54: =+[6]SI!J49 -> R_JDW-MPM_ICE-PET00 | D54: =+[6]SI!A49&" - "&[6]SI!C49&" - "&[6]SI!D49 -> Joined dwellings - Stationary Motors - Internal Combustion (Domestic Use) | E54: =+[6]SI!K49 -> RESPET | F54: =+[6]SI!L49 -> R_JDW-MPM | G54: =+[6]SI!O49 -> 0.25 | H54: =+[6]SI!Q49 -> 0.0029 | I54: =+IF(L54>0.01,H54*0.75,0) -> 0 | J54: =+[6]SI!P49 -> 10 | K54: 31.536 | L54: =+N54/K54/H54 -> 3.1238906e-05 | N54: 2.8569354e-06 | O54: =+[6]SI!U49 -> 1466.6667

Sheet COM_techs
A5: ~FI_Comm | O5: ~FI_Process
A6: Csets | B6: CommName | C6: * Fuel | D6: * Enduse | E6: CommDesc | F6: * OLD CommDesc | G6: Unit | H6: LimType | I6: CTSLvl | J6: PeakTS | K6: Ctype | O6: Sets | P6: TechName | Q6: * Sector | R6: * Subsector | S6: * Technology | T6: * Fuel | U6: TechDesc | V6: * OLD TechDesc | W6: Tact | X6: Tcap | Y6: Tslvl | Z6: PrimaryCG | AA6: Vintage
A7: NRG | B7: COMCOA | C7: Coal | E7: =_xlfn.CONCAT(C7, " -:- ", D7 ) -> Coal -:- | F7: Commercial Coal | G7: PJ | H7: FX | O7: PRE | P7: ="FTE_"&B7&"_00" -> FTE_COMCOA_00 | Q7: Commercial | T7: Coal | U7: =_xlfn.CONCAT( Q7, " -:- ", R7, " -:- ", S7, " -:- ", T7) -> Commercial -:- -:- -:- Coal | V7: ="Distribution network for "&F7 -> Distribution network for Commercial Coal | W7: PJ | X7: PJ_a
A8: NRG | B8: COMNGA | C8: Natural Gas | E8: =_xlfn.CONCAT(C8, " -:- ", D8 ) -> Natural Gas -:- | F8: Commercial Natural gas | G8: PJ | H8: FX | O8: PRE | P8: ="FTE_"&B8&"_00" -> FTE_COMNGA_00 | Q8: Commercial | T8: Natural Gas | U8: =_xlfn.CONCAT( Q8, " -:- ", R8, " -:- ", S8, " -:- ", T8) -> Commercial -:- -:- -:- Natural Gas | V8: ="Distribution network for "&F8 -> Distribution network for Commercial Natural gas | W8: PJ | X8: PJ_a
A9: NRG | B9: COMLPG | C9: LPG | E9: =_xlfn.CONCAT(C9, " -:- ", D9 ) -> LPG -:- | F9: Commercial LPG | G9: PJ | H9: FX | O9: PRE | P9: ="FTE_"&B9&"_00" -> FTE_COMLPG_00 | Q9: Commercial | T9: LPG | U9: =_xlfn.CONCAT( Q9, " -:- ", R9, " -:- ", S9, " -:- ", T9) -> Commercial -:- -:- -:- LPG | V9: ="Distribution network for "&F9 -> Distribution network for Commercial LPG | W9: PJ | X9: PJ_a
A10: NRG | B10: COMDSL | C10: Diesel | E10: =_xlfn.CONCAT(C10, " -:- ", D10 ) -> Diesel -:- | F10: Commercial Diesel | G10: PJ | H10: FX | O10: PRE | P10: ="FTE_"&B10&"_00" -> FTE_COMDSL_00 | Q10: Commercial | T10: Diesel | U10: =_xlfn.CONCAT( Q10, " -:- ", R10, " -:- ", S10, " -:- ", T10) -> Commercial -:- -:- -:- Diesel | V10: ="Distribution network for "&F10 -> Distribution network for Commercial Diesel | W10: PJ | X10: PJ_a
A11: NRG | B11: COMBIG | C11: Biogas | E11: =_xlfn.CONCAT(C11, " -:- ", D11 ) -> Biogas -:- | F11: Commercial Biogas | G11: PJ | H11: FX | O11: PRE | P11: ="FTE_"&B11&"_00" -> FTE_COMBIG_00 | Q11: Commercial | T11: Biogas | U11: =_xlfn.CONCAT( Q11, " -:- ", R11, " -:- ", S11, " -:- ", T11) -> Commercial -:- -:- -:- Biogas | V11: ="Distribution network for "&F11 -> Distribution network for Commercial Biogas | W11: PJ | X11: PJ_a
A12: NRG | B12: COMGEO | C12: Geothermal | E12: =_xlfn.CONCAT(C12, " -:- ", D12 ) -> Geothermal -:- | F12: Commercial Geothermal | G12: PJ | H12: FX | O12: PRE | P12: ="FTE_"&B12&"_00" -> FTE_COMGEO_00 | Q12: Commercial | T12: Geothermal | U12: =_xlfn.CONCAT( Q12, " -:- ", R12, " -:- ", S12, " -:- ", T12) -> Commercial -:- -:- -:- Geothermal | V12: ="Distribution network for "&F12 -> Distribution network for Commercial Geothermal | W12: PJ | X12: PJ_a
A13: NRG | B13: COMFOL | C13: Fuel Oil | E13: =_xlfn.CONCAT(C13, " -:- ", D13 ) -> Fuel Oil -:- | F13: Commercial Fuel Oil | G13: PJ | H13: FX | O13: PRE | P13: ="FTE_"&B13&"_00" -> FTE_COMFOL_00 | Q13: Commercial | T13: Fuel Oil | U13: =_xlfn.CONCAT( Q13, " -:- ", R13, " -:- ", S13, " -:- ", T13) -> Commercial -:- -:- -:- Fuel Oil | V13: ="Distribution network for "&F13 -> Distribution network for Commercial Fuel Oil | W13: PJ | X13: PJ_a
A14: NRG | B14: COMPET | C14: Petrol | E14: =_xlfn.CONCAT(C14, " -:- ", D14 ) -> Petrol -:- | F14: Commercial petroleum | G14: PJ | H14: FX | O14: PRE | P14: ="FTE_"&B14&"_00" -> FTE_COMPET_00 | Q14: Commercial | T14: Petrol | U14: =_xlfn.CONCAT( Q14, " -:- ", R14, " -:- ", S14, " -:- ", T14) -> Commercial -:- -:- -:- Petrol | V14: ="Distribution network for "&F14 -> Distribution network for Commercial petroleum | W14: PJ | X14: PJ_a
A15: NRG | B15: COMWOD | C15: Wood | E15: =_xlfn.CONCAT(C15, " -:- ", D15 ) -> Wood -:- | F15: Commercial wood | G15: PJ | H15: FX | O15: PRE | P15: ="FTE_"&B15&"_00" -> FTE_COMWOD_00 | Q15: Commercial | T15: Wood | U15: =_xlfn.CONCAT( Q15, " -:- ", R15, " -:- ", S15, " -:- ", T15) -> Commercial -:- -:- -:- Wood | V15: ="Distribution network for "&F15 -> Distribution network for Commercial wood | W15: PJ | X15: PJ_a
A16: NRG | B16: COMPLT | C16: Wood | E16: =_xlfn.CONCAT(C16, " -:- ", D16 ) -> Wood -:- | F16: Commercial pellet | G16: PJ | H16: FX | O16: PRE | P16: ="FTE_"&B16&"_00" -> FTE_COMPLT_00 | Q16: Commercial | T16: Wood | U16: =_xlfn.CONCAT( Q16, " -:- ", R16, " -:- ", S16, " -:- ", T16) -> Commercial -:- -:- -:- Wood | V16: ="Distribution network for "&F16 -> Distribution network for Commercial pellet | W16: PJ | X16: PJ_a
A17: ENV | B17: COMCO2 | E17: =_xlfn.CONCAT(C17, " -:- ", D17 ) -> -:- | F17: Commercial sector CO2 | G17: kt | O17: DMD | P17: C_EDU-OTH_ELEC-ELC00 | Q17: Commercial | R17: Education | S17: Electronics and Other Appliances | T17: Electricity | U17: =_xlfn.CONCAT( Q17, " -:- ", R17, " -:- ", S17, " -:- ", T17) -> Commercial -:- Education -:- Electronics and Other Appliances -:- Electricity | V17: Education Electronics ELC | W17: PJ | X17: GW
A18: DEM | B18: C_EDU-OTH | D18: Electronics and Other Appliances | E18: =_xlfn.CONCAT(C18, " -:- ", D18 ) -> -:- Electronics and Other Appliances | F18: Education Other | G18: PJ | O18: DMD | P18: C_EDU-LT_INC-ELC00 | Q18: Commercial | R18: Education | S18: Lights (Incandescent) | T18: Electricity | U18: =_xlfn.CONCAT( Q18, " -:- ", R18, " -:- ", S18, " -:- ", T18) -> Commercial -:- Education -:- Lights (Incandescent) -:- Electricity | V18: Education Lighting Incandescent ELC | W18: PJ | X18: GW
A19: DEM | B19: C_EDU-LT | D19: Lighting | E19: =_xlfn.CONCAT(C19, " -:- ", D19 ) -> -:- Lighting | F19: Education Lighting | G19: PJ | O19: DMD | P19: C_EDU-LT_FLU-ELC00 | Q19: Commercial | R19: Education | S19: Lights (Fluorescent) | T19: Electricity | U19: =_xlfn.CONCAT( Q19, " -:- ", R19, " -:- ", S19, " -:- ", T19) -> Commercial -:- Education -:- Lights (Fluorescent) -:- Electricity | V19: Education Lighting Fluorescent ELC | W19: PJ | X19: GW
A20: DEM | B20: C_EDU-SH | D20: Space Heating | E20: =_xlfn.CONCAT(C20, " -:- ", D20 ) -> -:- Space Heating | F20: Education Space Heating | G20: PJ | O20: DMD | P20: C_EDU-LT_LED-ELC00 | Q20: Commercial | R20: Education | S20: Lights (LED) | T20: Electricity | U20: =_xlfn.CONCAT( Q20, " -:- ", R20, " -:- ", S20, " -:- ", T20) -> Commercial -:- Education -:- Lights (LED) -:- Electricity | V20: Education Lighting LED ELC | W20: PJ | X20: GW
A21: DEM | B21: C_EDU-WH | D21: Water Heating | E21: =_xlfn.CONCAT(C21, " -:- ", D21 ) -> -:- Water Heating | F21: Education Hot Water | G21: PJ | O21: DMD | P21: C_EDU-SH_Boiler-COA00 | Q21: Commercial | R21: Education | S21: Boiler | T21: Coal | U21: =_xlfn.CONCAT( Q21, " -:- ", R21, " -:- ", S21, " -:- ", T21) -> Commercial -:- Education -:- Boiler -:- Coal | V21: Education Boiler Systems COA | W21: PJ | X21: GW
A22: DEM | B22: C_EDU-MPM | D22: Motive Power, Mobile | E22: =_xlfn.CONCAT(C22, " -:- ", D22 ) -> -:- Motive Power, Mobile | F22: Education Motive Power, Mobile | G22: PJ | O22: DMD | P22: C_EDU-SH_Boiler-DSL00 | Q22: Commercial | R22: Education | S22: Boiler | T22: Diesel | U22: =_xlfn.CONCAT( Q22, " -:- ", R22, " -:- ", S22, " -:- ", T22) -> Commercial -:- Education -:- Boiler -:- Diesel | V22: Education Boiler Systems DSL | W22: PJ | X22: GW
A23: DEM | B23: C_EDU-MPS | D23: Motive Power, Stationary | E23: =_xlfn.CONCAT(C23, " -:- ", D23 ) -> -:- Motive Power, Stationary | F23: Education Motive Power, Stationery | G23: PJ | O23: DMD | P23: C_EDU-SH_Boiler-FOL00 | Q23: Commercial | R23: Education | S23: Boiler | T23: Fuel Oil | U23: =_xlfn.CONCAT( Q23, " -:- ", R23, " -:- ", S23, " -:- ", T23) -> Commercial -:- Education -:- Boiler -:- Fuel Oil | V23: Education Boiler Systems FOL | W23: PJ | X23: GW
A24: DEM | B24: C_EDU-RF | D24: Refrigeration | E24: =_xlfn.CONCAT(C24, " -:- ", D24 ) -> -:- Refrigeration | F24: Education Refrigeration | G24: PJ | O24: DMD | P24: C_EDU-SH_Boiler-NGA00 | Q24: Commercial | R24: Education | S24: Boiler | T24: Natural Gas | U24: =_xlfn.CONCAT( Q24, " -:- ", R24, " -:- ", S24, " -:- ", T24) -> Commercial -:- Education -:- Boiler -:- Natural Gas | V24: Education Boiler Systems NGA | W24: PJ | X24: GW
A25: DEM | B25: C_EDU-SC | D25: Space Cooling | E25: =_xlfn.CONCAT(C25, " -:- ", D25 ) -> -:- Space Cooling | F25: Education Space Cooling | G25: PJ | O25: DMD | P25: C_EDU-SH_Burner-NGA00 | Q25: Commercial | R25: Education | S25: Burner | T25: Natural Gas | U25: =_xlfn.CONCAT( Q25, " -:- ", R25, " -:- ", S25, " -:- ", T25) -> Commercial -:- Education -:- Burner -:- Natural Gas | V25: Education Burner (Direct Heat) NGA | W25: PJ | X25: GW
A26: DEM | B26: C_HLTH-OTH | D26: Electronics and Other Appliances | E26: =_xlfn.CONCAT(C26, " -:- ", D26 ) -> -:- Electronics and Other Appliances | F26: Healthcare Other | G26: PJ | O26: DMD | P26: C_EDU-SH_AIRHP-ELC00 | Q26: Commercial | R26: Education | S26: Heat Pump | T26: Electricity | U26: =_xlfn.CONCAT( Q26, " -:- ", R26, " -:- ", S26, " -:- ", T26) -> Commercial -:- Education -:- Heat Pump -:- Electricity | V26: Education Heat Pump Air Source (for Heating) ELC | W26: PJ | X26: GW
A27: DEM | B27: C_HLTH-LT | D27: Lighting | E27: =_xlfn.CONCAT(C27, " -:- ", D27 ) -> -:- Lighting | F27: Healthcare Lighting | G27: PJ | O27: DMD | P27: C_EDU-SH_RH-ELC00 | Q27: Commercial | R27: Education | S27: Resistance Heater | T27: Electricity | U27: =_xlfn.CONCAT( Q27, " -:- ", R27, " -:- ", S27, " -:- ", T27) -> Commercial -:- Education -:- Resistance Heater -:- Electricity | V27: Education Resistance Heater ELC | W27: PJ | X27: GW
A28: DEM | B28: C_HLTH-SH | D28: Space Heating | E28: =_xlfn.CONCAT(C28, " -:- ", D28 ) -> -:- Space Heating | F28: Healthcare Space Heating | G28: PJ | O28: DMD | P28: C_EDU-WH_Boiler-COA00 | Q28: Commercial | R28: Education | S28: Boiler | T28: Coal | U28: =_xlfn.CONCAT( Q28, " -:- ", R28, " -:- ", S28, " -:- ", T28) -> Commercial -:- Education -:- Boiler -:- Coal | V28: Education Boiler Systems COA | W28: PJ | X28: GW
A29: DEM | B29: C_HLTH-WH | D29: Water Heating | E29: =_xlfn.CONCAT(C29, " -:- ", D29 ) -> -:- Water Heating | F29: Healthcare Hot Water | G29: PJ | O29: DMD | P29: C_EDU-WH_Cylinder-ELC00 | Q29: Commercial | R29: Education | S29: Hot Water Cylinder | T29: Electricity | U29: =_xlfn.CONCAT( Q29, " -:- ", R29, " -:- ", S29, " -:- ", T29) -> Commercial -:- Education -:- Hot Water Cylinder -:- Electricity | V29: Education Hot Water Cylinder ELC | W29: PJ | X29: GW
... A57: DEM | B57: C_OTH-SC | D57: Space Cooling | E57: =_xlfn.CONCAT(C57, " -:- ", D57 ) -> -:- Space Cooling | F57: Other Space Cooling | G57: PJ | O57: DMD | P57: C_HLTH-SC_AIRHP-ELC00 | Q57: Commercial | R57: Healthcare | S57: Heat Pump | T57: Electricity | U57: =_xlfn.CONCAT( Q57, " -:- ", R57, " -:- ", S57, " -:- ", T57) -> Commercial -:- Healthcare -:- Heat Pump -:- Electricity | V57: Healthcare Heat Pump Air Source (for Cooling) ELC | W57: PJ | X57: GW
O58: DMD | P58: C_OFFC-OTH_EELC-ELC00 | Q58: Commercial | R58: Office Blocks | S58: Electronics and Other Appliances | T58: Electricity | U58: =_xlfn.CONCAT( Q58, " -:- ", R58, " -:- ", S58, " -:- ", T58) -> Commercial -:- Office Blocks -:- Electronics and Other Appliances -:- Electricity | V58: Office Blocks Electronics ELC | W58: PJ | X58: GW
O59: DMD | P59: C_OFFC-LT_INC-ELC00 | Q59: Commercial | R59: Office Blocks | S59: Lights (Incandescent) | T59: Electricity | U59: =_xlfn.CONCAT( Q59, " -:- ", R59, " -:- ", S59, " -:- ", T59) -> Commercial -:- Office Blocks -:- Lights (Incandescent) -:- Electricity | V59: Office Blocks Lighting Incandescent ELC | W59: PJ | X59: GW
O60: DMD | P60: C_OFFC-LT_FLU-ELC00 | Q60: Commercial | R60: Office Blocks | S60: Lights (Fluorescent) | T60: Electricity | U60: =_xlfn.CONCAT( Q60, " -:- ", R60, " -:- ", S60, " -:- ", T60) -> Commercial -:- Office Blocks -:- Lights (Fluorescent) -:- Electricity | V60: Office Blocks Lighting Fluorescent ELC | W60: PJ | X60: GW
O61: DMD | P61: C_OFFC-LT_LED-ELC00 | Q61: Commercial | R61: Office Blocks | S61: Lights (LED) | T61: Electricity | U61: =_xlfn.CONCAT( Q61, " -:- ", R61, " -:- ", S61, " -:- ", T61) -> Commercial -:- Office Blocks -:- Lights (LED) -:- Electricity | V61: Office Blocks Lighting LED ELC | W61: PJ | X61: GW
O62: DMD | P62: C_OFFC-SH_Boiler-COA00 | Q62: Commercial | R62: Office Blocks | S62: Boiler | T62: Coal | U62: =_xlfn.CONCAT( Q62, " -:- ", R62, " -:- ", S62, " -:- ", T62) -> Commercial -:- Office Blocks -:- Boiler -:- Coal | V62: Office Blocks Boiler Systems COA | W62: PJ | X62: GW
O63: DMD | P63: C_OFFC-SH_Boiler-DSL00 | Q63: Commercial | R63: Office Blocks | S63: Boiler | T63: Diesel | U63: =_xlfn.CONCAT( Q63, " -:- ", R63, " -:- ", S63, " -:- ", T63) -> Commercial -:- Office Blocks -:- Boiler -:- Diesel | V63: Office Blocks Boiler Systems DSL | W63: PJ | X63: GW
O64: DMD | P64: C_OFFC-SH_Boiler-FOL00 | Q64: Commercial | R64: Office Blocks | S64: Boiler | T64: Fuel Oil | U64: =_xlfn.CONCAT( Q64, " -:- ", R64, " -:- ", S64, " -:- ", T64) -> Commercial -:- Office Blocks -:- Boiler -:- Fuel Oil | V64: Office Blocks Boiler Systems FOL | W64: PJ | X64: GW
O65: DMD | P65: C_OFFC-SH_Boiler-NGA00 | Q65: Commercial | R65: Office Blocks | S65: Boiler | T65: Natural Gas | U65: =_xlfn.CONCAT( Q65, " -:- ", R65, " -:- ", S65, " -:- ", T65) -> Commercial -:- Office Blocks -:- Boiler -:- Natural Gas | V65: Office Blocks Boiler Systems NGA | W65: PJ | X65: GW
O66: DMD | P66: C_OFFC-SH_Burner-NGA00 | Q66: Commercial | R66: Office Blocks | S66: Burner | T66: Natural Gas | U66: =_xlfn.CONCAT( Q66, " -:- ", R66, " -:- ", S66, " -:- ", T66) -> Commercial -:- Office Blocks -:- Burner -:- Natural Gas | V66: Office Blocks Burner (Direct Heat) NGA | W66: PJ | X66: GW
O67: DMD | P67: C_OFFC-SH_AirHP-ELC00 | Q67: Commercial | R67: Office Blocks | S67: Heat Pump | T67: Electricity | U67: =_xlfn.CONCAT( Q67, " -:- ", R67, " -:- ", S67, " -:- ", T67) -> Commercial -:- Office Blocks -:- Heat Pump -:- Electricity | V67: Office Blocks Heat Pump Air Source (for Heating) ELC | W67: PJ | X67: GW
O68: DMD | P68: C_OFFC-SH_RH-ELC00 | Q68: Commercial | R68: Office Blocks | S68: Resistance Heater | T68: Electricity | U68: =_xlfn.CONCAT( Q68, " -:- ", R68, " -:- ", S68, " -:- ", T68) -> Commercial -:- Office Blocks -:- Resistance Heater -:- Electricity | V68: Office Blocks Resistance Heater ELC | W68: PJ | X68: GW
O69: DMD | P69: C_OFFC-WH_Boiler-FOL00 | Q69: Commercial | R69: Office Blocks | S69: Boiler | T69: Fuel Oil | U69: =_xlfn.CONCAT( Q69, " -:- ", R69, " -:- ", S69, " -:- ", T69) -> Commercial -:- Office Blocks -:- Boiler -:- Fuel Oil | V69: Office Blocks Boiler Systems FOL | W69: PJ | X69: GW
... O128: DMD | P128: C_OTH-SC_AIRHP-ELC00 | Q128: Commercial | R128: Other (Commercial) | S128: Heat Pump | T128: Electricity | U128: =_xlfn.CONCAT( Q128, " -:- ", R128, " -:- ", S128, " -:- ", T128) -> Commercial -:- Other (Commercial) -:- Heat Pump -:- Electricity | V128: Other Heat Pump Air Source (for Cooling) ELC | W128: PJ | X128: GW

Sheet COM_fuels
F2: ~FI_T
D3: TechName | E3: Comm-IN | F3: Comm-OUT | G3: Share-I~UP | H3: STOCK | I3: EFF | J3: LIFE | K3: INVCOST | L3: FIXOM | M3: VAROM
D4: *Technology Name | E4: Input Commodity | F4: Output Commodity | G4: Input Share | H4: Existing Installed Capacity | I4: Efficiency | J4: Lifetime | K4: Capital costs | L4: Fixed O&M | M4: Variable O&M
D5: *Units | H5: PJa | J5: Years | K5: MNZD/Pja | L5: MNZD/Pja | M5: MNZD/PJ
D6: =COM_techs!P7 -> FTE_COMCOA_00 | E6: COA | F6: =MID(D6,5,6) -> COMCOA | G6: 1 | I6: 1 | J6: 100
E7: COL | G7: =0.1 -> 0.1
D8: =COM_techs!P8 -> FTE_COMNGA_00 | E8: =+RIGHT(F8,3) -> NGA | F8: =MID(D8,5,6) -> COMNGA | I8: 1 | J8: 100 | M8: 9.35
D9: =COM_techs!P9 -> FTE_COMLPG_00 | E9: =+RIGHT(F9,3) -> LPG | F9: =MID(D9,5,6) -> COMLPG | I9: 1 | J9: 100
D10: =COM_techs!P10 -> FTE_COMDSL_00 | E10: =+RIGHT(F10,3) -> DSL | F10: =MID(D10,5,6) -> COMDSL | I10: 1 | J10: 100 | M10: 0.92
D11: =COM_techs!P11 -> FTE_COMBIG_00 | E11: =+RIGHT(F11,3) -> BIG | F11: =MID(D11,5,6) -> COMBIG | I11: 1 | J11: 100
D12: =COM_techs!P12 -> FTE_COMGEO_00 | E12: =+RIGHT(F12,3) -> GEO | F12: =MID(D12,5,6) -> COMGEO | I12: 1 | J12: 100
D13: =COM_techs!P13 -> FTE_COMFOL_00 | E13: =+RIGHT(F13,3) -> FOL | F13: =MID(D13,5,6) -> COMFOL | I13: 1 | J13: 100 | M13: 0.92
D14: =COM_techs!P14 -> FTE_COMPET_00 | E14: =+RIGHT(F14,3) -> PET | F14: =MID(D14,5,6) -> COMPET | I14: 1 | J14: 100 | M14: 0.92
D15: =COM_techs!P15 -> FTE_COMWOD_00 | E15: =+RIGHT(F15,3) -> WOD | F15: =MID(D15,5,6) -> COMWOD | I15: 1 | J15: 100
D16: =COM_techs!P16 -> FTE_COMPLT_00 | E16: =+RIGHT(F16,3) -> PLT | F16: =MID(D16,5,6) -> COMPLT | I16: 1 | J16: 100

Sheet COM
F3: ~FI_T
C4: TechName | D4: *TechDesc | E4: Comm-IN | F4: Comm-OUT | G4: *Delivered energy | H4: EFF | I4: *Share~UP~2018 | J4: Life | K4: INVCOST | L4: FIXOM | M4: AFA | N4: CAP2ACT | O4: PRC_RESID | P4: *ACT_BND~Total | Q4: *NI Split | R4: ACT_BND
C5: *Technology Name | D5: Technology Description | E5: Input Commodity | F5: Output Commodity | G5: Energy consumption 2018 | H5: Efficiency | J5: Lifetime of Process | K5: Investment Cost | L5: O&M Cost | M5: Capacity Factor | N5: Capacity to activity | O5: Existing Installed Capacity in Pja | P5: Bound on activity of a process | Q5: Consumption of North Island | R5: Bound on activity of a process
C6: C_EDU-OTH_ELEC-ELC00 | D6: Education Electronics ELC | E6: COMELC | F6: C_EDU-OTH | G6: 0.11312763 | H6: 0.9 | J6: 4 | K6: 5000 | L6: 0 | M6: 0.22 | N6: 31.536 | O6: =+R6/M6/N6 -> 0.0031845028 | P6: =+G6*H6 -> 0.10181487 | Q6: 0.783 | R6: =+P6*(1-Q6) -> 0.022093826
C7: C_EDU-LT_INC-ELC00 | D7: Education Lighting Incandescent ELC | E7: COMELC | F7: C_EDU-LT | G7: 0.0060710996 | H7: 0.015 | I7: 0.01 | J7: 1 | K7: 22 | L7: 0 | M7: 0.22 | N7: 31.536 | O7: =+R7/M7/N7 -> 2.8483218e-06 | P7: =+G7*H7 -> 9.1066493e-05 | Q7: 0.783 | R7: =+P7*(1-Q7) -> 1.9761429e-05
C8: C_EDU-LT_FLU-ELC00 | D8: Education Lighting Fluorescent ELC | E8: COMELC | F8: C_EDU-LT | G8: 0.49175906 | H8: 0.135 | I8: 0.81 | J8: 5 | K8: 333 | L8: 0 | M8: 0.22 | N8: 31.536 | O8: =+R8/M8/N8 -> 0.0020764266 | P8: =+G8*H8 -> 0.066387474 | Q8: 0.783 | R8: =+P8*(1-Q8) -> 0.014406082
C9: C_EDU-LT_LED-ELC00 | D9: Education Lighting LED ELC | E9: COMELC | F9: C_EDU-LT | G9: 0.10927979 | H9: 0.25 | I9: 0.18 | J9: 20 | K9: 1000 | L9: 0 | M9: 0.22 | N9: 31.536 | O9: =+R9/M9/N9 -> 0.00085449655 | P9: =+G9*H9 -> 0.027319948 | Q9: 0.783 | R9: =+P9*(1-Q9) -> 0.0059284287
C10: C_EDU-SH_Boiler-COA00 | D10: Education Boiler Systems COA | E10: COMCOA | F10: C_EDU-SH | G10: 0.10740089 | H10: 0.75 | J10: 25 | K10: 4000 | L10: 15 | M10: 0.1 | N10: 31.536 | O10: =+R10/M10/N10 -> 0.0055427117 | P10: =+G10*H10 -> 0.080550671 | Q10: 0.783 | R10: =+P10*(1-Q10) -> 0.017479495
C11: C_EDU-SH_Boiler-DSL00 | D11: Education Boiler Systems DSL | E11: COMDSL | F11: C_EDU-SH | G11: 0.022328154 | H11: 0.85 | J11: 25 | K11: 1900 | L11: 3 | M11: 0.1 | N11: 31.536 | O11: =+R11/M11/N11 -> 0.001305945 | P11: =+G11*H11 -> 0.018978931 | Q11: 0.783 | R11: =+P11*(1-Q11) -> 0.004118428
C12: C_EDU-SH_Boiler-FOL00 | D12: Education Boiler Systems FOL | E12: COMFOL | F12: C_EDU-SH | G12: 0.003734259 | H12: 0.84 | J12: 25 | K12: 1900 | L12: 3 | M12: 0.1 | N12: 31.536 | O12: =+R12/M12/N12 -> 0.00021584244 | P12: =+G12*H12 -> 0.0031367776 | Q12: 0.783 | R12: =+P12*(1-Q12) -> 0.00068068073
C13: C_EDU-SH_Boiler-NGA00 | D13: Education Boiler Systems NGA | E13: COMNGA | F13: C_EDU-SH | G13: 0.42693984 | H13: 0.85 | J13: 25 | K13: 1250 | L13: 2 | M13: 0.1 | N13: 31.536 | O13: =+R13/M13/N13 -> 0 | P13: =+G13*H13 -> 0.36289886 | Q13: 1 | R13: =+P13*(1-Q13) -> 0
C14: C_EDU-SH_Burner-NGA00 | D14: Education Burner (Direct Heat) NGA | E14: COMNGA | F14: C_EDU-SH | G14: 0.23460197 | H14: 0.8 | J14: 12.5 | K14: 300 | L14: 0 | M14: 0.1 | N14: 31.536 | O14: =+R14/M14/N14 -> 0 | P14: =+G14*H14 -> 0.18768158 | Q14: 1 | R14: =+P14*(1-Q14) -> 0
C15: C_EDU-SH_AIRHP-ELC00 | D15: Education Heat Pump Air Source (for Heating) ELC | E15: COMELC | F15: C_EDU-SH | G15: 0.020628337 | H15: 3.5 | J15: 10 | K15: 1718 | L15: 0 | M15: 0.1 | N15: 31.536 | O15: =+R15/M15/N15 -> 0.0049680435 | P15: =+G15*H15 -> 0.07219918 | Q15: 0.783 | R15: =+P15*(1-Q15) -> 0.015667222
C16: C_EDU-SH_RH-ELC00 | D16: Education Resistance Heater ELC | E16: COMELC | F16: C_EDU-SH | G16: 1.3732336 | H16: 0.99 | J16: 10 | K16: 80 | L16: 0 | M16: 0.1 | N16: 31.536 | O16: =+R16/M16/N16 -> 0.093547621 | P16: =+G16*H16 -> 1.3595013 | Q16: 0.783 | R16: =+P16*(1-Q16) -> 0.29501178
C17: C_EDU-WH_Boiler-COA00 | D17: Education Boiler Systems COA | E17: COMCOA | F17: C_EDU-WH | G17: 0.012821948 | H17: 0.75 | J17: 25 | K17: 4000 | L17: 15 | M17: 0.22 | N17: 31.536 | O17: =+R17/M17/N17 -> 0.00030077776 | P17: =+G17*H17 -> 0.009616461 | Q17: 0.783 | R17: =+P17*(1-Q17) -> 0.002086772
C18: C_EDU-WH_Cylinder-ELC00 | D18: Education Hot Water Cylinder ELC | E18: COMELC | F18: C_EDU-WH | G18: 0.12639835 | H18: 0.9 | J18: 15 | K18: 655 | L18: 0 | M18: 0.22 | N18: 31.536 | O18: =+R18/M18/N18 -> 0.0035580689 | P18: =+G18*H18 -> 0.11375851 | Q18: 0.783 | R18: =+P18*(1-Q18) -> 0.024685597
C19: C_EDU-WH_Cylinder-NGA00 | D19: Education Hot Water Cylinder NGA | E19: COMNGA | F19: C_EDU-WH | G19: 0.054405725 | H19: 0.6 | J19: 15 | K19: 316 | L19: 0 | M19: 0.22 | N19: 31.536 | O19: =+R19/M19/N19 -> 0 | P19: =+G19*H19 -> 0.032643435 | Q19: 1 | R19: =+P19*(1-Q19) -> 0
C20: C_EDU-MPM_-DSL00 | D20: Education Motive power - mobile DSL | E20: COMDSL | F20: C_EDU-MPM | G20: 0.49166673 | H20: 0.16 | J20: 20 | K20: 929 | L20: 7 | M20: 0.05 | N20: 31.536 | O20: =+R20/M20/N20 -> 0.010826147 | P20: =+G20*H20 -> 0.078666676 | Q20: 0.783 | R20: =+P20*(1-Q20) -> 0.017070669
C21: C_EDU-MPM_-PET00 | D21: Education Motive power - mobile PET | E21: COMPET | F21: C_EDU-MPM | G21: 0.11004509 | H21: 0.14 | J21: 20 | K21: 650 | L21: 7 | M21: 0.05 | N21: 31.536 | O21: =+R21/M21/N21 -> 0.0021202244 | P21: =+G21*H21 -> 0.015406312 | Q21: 0.783 | R21: =+P21*(1-Q21) -> 0.0033431698
... C25: C_EDU-SC_AirHP-ELC00 | D25: Education Heat Pump Air Source (for Cooling) ELC | E25: COMELC | F25: C_EDU-SC | G25: 0.12934478 | H25: 3.5 | J25: 10 | K25: 1718 | L25: 0 | M25: 0.11 | N25: 31.536 | O25: =+R25/M25/N25 -> 0.028318965 | P25: =+G25*H25 -> 0.45270672 | Q25: 0.783 | R25: =+P25*(1-Q25) -> 0.098237358
C26: \I:
C27: C_HLTH-OTH_ELEC-ELC00 | D27: Healthcare Electronics ELC | E27: COMELC | F27: C_HLTH-OTH | G27: 0.2421687 | H27: 0.9 | J27: 4 | K27: 5000 | L27: 0 | M27: 0.46 | N27: 31.536 | O27: =+R27/M27/N27 -> 0.0039814564 | P27: =+G27*H27 -> 0.21795183 | Q27: 0.735 | R27: =+P27*(1-Q27) -> 0.057757236
C28: C_HLTH-LT_INC-ELC00 | D28: Healthcare Lighting Incandescent ELC | E28: COMELC | F28: C_HLTH-LT | G28: 0.0044443341 | H28: 0.015 | I28: 0.01 | J28: 1 | K28: 88 | L28: 0 | M28: 0.46 | N28: 31.536 | O28: =+R28/M28/N28 -> 1.2178096e-06 | P28: =+G28*H28 -> 6.6665011e-05 | Q28: 0.735 | R28: =+P28*(1-Q28) -> 1.7666228e-05
C29: C_HLTH-LT_FLU-ELC00 | D29: Healthcare Lighting Fluorescent ELC | E29: COMELC | F29: C_HLTH-LT | G29: 0.35999106 | H29: 0.135 | I29: 0.81 | J29: 5 | K29: 1332 | L29: 0 | M29: 0.46 | N29: 31.536 | O29: =+R29/M29/N29 -> 0.0008877832 | P29: =+G29*H29 -> 0.048598793 | Q29: 0.735 | R29: =+P29*(1-Q29) -> 0.01287868
C30: C_HLTH-LT_LED-ELC00 | D30: Healthcare Lighting LED ELC | E30: COMELC | F30: C_HLTH-LT | G30: 0.079998014 | H30: 0.25 | I30: 0.18 | J30: 20 | K30: 4000 | L30: 0 | M30: 0.46 | N30: 31.536 | O30: =+R30/M30/N30 -> 0.00036534288 | P30: =+G30*H30 -> 0.019999503 | Q30: 0.735 | R30: =+P30*(1-Q30) -> 0.0052998684
C31: C_HLTH-SH_Boiler-COA00 | D31: Healthcare Boiler Systems COA | E31: COMCOA | F31: C_HLTH-SH | G31: 0.071848824 | H31: 0.75 | J31: 25 | K31: 1600 | L31: 15 | M31: 0.34 | N31: 31.536 | O31: =+R31/M31/N31 -> 0.001331807 | P31: =+G31*H31 -> 0.053886618 | Q31: 0.735 | R31: =+P31*(1-Q31) -> 0.014279954
C32: C_HLTH-SH_Boiler-DSL00 | D32: Healthcare Boiler Systems DSL | E32: COMDSL | F32: C_HLTH-SH | G32: 0.012593835 | H32: 0.85 | J32: 25 | K32: 760 | L32: 3 | M32: 0.34 | N32: 31.536 | O32: =+R32/M32/N32 -> 0.00026456798 | P32: =+G32*H32 -> 0.01070476 | Q32: 0.735 | R32: =+P32*(1-Q32) -> 0.0028367613
C33: C_HLTH-SH_Boiler-NGA00 | D33: Healthcare Boiler Systems NGA | E33: COMNGA | F33: C_HLTH-SH | G33: 1.5158104 | H33: 0.85 | J33: 25 | K33: 500 | L33: 2 | M33: 0.34 | N33: 31.536 | O33: =+R33/M33/N33 -> 0 | P33: =+G33*H33 -> 1.2884389 | Q33: 1 | R33: =+P33*(1-Q33) -> 0
C34: C_HLTH-SH_AIRHP-ELC00 | D34: Healthcare Heat Pump Air Source (for Heating) ELC | E34: COMELC | F34: C_HLTH-SH | G34: 0.099243505 | H34: 3.5 | J34: 10 | K34: 1718 | L34: 0 | M34: 0.34 | N34: 31.536 | O34: =+R34/M34/N34 -> 0.0085848061 | P34: =+G34*H34 -> 0.34735227 | Q34: 0.735 | R34: =+P34*(1-Q34) -> 0.092048351
C35: C_HLTH-SH_RH-ELC00 | D35: Healthcare Resistance Heater ELC | E35: COMELC | F35: C_HLTH-SH | G35: 0.53835991 | H35: 0.99 | J35: 10 | K35: 80 | L35: 0 | M35: 0.34 | N35: 31.536 | O35: =+R35/M35/N35 -> 0.013172502 | P35: =+G35*H35 -> 0.53297631 | Q35: 0.735 | R35: =+P35*(1-Q35) -> 0.14123872
C36: C_HLTH-WH_Boiler-FOL00 | D36: Healthcare Boiler Systems FOL | E36: COMFOL | F36: C_HLTH-WH | G36: 0.002456939 | H36: 0.84 | J36: 25 | K36: 760 | L36: 3 | M36: 0.46 | N36: 31.536 | O36: =+R36/M36/N36 -> 3.7701193e-05 | P36: =+G36*H36 -> 0.0020638288 | Q36: 0.735 | R36: =+P36*(1-Q36) -> 0.00054691462
C37: C_HLTH-WH_Boiler-COA00 | D37: Healthcare Boiler Systems COA | E37: COMCOA | F37: C_HLTH-WH | G37: 0.071019019 | H37: 0.75 | J37: 25 | K37: 1600 | L37: 15 | M37: 0.46 | N37: 31.536 | O37: =+R37/M37/N37 -> 0.00097301014 | P37: =+G37*H37 -> 0.053264264 | Q37: 0.735 | R37: =+P37*(1-Q37) -> 0.01411503
C38: C_HLTH-WH_Cylinder-ELC00 | D38: Healthcare Hot Water Cylinder ELC | E38: COMELC | F38: C_HLTH-WH | G38: 0.57176058 | H38: 0.9 | J38: 15 | K38: 655 | L38: 0 | M38: 0.46 | N38: 31.536 | O38: =+R38/M38/N38 -> 0.0094002229 | P38: =+G38*H38 -> 0.51458452 | Q38: 0.735 | R38: =+P38*(1-Q38) -> 0.1363649
C39: C_HLTH-WH_DirectH-GEO00 | D39: Healthcare Direct Heat GEO | E39: COMGEO | F39: C_HLTH-WH | G39: 0.052019952 | H39: 1 | J39: 10 | K39: 100 | L39: 0 | M39: 0.46 | N39: 31.536 | O39: =+R39/M39/N39 -> 0 | P39: =+G39*H39 -> 0.052019952 | Q39: 1 | R39: =+P39*(1-Q39) -> 0
C40: C_HLTH-PH_RH-ELC00 | D40: Healthcare Resistance Heater ELC | E40: COMELC | F40: C_HLTH-PH | G40: 0.27280019 | H40: 0.99 | J40: 10 | K40: 80 | L40: 0 | M40: 0.46 | N40: 31.536 | O40: =+R40/M40/N40 -> 0.00493357 | P40: =+G40*H40 -> 0.27007219 | Q40: 0.735 | R40: =+P40*(1-Q40) -> 0.071569129
C41: C_HLTH-PH_Boiler-COA00 | D41: Healthcare Boiler Systems COA | E41: COMCOA | F41: C_HLTH-PH | G41: 0.030929005 | H41: 0.75 | J41: 25 | K41: 1600 | L41: 15 | M41: 0.46 | N41: 31.536 | O41: =+R41/M41/N41 -> 0.00042374896 | P41: =+G41*H41 -> 0.023196754 | Q41: 0.735 | R41: =+P41*(1-Q41) -> 0.0061471397
C42: C_HLTH-PH_Boiler-NGA00 | D42: Healthcare Boiler Systems NGA | E42: COMNGA | F42: C_HLTH-PH | G42: 0 | H42: 0.85 | J42: 25 | K42: 500 | L42: 2 | M42: 0.34 | N42: 31.536 | O42: =+R42/M42/N42 -> 0 | P42: =+G42*H42 -> 0 | Q42: 1 | R42: =+P42*(1-Q42) -> 0
... C47: C_HLTH-SC_AIRHP-ELC00 | D47: Healthcare Heat Pump Air Source (for Cooling) ELC | E47: COMELC | F47: C_HLTH-SC | G47: 0.21301599 | H47: 3.5 | J47: 10 | K47: 1718 | L47: 0 | M47: 0.23 | N47: 31.536 | O47: =+R47/M47/N47 -> 0.027239033 | P47: =+G47*H47 -> 0.74555598 | Q47: 0.735 | R47: =+P47*(1-Q47) -> 0.19757233
C48: \I:
C49: C_OFFC-OTH_EELC-ELC00 | D49: Office Blocks Electronics ELC | E49: COMELC | F49: C_OFFC-OTH | G49: 2.3067525 | H49: 0.9 | J49: 4 | K49: 5000 | L49: 0 | M49: 0.45 | N49: 31.536 | O49: =+R49/M49/N49 -> 0.034232628 | P49: =+G49*H49 -> 2.0760772 | Q49: 0.766 | R49: =+P49*(1-Q49) -> 0.48580207
C50: C_OFFC-LT_INC-ELC00 | D50: Office Blocks Lighting Incandescent ELC | E50: COMELC | F50: C_OFFC-LT | G50: 0.033797666 | H50: 0.015 | I50: 0.01 | J50: 1 | K50: 44 | L50: 0 | M50: 0.45 | N50: 31.536 | O50: =+R50/M50/N50 -> 8.3593923e-06 | P50: =+G50*H50 -> 0.00050696499 | Q50: 0.766 | R50: =+P50*(1-Q50) -> 0.00011862981
C51: C_OFFC-LT_FLU-ELC00 | D51: Office Blocks Lighting Fluorescent ELC | E51: COMELC | F51: C_OFFC-LT | G51: 2.737611 | H51: 0.135 | I51: 0.81 | J51: 5 | K51: 666 | L51: 0 | M51: 0.45 | N51: 31.536 | O51: =+R51/M51/N51 -> 0.006093997 | P51: =+G51*H51 -> 0.36957748 | Q51: 0.766 | R51: =+P51*(1-Q51) -> 0.08648113
C52: C_OFFC-LT_LED-ELC00 | D52: Office Blocks Lighting LED ELC | E52: COMELC | F52: C_OFFC-LT | G52: 0.60835799 | H52: 0.25 | I52: 0.18 | J52: 20 | K52: 2000 | L52: 0 | M52: 0.45 | N52: 31.536 | O52: =+R52/M52/N52 -> 0.0025078177 | P52: =+G52*H52 -> 0.1520895 | Q52: 0.766 | R52: =+P52*(1-Q52) -> 0.035588943
C53: C_OFFC-SH_Boiler-COA00 | D53: Office Blocks Boiler Systems COA | E53: COMCOA | F53: C_OFFC-SH | G53: 0.05482311 | H53: 0.75 | J53: 25 | K53: 800 | L53: 15 | M53: 0.1 | N53: 31.536 | O53: =+R53/M53/N53 -> 0.0030509436 | P53: =+G53*H53 -> 0.041117332 | Q53: 0.766 | R53: =+P53*(1-Q53) -> 0.0096214558
C54: C_OFFC-SH_Boiler-DSL00 | D54: Office Blocks Boiler Systems DSL | E54: COMDSL | F54: C_OFFC-SH | G54: 1.3848737 | H54: 0.85 | J54: 25 | K54: 380 | L54: 3 | M54: 0.1 | N54: 31.536 | O54: =+R54/M54/N54 -> 0.087345056 | P54: =+G54*H54 -> 1.1771426 | Q54: 0.766 | R54: =+P54*(1-Q54) -> 0.27545137
C55: C_OFFC-SH_Boiler-FOL00 | D55: Office Blocks Boiler Systems FOL | E55: COMFOL | F55: C_OFFC-SH | G55: 0.029400894 | H55: 0.84 | J55: 25 | K55: 380 | L55: 3 | M55: 0.1 | N55: 31.536 | O55: =+R55/M55/N55 -> 0.0018325215 | P55: =+G55*H55 -> 0.024696751 | Q55: 0.766 | R55: =+P55*(1-Q55) -> 0.0057790397
C56: C_OFFC-SH_Boiler-NGA00 | D56: Office Blocks Boiler Systems NGA | E56: COMNGA | F56: C_OFFC-SH | G56: 1.1012969 | H56: 0.85 | J56: 25 | K56: 250 | L56: 2 | M56: 0.1 | N56: 31.536 | O56: =+R56/M56/N56 -> 0 | P56: =+G56*H56 -> 0.93610233 | Q56: 1 | R56: =+P56*(1-Q56) -> 0
C57: C_OFFC-SH_Burner-NGA00 | D57: Office Blocks Burner (Direct Heat) NGA | E57: COMNGA | F57: C_OFFC-SH | G57: 0.076031865 | H57: 0.8 | J57: 12.5 | K57: 300 | L57: 0 | M57: 0.1 | N57: 31.536 | O57: =+R57/M57/N57 -> 0 | P57: =+G57*H57 -> 0.060825492 | Q57: 1 | R57: =+P57*(1-Q57) -> 0
C58: C_OFFC-SH_AirHP-ELC00 | D58: Office Blocks Heat Pump Air Source (for Heating) ELC | E58: COMELC | F58: C_OFFC-SH | G58: 1.2728339 | H58: 3.5 | J58: 10 | K58: 1718 | L58: 0 | M58: 0.1 | N58: 31.536 | O58: =+R58/M58/N58 -> 0.33055903 | P58: =+G58*H58 -> 4.4549187 | Q58: 0.766 | R58: =+P58*(1-Q58) -> 1.042451
C59: C_OFFC-SH_RH-ELC00 | D59: Office Blocks Resistance Heater ELC | E59: COMELC | F59: C_OFFC-SH | G59: 0.68371166 | H59: 0.99 | J59: 10 | K59: 80 | L59: 0 | M59: 0.1 | N59: 31.536 | O59: =+R59/M59/N59 -> 0.050224709 | P59: =+G59*H59 -> 0.67687454 | Q59: 0.766 | R59: =+P59*(1-Q59) -> 0.15838864
C60: C_OFFC-WH_Boiler-FOL00 | D60: Office Blocks Boiler Systems FOL | E60: COMFOL | F60: C_OFFC-WH | G60: 8.6308e-05 | H60: 0.84 | J60: 25 | K60: 380 | L60: 3 | M60: 0.45 | N60: 31.536 | O60: =+R60/M60/N60 -> 1.1954381e-06 | P60: =+G60*H60 -> 7.249872e-05 | Q60: 0.766 | R60: =+P60*(1-Q60) -> 1.69647e-05
C61: C_OFFC-WH_Boiler-COA00 | D61: Office Blocks Boiler Systems COA | E61: COMCOA | F61: C_OFFC-WH | G61: 0.000382967 | H61: 0.75 | J61: 25 | K61: 800 | L61: 15 | M61: 0.45 | N61: 31.536 | O61: =+R61/M61/N61 -> 4.7360835e-06 | P61: =+G61*H61 -> 0.00028722525 | Q61: 0.766 | R61: =+P61*(1-Q61) -> 6.7210708e-05
C62: C_OFFC-WH_AirHP-ELC00 | D62: Office Blocks Heat Pump (for Heating) ELC | E62: COMELC | F62: C_OFFC-WH | G62: 0.21680042 | H62: 2.5 | J62: 10 | K62: 3750 | L62: 0 | M62: 0.45 | N62: 31.536 | O62: =+R62/M62/N62 -> 0.0089371051 | P62: =+G62*H62 -> 0.54200105 | Q62: 0.766 | R62: =+P62*(1-Q62) -> 0.12682825
C63: C_OFFC-WH_Cylinder-ELC00 | D63: Office Blocks Hot Water Cylinder ELC | E63: COMELC | F63: C_OFFC-WH | G63: 0.2322634 | H63: 0.9 | J63: 15 | K63: 655 | L63: 0 | M63: 0.45 | N63: 31.536 | O63: =+R63/M63/N63 -> 0.0034468313 | P63: =+G63*H63 -> 0.20903706 | Q63: 0.766 | R63: =+P63*(1-Q63) -> 0.048914673
C64: C_OFFC-WH_Cylinder-NGA00 | D64: Office Blocks Hot Water Cylinder NGA | E64: COMNGA | F64: C_OFFC-WH | G64: 0.024233406 | H64: 0.6 | J64: 15 | K64: 316 | L64: 0 | M64: 0.45 | N64: 31.536 | O64: =+R64/M64/N64 -> 0 | P64: =+G64*H64 -> 0.014540044 | Q64: 1 | R64: =+P64*(1-Q64) -> 0
... C69: C_OFFC-SC_AIRHP-ELC00 | D69: Office Blocks Heat Pump Air Source (for Cooling) ELC | E69: COMELC | F69: C_OFFC-SC | G69: 1.6504509 | H69: 3.5 | J69: 10 | K69: 1718 | L69: 0 | M69: 0.22 | N69: 31.536 | O69: =+R69/M69/N69 -> 0.19483062 | P69: =+G69*H69 -> 5.776578 | Q69: 0.766 | R69: =+P69*(1-Q69) -> 1.3517192
C70: \I:
C71: C_WSR-OTH_ELEC-ELC00 | D71: WSR Electronics ELC | E71: COMELC | F71: C_WSR-OTH | G71: 0.74029789 | H71: 0.9 | J71: 4 | K71: 5000 | L71: 0 | M71: 0.48 | N71: 31.536 | O71: =+R71/M71/N71 -> 0.010299521 | P71: =+G71*H71 -> 0.6662681 | Q71: 0.766 | R71: =+P71*(1-Q71) -> 0.15590674
C72: C_WSR-CK_Elements-ELC00 | D72: WSR Cooking Elements ELC | E72: COMELC | F72: C_WSR-CK | G72: 0.43474732 | H72: 0.74 | J72: 15 | K72: 312 | L72: 0 | M72: 0.48 | N72: 31.536 | O72: =+R72/M72/N72 -> 0.0049732083 | P72: =+G72*H72 -> 0.32171302 | Q72: 0.766 | R72: =+P72*(1-Q72) -> 0.075280847
C73: C_WSR-CK_Ovens-ELC00 | D73: WSR Cooking Ovens ELC | E73: COMELC | F73: C_WSR-CK | G73: 0.6781611 | H73: 0.65 | J73: 20 | K73: 1225 | L73: 0 | M73: 0.48 | N73: 31.536 | O73: =+R73/M73/N73 -> 0.0068141901 | P73: =+G73*H73 -> 0.44080471 | Q73: 0.766 | R73: =+P73*(1-Q73) -> 0.1031483
C74: C_WSR-CK_Ovens-LPG00 | D74: WSR Cooking Ovens LPG | E74: COMLPG | F74: C_WSR-CK | G74: 1.0608818 | H74: 0.3 | J74: 20 | K74: 824 | L74: 0 | M74: 0.48 | N74: 31.536 | O74: =+R74/M74/N74 -> 0.0049198998 | P74: =+G74*H74 -> 0.31826453 | Q74: 0.766 | R74: =+P74*(1-Q74) -> 0.0744739
C75: C_WSR-CK_Ovens-NGA00 | D75: WSR Cooking Ovens NGA | E75: COMNGA | F75: C_WSR-CK | G75: 0.87947263 | H75: 0.3 | J75: 20 | K75: 824 | L75: 0 | M75: 0.48 | N75: 31.536 | O75: =+R75/M75/N75 -> 0 | P75: =+G75*H75 -> 0.26384179 | Q75: 1 | R75: =+P75*(1-Q75) -> 0
C76: C_WSR-LT_INC-ELC00 | D76: WSR Lighting Incandescent ELC | E76: COMELC | F76: C_WSR-LT | G76: 0.026030653 | H76: 0.015 | I76: 0.01 | J76: 1 | K76: 22 | L76: 0 | M76: 0.48 | N76: 31.536 | O76: =+R76/M76/N76 -> 6.0359321e-06 | P76: =+G76*H76 -> 0.0003904598 | Q76: 0.766 | R76: =+P76*(1-Q76) -> 9.1367594e-05
C77: C_WSR-LT_FLU-ELC00 | D77: WSR Lighting Fluorescent ELC | E77: COMELC | F77: C_WSR-LT | G77: 2.1084829 | H77: 0.135 | I77: 0.81 | J77: 5 | K77: 333 | L77: 0 | M77: 0.48 | N77: 31.536 | O77: =+R77/M77/N77 -> 0.0044001945 | P77: =+G77*H77 -> 0.2846452 | Q77: 0.766 | R77: =+P77*(1-Q77) -> 0.066606976
C78: C_WSR-LT_LED-ELC00 | D78: WSR Lighting LED ELC | E78: COMELC | F78: C_WSR-LT | G78: 0.46855176 | H78: 0.25 | I78: 0.18 | J78: 20 | K78: 1000 | L78: 0 | M78: 0.48 | N78: 31.536 | O78: =+R78/M78/N78 -> 0.0018107796 | P78: =+G78*H78 -> 0.11713794 | Q78: 0.766 | R78: =+P78*(1-Q78) -> 0.027410278
C79: C_WSR-SH_Boiler-COA00 | D79: WSR Boiler Systems COA | E79: COMCOA | F79: C_WSR-SH | G79: 0.003803082 | H79: 0.75 | J79: 25 | K79: 800 | L79: 15 | M79: 0.1 | N79: 31.536 | O79: =+R79/M79/N79 -> 0.00021164412 | P79: =+G79*H79 -> 0.0028523115 | Q79: 0.766 | R79: =+P79*(1-Q79) -> 0.00066744089
C80: C_WSR-SH_Boiler-DSL00 | D80: WSR Boiler Systems DSL | E80: COMDSL | F80: C_WSR-SH | G80: 0.019841256 | H80: 0.85 | J80: 25 | K80: 380 | L80: 3 | M80: 0.1 | N80: 31.536 | O80: =+R80/M80/N80 -> 0.0012514034 | P80: =+G80*H80 -> 0.016865068 | Q80: 0.766 | R80: =+P80*(1-Q80) -> 0.0039464258
C81: C_WSR-SH_Boiler-FOL00 | D81: WSR Boiler Systems FOL | E81: COMFOL | F81: C_WSR-SH | G81: 0.017024308 | H81: 0.84 | J81: 25 | K81: 380 | L81: 3 | M81: 0.1 | N81: 31.536 | O81: =+R81/M81/N81 -> 0.0010611041 | P81: =+G81*H81 -> 0.014300419 | Q81: 0.766 | R81: =+P81*(1-Q81) -> 0.003346298
C82: C_WSR-SH_Boiler-LPG00 | D82: WSR Boiler Systems LPG | E82: COMLPG | F82: C_WSR-SH | G82: 0.040573375 | H82: 0.85 | J82: 25 | K82: 250 | L82: 2 | M82: 0.1 | N82: 31.536 | O82: =+R82/M82/N82 -> 0.0025589943 | P82: =+G82*H82 -> 0.034487369 | Q82: 0.766 | R82: =+P82*(1-Q82) -> 0.0080700443
C83: C_WSR-SH_Boiler-NGA00 | D83: WSR Boiler Systems NGA | E83: COMNGA | F83: C_WSR-SH | G83: 0.81503023 | H83: 0.85 | J83: 25 | K83: 250 | L83: 2 | M83: 0.1 | N83: 31.536 | O83: =+R83/M83/N83 -> 0 | P83: =+G83*H83 -> 0.6927757 | Q83: 1 | R83: =+P83*(1-Q83) -> 0
C84: C_WSR-SH_HeatHD-COA00 | D84: WSR Burner (Direct Heat) COA | E84: COMCOA | F84: C_WSR-SH | G84: 0.31314995 | H84: 0.77 | J84: 12.5 | K84: 500 | L84: 0 | M84: 0.1 | N84: 31.536 | O84: =+R84/M84/N84 -> 0.017891729 | P84: =+G84*H84 -> 0.24112546 | Q84: 0.766 | R84: =+P84*(1-Q84) -> 0.056423357
C85: C_WSR-SH_HeatHD-FOL00 | D85: WSR Burner (Direct Heat) FOL | E85: COMFOL | F85: C_WSR-SH | G85: 0.007537775 | H85: 0.75 | J85: 12.5 | K85: 250 | L85: 0 | M85: 0.1 | N85: 31.536 | O85: =+R85/M85/N85 -> 0.00041948234 | P85: =+G85*H85 -> 0.0056533313 | Q85: 0.766 | R85: =+P85*(1-Q85) -> 0.0013228795
C86: C_WSR-SH_HeatHD-LPG00 | D86: WSR Burner (Direct Heat) LPG | E86: COMLPG | F86: C_WSR-SH | G86: 0.55923512 | H86: 0.8 | J86: 12.5 | K86: 300 | L86: 0 | M86: 0.1 | N86: 31.536 | O86: =+R86/M86/N86 -> 0.033196605 | P86: =+G86*H86 -> 0.44738809 | Q86: 0.766 | R86: =+P86*(1-Q86) -> 0.10468881
C87: C_WSR-SH_HeatHD-NGA00 | D87: WSR Burner (Direct Heat) NGA | E87: COMNGA | F87: C_WSR-SH | G87: 0.9359606 | H87: 0.8 | J87: 12.5 | K87: 300 | L87: 0 | M87: 0.1 | N87: 31.536 | O87: =+R87/M87/N87 -> 0 | P87: =+G87*H87 -> 0.74876848 | Q87: 1 | R87: =+P87*(1-Q87) -> 0
C88: C_WSR-SH_AirHP-ELC00 | D88: WSR Heat Pump Air Source (for Heating) ELC | E88: COMELC | F88: C_WSR-SH | G88: 0.29241004 | H88: 3.5 | J88: 10 | K88: 1718 | L88: 0 | M88: 0.1 | N88: 31.536 | O88: =+R88/M88/N88 -> 0.075939822 | P88: =+G88*H88 -> 1.0234351 | Q88: 0.766 | R88: =+P88*(1-Q88) -> 0.23948382
C89: C_WSR-SH_RH-ELC00 | D89: WSR Resistance Heater ELC | E89: COMELC | F89: C_WSR-SH | G89: 1.9271023 | H89: 0.99 | J89: 10 | K89: 80 | L89: 0 | M89: 0.1 | N89: 31.536 | O89: =+R89/M89/N89 -> 0.14156283 | P89: =+G89*H89 -> 1.9078313 | Q89: 0.766 | R89: =+P89*(1-Q89) -> 0.44643253
C90: C_WSR-SH_DirectH-GEO00 | D90: WSR Direct Heat GEO | E90: COMGEO | F90: C_WSR-SH | G90: 0.20212627 | H90: 1 | J90: 10 | K90: 100 | L90: 0 | M90: 0.1 | N90: 31.536 | O90: =+R90/M90/N90 -> 0 | P90: =+G90*H90 -> 0.20212627 | Q90: 1 | R90: =+P90*(1-Q90) -> 0
... C99: C_WSR-SC_AIRHP-ELC00 | D99: WSR Heat Pump Air Source (for Cooling) ELC | E99: COMELC | F99: C_WSR-SC | G99: 0.35709882 | H99: 3.5 | J99: 10 | K99: 1718 | L99: 0 | M99: 0.24 | N99: 31.536 | O99: =+R99/M99/N99 -> 0.038641544 | P99: =+G99*H99 -> 1.2498459 | Q99: 0.766 | R99: =+P99*(1-Q99) -> 0.29246393
C100: \I:
C101: C_OTH-OTH_Elec-ELC00 | D101: Other Electronics ELC | E101: COMELC | F101: C_OTH-OTH | G101: 0.3447641 | H101: 0.9 | J101: 4 | K101: 5000 | L101: 0 | M101: 0.55 | N101: 31.536 | O101: =+R101/M101/N101 -> 0.0042218933 | P101: =+G101*H101 -> 0.31028769 | Q101: 0.764 | R101: =+P101*(1-Q101) -> 0.073227894
C102: C_OTH-LT_INC-ELC00 | D102: Other Lighting Incandescent ELC | E102: COMELC | F102: C_OTH-LT | G102: 0.0087038241 | H102: 0.015 | I102: 0.01 | J102: 1 | K102: 22 | L102: 0 | M102: 0.55 | N102: 31.536 | O102: =+R102/M102/N102 -> 1.7764135e-06 | P102: =+G102*H102 -> 0.00013055736 | Q102: 0.764 | R102: =+P102*(1-Q102) -> 3.0811537e-05
C103: C_OTH-LT_FLU-ELC00 | D103: Other Lighting Fluorescent ELC | E103: COMELC | F103: C_OTH-LT | G103: 0.70500975 | H103: 0.135 | I103: 0.81 | J103: 5 | K103: 333 | L103: 0 | M103: 0.55 | N103: 31.536 | O103: =+R103/M103/N103 -> 0.0012950055 | P103: =+G103*H103 -> 0.095176316 | Q103: 0.764 | R103: =+P103*(1-Q103) -> 0.022461611
C104: C_OTH-LT_LED-ELC00 | D104: Other Lighting LED ELC | E104: COMELC | F104: C_OTH-LT | G104: 0.15666883 | H104: 0.25 | I104: 0.18 | J104: 20 | K104: 1000 | L104: 0 | M104: 0.55 | N104: 31.536 | O104: =+R104/M104/N104 -> 0.00053292406 | P104: =+G104*H104 -> 0.039167208 | Q104: 0.764 | R104: =+P104*(1-Q104) -> 0.0092434612
C105: C_OTH-SH_Boiler-COA00 | D105: Other Boiler Systems COA | E105: COMCOA | F105: C_OTH-SH | G105: 0.071069505 | H105: 0.75 | J105: 25 | K105: 800 | L105: 15 | M105: 0.1 | N105: 31.536 | O105: =+R105/M105/N105 -> 0.0039888706 | P105: =+G105*H105 -> 0.053302129 | Q105: 0.764 | R105: =+P105*(1-Q105) -> 0.012579302
C106: C_OTH-SH_Boiler-DSL00 | D106: Other Boiler Systems DSL | E106: COMDSL | F106: C_OTH-SH | G106: 0.016881726 | H106: 0.85 | J106: 25 | K106: 380 | L106: 3 | M106: 0.1 | N106: 31.536 | O106: =+R106/M106/N106 -> 0.0010738439 | P106: =+G106*H106 -> 0.014349467 | Q106: 0.764 | R106: =+P106*(1-Q106) -> 0.0033864742
C107: C_OTH-SH_Boiler-FOL00 | D107: Other Boiler Systems FOL | E107: COMFOL | F107: C_OTH-SH | G107: 0.007875074 | H107: 0.84 | J107: 25 | K107: 380 | L107: 3 | M107: 0.1 | N107: 31.536 | O107: =+R107/M107/N107 -> 0.0004950389 | P107: =+G107*H107 -> 0.0066150622 | Q107: 0.764 | R107: =+P107*(1-Q107) -> 0.0015611547
C108: C_OTH-SH_Boiler-NGA00 | D108: Other Boiler Systems NGA | E108: COMNGA | F108: C_OTH-SH | G108: 0.92886491 | H108: 0.85 | J108: 25 | K108: 250 | L108: 2 | M108: 0.1 | N108: 31.536 | O108: =+R108/M108/N108 -> 0 | P108: =+G108*H108 -> 0.78953517 | Q108: 1 | R108: =+P108*(1-Q108) -> 0
C109: C_OTH-SH_Burner-NGA00 | D109: Other Burner (Direct Heat) NGA | E109: COMNGA | F109: C_OTH-SH | G109: 0.32388031 | H109: 0.8 | J109: 12.5 | K109: 300 | L109: 0 | M109: 0.1 | N109: 31.536 | O109: =+R109/M109/N109 -> 0 | P109: =+G109*H109 -> 0.25910425 | Q109: 1 | R109: =+P109*(1-Q109) -> 0
C110: C_OTH-SH_AirHP-ELC00 | D110: Other Heat Pump Air Source (for Heating) ELC | E110: COMELC | F110: C_OTH-SH | G110: 0.27297176 | H110: 3.5 | J110: 10 | K110: 1718 | L110: 0 | M110: 0.1 | N110: 31.536 | O110: =+R110/M110/N110 -> 0.07149755 | P110: =+G110*H110 -> 0.95540116 | Q110: 0.764 | R110: =+P110*(1-Q110) -> 0.22547467
C111: C_OTH-SH_RH-ELC00 | D111: Other Resistance Heater ELC | E111: COMELC | F111: C_OTH-SH | G111: 0.42739634 | H111: 0.99 | J111: 10 | K111: 80 | L111: 0 | M111: 0.1 | N111: 31.536 | O111: =+R111/M111/N111 -> 0.03166441 | P111: =+G111*H111 -> 0.42312238 | Q111: 0.764 | R111: =+P111*(1-Q111) -> 0.099856882
C112: C_OTH-WH_Boiler-FOL00 | D112: Other Boiler Systems FOL | E112: COMFOL | F112: C_OTH-WH | G112: 0.00127491 | H112: 0.84 | J112: 25 | K112: 380 | L112: 3 | M112: 0.55 | N112: 31.536 | O112: =+R112/M112/N112 -> 1.4571408e-05 | P112: =+G112*H112 -> 0.0010709244 | Q112: 0.764 | R112: =+P112*(1-Q112) -> 0.00025273816
C113: C_OTH-WH_Boiler-COA00 | D113: Other Boiler Systems COA | E113: COMCOA | F113: C_OTH-WH | G113: 0.023116087 | H113: 0.75 | J113: 25 | K113: 800 | L113: 15 | M113: 0.55 | N113: 31.536 | O113: =+R113/M113/N113 -> 0.00023589476 | P113: =+G113*H113 -> 0.017337065 | Q113: 0.764 | R113: =+P113*(1-Q113) -> 0.0040915474
C114: C_OTH-WH_Cylinder-ELC00 | D114: Other Hot Water Cylinder ELC | E114: COMELC | F114: C_OTH-WH | G114: 0.10049802 | H114: 0.9 | J114: 15 | K114: 655 | L114: 0 | M114: 0.55 | N114: 31.536 | O114: =+R114/M114/N114 -> 0.0012306732 | P114: =+G114*H114 -> 0.090448222 | Q114: 0.764 | R114: =+P114*(1-Q114) -> 0.02134578
C115: C_OTH-WH_Cylinder-NGA00 | D115: Other Hot Water Cylinder NGA | E115: COMNGA | F115: C_OTH-WH | G115: 0.055481543 | H115: 0.6 | J115: 15 | K115: 316 | L115: 0 | M115: 0.55 | N115: 31.536 | O115: =+R115/M115/N115 -> 0 | P115: =+G115*H115 -> 0.033288926 | Q115: 1 | R115: =+P115*(1-Q115) -> 0
C116: C_OTH-WH_DirectH-GEO00 | D116: Other Direct Heat GEO | E116: COMGEO | F116: C_OTH-WH | G116: 2.1306314 | H116: 1 | J116: 10 | K116: 100 | L116: 0 | M116: 0.55 | N116: 31.536 | O116: =+R116/M116/N116 -> 0 | P116: =+G116*H116 -> 2.1306314 | Q116: 1 | R116: =+P116*(1-Q116) -> 0
... C121: C_OTH-SC_AIRHP-ELC00 | D121: Other Heat Pump Air Source (for Cooling) ELC | E121: COMELC | F121: C_OTH-SC | G121: 0.37788849 | H121: 3.5 | J121: 10 | K121: 1718 | L121: 0 | M121: 0.27 | N121: 31.536 | O121: =+R121/M121/N121 -> 0.036658386 | P121: =+G121*H121 -> 1.3226097 | Q121: 0.764 | R121: =+P121*(1-Q121) -> 0.3121359
C130: ~FI_T
C131: CommName | D131: Demand~2018
C132: C_EDU-OTH | D132: =ROUNDDOWN(SUMIF($F$6:$F$121,C132,$R$6:$R$121),3) -> 0.022
C133: C_EDU-LT | D133: =ROUNDDOWN(SUMIF($F$6:$F$121,C133,$R$6:$R$121),3) -> 0.02
...

Sheet Emi
B2: ~COMEMI
B3: CommName | C3: AGRCOA | D3: AGRDSL | E3: AGRPET | F3: AGRFOL | G3: AGRLPG | H3: AGRNGA | I3: AGRGEO | J3: AGRWOD | K3: AGRPLT
B4: *Units | C4: kt/PJ | D4: kt/PJ | E4: kt/PJ | F4: kt/PJ | G4: kt/PJ | H4: kt/PJ | I4: kt/PJ | J4: kt/PJ | K4: kt/PJ
B5: AGRCO2 | C5: 92 | D5: 69.69 | E5: 66.58 | F5: 72.91 | G5: 60.43 | H5: 53.96
B8: ~COMEMI
B9: CommName | C9: RESCOA | D9: RESNGA | E9: RESLPG | F9: RESDSL | G9: RESWOD
B10: *Units | C10: kt/PJ | D10: kt/PJ | E10: kt/PJ | F10: kt/PJ | G10: kt/PJ
B11: RESCO2 | C11: 92 | D11: 53.96 | E11: 60.43 | F11: 69.69
B14: ~COMEMI
B15: CommName | C15: COMCOA | D15: COMNGA | E15: COMLPG | F15: COMDSL | G15: COMBIG | H15: COMGEO | I15: COMFOL | J15: COMPET | K15: COMWOD | L15: COMPLT
B16: *Units | C16: kt/PJ | D16: kt/PJ | E16: kt/PJ | F16: kt/PJ | G16: kt/PJ | H16: kt/PJ | I16: kt/PJ | J16: kt/PJ | K16: kt/PJ | L16: kt/PJ
B17: COMCO2 | C17: 92 | D17: 53.96 | E17: 60.43 | F17: 69.69 | I17: 72.91 | J17: 66.58
C22: see also VT_NI_OTH_V4.xls

Sheet Matrices
B4: Existing | C4: Sector | D4: Sector (Key) | E4: Demands | F4: Demand (Key) | G4: Fuel | H4: Fuel (Key) | I4: Fuel Application | J4: Validity | K4: Technology Key | L4: Valid Technology Key | P4: TechName | Q4: Comm-IN | R4: Comm-OUT | S4: EFF | T4: *AFA | U4: ActBnd | V4: PRC_RESID~2015 | W4: PRC_RESID~2035 | X4: PRC_RESID~2050 | Y4: ActBnd~LO~2015 | Z4: *ActBnd~LO~2035 | AA4: ActBnd~LO~2050 | AB4: ActBnd~LO~0 | AC4: ACT_BND~UP~2021 | AD4: ACT_BND~UP~2040 | AG4: EFF | AH4: *AFA | AI4: ActBnd | AJ4: PRC_RESID~2015 | AK4: PRC_RESID~2035 | AL4: PRC_RESID~2050 | AM4: ActBnd~LO~2015 | AN4: *ActBnd~LO~2035 | AO4: ActBnd~LO~2050 | AP4: ActBnd~LO~0 | AQ4: ACT_BND~UP~2021 | AR4: ACT_BND~UP~2040
B5: Ext | C5: Industry | D5: IND- | E5: Space heating | F5: SH | G5: =C5&" Coal" -> Industry Coal | H5: INDCOA | I5: =$C$5&" "&$E$5&" "&RIGHT(G5,LEN(G5)-FIND(" ",G5)) -> Industry Space heating Coal | J5: no | K5: =$D$5&$F$5&RIGHT(H5,3)&$B$5 -> IND-SHCOAExt | L5: =IF(J5="Yes",K5,"") | O5: =IF(J5="Yes",I5,"") | P5: =L5 | Q5: =IF(J5="yes",LEFT(P5,3)&"-"&MID(P5,7,3),"") | R5: =LEFT(P5,6) | S5: =IF(P5<>"",AG5,"") | T5: =IF(Q5<>"",AH5,"") | U5: =IF(R5<>"",AI5,"") | V5: =IF(S5<>"",AJ5,"") | W5: =IF(T5<>"",AK5,"") | X5: =IF(U5<>"",AL5,"") | Y5: =IF(V5<>"",AM5,"") | Z5: =IF(W5<>"",AN5,"") | ... AD5: =IF(AA5<>"",AR5,"") | AG5: 0.6 | AH5: 2 | AI5: 1 | AJ5: 1 | AK5: =0.8*AJ5 -> 0.8 | AL5: =AJ5*0 -> 0 | AM5: 0.5 | AN5: 0.4 | AO5: 0 | AP5: 1
E6: Water heating | F6: WH | G6: =C5&" Lignite" -> Industry Lignite | H6: INDCOL | I6: =$C$5&" "&$E$5&" "&RIGHT(G6,LEN(G6)-FIND(" ",G6)) -> Industry Space heating Lignite | J6: no | K6: =$D$5&$F$5&RIGHT(H6,3)&$B$5 -> IND-SHCOLExt | L6: =IF(J6="Yes",K6,"") | O6: =IF(J6="Yes",I6,"") | P6: =L6 | Q6: =IF(J6="yes",LEFT(P6,3)&"-"&MID(P6,7,3),"") | R6: =LEFT(P6,6) | S6: =IF(P6<>"",AG6,"") | T6: =IF(Q6<>"",AH6,"") | U6: =IF(R6<>"",AI6,"") | V6: =IF(S6<>"",AJ6,"") | W6: =IF(T6<>"",AK6,"") | X6: =IF(U6<>"",AL6,"") | Y6: =IF(V6<>"",AM6,"") | Z6: =IF(W6<>"",AN6,"") | ... AD6: =IF(AA6<>"",AR6,"") | AG6: 0.6 | AH6: 2 | AI6: 1 | AJ6: 1 | AK6: =0.8*AJ6 -> 0.8 | AL6: =AJ6*0 -> 0 | AM6: 0.5 | AN6: 0.4 | AO6: 0 | AP6: 1
E7: High temperature process heat | F7: PH | G7: =C5&" Crude oil" -> Industry Crude oil | H7: INDOIL | I7: =$C$5&" "&$E$5&" "&RIGHT(G7,LEN(G7)-FIND(" ",G7)) -> Industry Space heating Crude oil | J7: yes | K7: =$D$5&$F$5&RIGHT(H7,3)&$B$5 -> IND-SHOILExt | L7: =IF(J7="Yes",K7,"") -> IND-SHOILExt | O7: =IF(J7="Yes",I7,"") -> Industry Space heating Crude oil | P7: =L7 -> IND-SHOILExt | Q7: =IF(J7="yes",LEFT(P7,3)&"-"&MID(P7,7,3),"") -> IND-OIL | R7: =LEFT(P7,6) -> IND-SH | S7: =IF(P7<>"",AG7,"") -> 0.6 | T7: =IF(Q7<>"",AH7,"") -> 2 | U7: =IF(R7<>"",AI7,"") -> 1 | V7: =IF(S7<>"",AJ7,"") -> 1 | W7: =IF(T7<>"",AK7,"") -> 0.8 | X7: =IF(U7<>"",AL7,"") -> 0 | Y7: =IF(V7<>"",AM7,"") -> 0.5 | Z7: =IF(W7<>"",AN7,"") -> 0.4 | ... AD7: =IF(AA7<>"",AR7,"") -> 0 | AG7: 0.6 | AH7: 2 | AI7: 1 | AJ7: 1 | AK7: =0.8*AJ7 -> 0.8 | AL7: =AJ7*0 -> 0 | AM7: 0.5 | AN7: 0.4 | AO7: 0 | AP7: 1
E8: Lighting | F8: LT | G8: =C5&" Natural Gas" -> Industry Natural Gas | H8: INDNGA | I8: =$C$5&" "&$E$5&" "&RIGHT(G8,LEN(G8)-FIND(" ",G8)) -> Industry Space heating Natural Gas | J8: yes | K8: =$D$5&$F$5&RIGHT(H8,3)&$B$5 -> IND-SHNGAExt | L8: =IF(J8="Yes",K8,"") -> IND-SHNGAExt | O8: =IF(J8="Yes",I8,"") -> Industry Space heating Natural Gas | P8: =L8 -> IND-SHNGAExt | Q8: =IF(J8="yes",LEFT(P8,3)&"-"&MID(P8,7,3),"") -> IND-NGA | R8: =LEFT(P8,6) -> IND-SH | S8: =IF(P8<>"",AG8,"") -> 0.6 | T8: =IF(Q8<>"",AH8,"") -> 2 | U8: =IF(R8<>"",AI8,"") -> 1 | V8: =IF(S8<>"",AJ8,"") -> 1 | W8: =IF(T8<>"",AK8,"") -> 0.8 | X8: =IF(U8<>"",AL8,"") -> 0 | Y8: =IF(V8<>"",AM8,"") -> 0.5 | Z8: =IF(W8<>"",AN8,"") -> 0.4 | ... AD8: =IF(AA8<>"",AR8,"") -> 0 | AG8: 0.6 | AH8: 2 | AI8: 1 | AJ8: 1 | AK8: =0.8*AJ8 -> 0.8 | AL8: =AJ8*0 -> 0 | AM8: 0.5 | AN8: 0.4 | AO8: 0 | AP8: 1
E9: Air conditioning | F9: AC | G9: =C5&" Hydro" -> Industry Hydro | H9: INDHYD | I9: =$C$5&" "&$E$5&" "&RIGHT(G9,LEN(G9)-FIND(" ",G9)) -> Industry Space heating Hydro | J9: no | K9: =$D$5&$F$5&RIGHT(H9,3)&$B$5 -> IND-SHHYDExt | L9: =IF(J9="Yes",K9,"") | O9: =IF(J9="Yes",I9,"") | P9: =L9 | Q9: =IF(J9="yes",LEFT(P9,3)&"-"&MID(P9,7,3),"") | R9: =LEFT(P9,6) | S9: =IF(P9<>"",AG9,"") | T9: =IF(Q9<>"",AH9,"") | U9: =IF(R9<>"",AI9,"") | V9: =IF(S9<>"",AJ9,"") | W9: =IF(T9<>"",AK9,"") | X9: =IF(U9<>"",AL9,"") | Y9: =IF(V9<>"",AM9,"") | Z9: =IF(W9<>"",AN9,"") | ... AD9: =IF(AA9<>"",AR9,"") | AG9: 0.6 | AH9: 2 | AI9: 1 | AJ9: 1 | AK9: =0.8*AJ9 -> 0.8 | AL9: =AJ9*0 -> 0 | AM9: 0.5 | AN9: 0.4 | AO9: 0 | AP9: 1
E10: Electrical and ICT equipments | F10: EQ | G10: =C5&" Geothermal" -> Industry Geothermal | H10: INDGEO | I10: =$C$5&" "&$E$5&" "&RIGHT(G10,LEN(G10)-FIND(" ",G10)) -> Industry Space heating Geothermal | J10: yes | K10: =$D$5&$F$5&RIGHT(H10,3)&$B$5 -> IND-SHGEOExt | L10: =IF(J10="Yes",K10,"") -> IND-SHGEOExt | O10: =IF(J10="Yes",I10,"") -> Industry Space heating Geothermal | P10: =L10 -> IND-SHGEOExt | Q10: =IF(J10="yes",LEFT(P10,3)&"-"&MID(P10,7,3),"") -> IND-GEO | R10: =LEFT(P10,6) -> IND-SH | S10: =IF(P10<>"",AG10,"") -> 0.6 | T10: =IF(Q10<>"",AH10,"") -> 2 | U10: =IF(R10<>"",AI10,"") -> 1 | V10: =IF(S10<>"",AJ10,"") -> 1 | W10: =IF(T10<>"",AK10,"") -> 0.8 | X10: =IF(U10<>"",AL10,"") -> 0 | Y10: =IF(V10<>"",AM10,"") -> 0.5 | Z10: =IF(W10<>"",AN10,"") -> 0.4 | ... AD10: =IF(AA10<>"",AR10,"") -> 0 | AG10: 0.6 | AH10: 2 | AI10: 1 | AJ10: 1 | AK10: =0.8*AJ10 -> 0.8 | AL10: =AJ10*0 -> 0 | AM10: 0.5 | AN10: 0.4 | AO10: 0 | AP10: 1
E11: Mechanical drive | F11: MD | G11: =C5&" Solar" -> Industry Solar | H11: INDSOL | I11: =$C$5&" "&$E$5&" "&RIGHT(G11,LEN(G11)-FIND(" ",G11)) -> Industry Space heating Solar | J11: yes | K11: =$D$5&$F$5&RIGHT(H11,3)&$B$5 -> IND-SHSOLExt | L11: =IF(J11="Yes",K11,"") -> IND-SHSOLExt | O11: =IF(J11="Yes",I11,"") -> Industry Space heating Solar | P11: =L11 -> IND-SHSOLExt | Q11: =IF(J11="yes",LEFT(P11,3)&"-"&MID(P11,7,3),"") -> IND-SOL | R11: =LEFT(P11,6) -> IND-SH | S11: =IF(P11<>"",AG11,"") -> 0.6 | T11: =IF(Q11<>"",AH11,"") -> 2 | U11: =IF(R11<>"",AI11,"") -> 1 | V11: =IF(S11<>"",AJ11,"") -> 1 | W11: =IF(T11<>"",AK11,"") -> 0.8 | X11: =IF(U11<>"",AL11,"") -> 0 | Y11: =IF(V11<>"",AM11,"") -> 0.5 | Z11: =IF(W11<>"",AN11,"") -> 0.4 | ... AD11: =IF(AA11<>"",AR11,"") -> 0 | AG11: 0.6 | AH11: 2 | AI11: 1 | AJ11: 1 | AK11: =0.8*AJ11 -> 0.8 | AL11: =AJ11*0 -> 0 | AM11: 0.5 | AN11: 0.4 | AO11: 0 | AP11: 1
E12: Internal transport and others | F12: OT | G12: =C5&" Wind" -> Industry Wind | H12: INDWIN | I12: =$C$5&" "&$E$5&" "&RIGHT(G12,LEN(G12)-FIND(" ",G12)) -> Industry Space heating Wind | J12: no | K12: =$D$5&$F$5&RIGHT(H12,3)&$B$5 -> IND-SHWINExt | L12: =IF(J12="Yes",K12,"") | O12: =IF(J12="Yes",I12,"") | P12: =L12 | Q12: =IF(J12="yes",LEFT(P12,3)&"-"&MID(P12,7,3),"") | R12: =LEFT(P12,6) | S12: =IF(P12<>"",AG12,"") | T12: =IF(Q12<>"",AH12,"") | U12: =IF(R12<>"",AI12,"") | V12: =IF(S12<>"",AJ12,"") | W12: =IF(T12<>"",AK12,"") | X12: =IF(U12<>"",AL12,"") | Y12: =IF(V12<>"",AM12,"") | Z12: =IF(W12<>"",AN12,"") | ... AD12: =IF(AA12<>"",AR12,"") | AG12: 0.6 | AH12: 2 | AI12: 1 | AJ12: 1 | AK12: =0.8*AJ12 -> 0.8 | AL12: =AJ12*0 -> 0 | AM12: 0.5 | AN12: 0.4 | AO12: 0 | AP12: 1
E13: Process cooling | F13: PC | G13: =C5&" Bio Liquids" -> Industry Bio Liquids | H13: INDBIL | I13: =$C$5&" "&$E$5&" "&RIGHT(G13,LEN(G13)-FIND(" ",G13)) -> Industry Space heating Bio Liquids | J13: no | K13: =$D$5&$F$5&RIGHT(H13,3)&$B$5 -> IND-SHBILExt | L13: =IF(J13="Yes",K13,"") | O13: =IF(J13="Yes",I13,"") | P13: =L13 | Q13: =IF(J13="yes",LEFT(P13,3)&"-"&MID(P13,7,3),"") | R13: =LEFT(P13,6) | S13: =IF(P13<>"",AG13,"") | T13: =IF(Q13<>"",AH13,"") | U13: =IF(R13<>"",AI13,"") | V13: =IF(S13<>"",AJ13,"") | W13: =IF(T13<>"",AK13,"") | X13: =IF(U13<>"",AL13,"") | Y13: =IF(V13<>"",AM13,"") | Z13: =IF(W13<>"",AN13,"") | ... AD13: =IF(AA13<>"",AR13,"") | AG13: 0.6 | AH13: 2 | AI13: 1 | AJ13: 1 | AK13: =0.8*AJ13 -> 0.8 | AL13: =AJ13*0 -> 0 | AM13: 0.5 | AN13: 0.4 | AO13: 0 | AP13: 1
G14: =C5&" Biogas" -> Industry Biogas | H14: INDBIG | I14: =$C$5&" "&$E$5&" "&RIGHT(G14,LEN(G14)-FIND(" ",G14)) -> Industry Space heating Biogas | J14: yes | K14: =$D$5&$F$5&RIGHT(H14,3)&$B$5 -> IND-SHBIGExt | L14: =IF(J14="Yes",K14,"") -> IND-SHBIGExt | O14: =IF(J14="Yes",I14,"") -> Industry Space heating Biogas | P14: =L14 -> IND-SHBIGExt | Q14: =IF(J14="yes",LEFT(P14,3)&"-"&MID(P14,7,3),"") -> IND-BIG | R14: =LEFT(P14,6) -> IND-SH | S14: =IF(P14<>"",AG14,"") -> 0.6 | T14: =IF(Q14<>"",AH14,"") -> 2 | U14: =IF(R14<>"",AI14,"") -> 1 | V14: =IF(S14<>"",AJ14,"") -> 1 | W14: =IF(T14<>"",AK14,"") -> 0.8 | X14: =IF(U14<>"",AL14,"") -> 0 | Y14: =IF(V14<>"",AM14,"") -> 0.5 | Z14: =IF(W14<>"",AN14,"") -> 0.4 | ... AD14: =IF(AA14<>"",AR14,"") -> 0 | AG14: 0.6 | AH14: 2 | AI14: 1 | AJ14: 1 | AK14: =0.8*AJ14 -> 0.8 | AL14: =AJ14*0 -> 0 | AM14: 0.5 | AN14: 0.4 | AO14: 0 | AP14: 1
G15: =C5&" Wood" -> Industry Wood | H15: INDWOD | I15: =$C$5&" "&$E$5&" "&RIGHT(G15,LEN(G15)-FIND(" ",G15)) -> Industry Space heating Wood | J15: yes | K15: =$D$5&$F$5&RIGHT(H15,3)&$B$5 -> IND-SHWODExt | L15: =IF(J15="Yes",K15,"") -> IND-SHWODExt | O15: =IF(J15="Yes",I15,"") -> Industry Space heating Wood | P15: =L15 -> IND-SHWODExt | Q15: =IF(J15="yes",LEFT(P15,3)&"-"&MID(P15,7,3),"") -> IND-WOD | R15: =LEFT(P15,6) -> IND-SH | S15: =IF(P15<>"",AG15,"") -> 0.6 | T15: =IF(Q15<>"",AH15,"") -> 2 | U15: =IF(R15<>"",AI15,"") -> 1 | V15: =IF(S15<>"",AJ15,"") -> 1 | W15: =IF(T15<>"",AK15,"") -> 0.8 | X15: =IF(U15<>"",AL15,"") -> 0 | Y15: =IF(V15<>"",AM15,"") -> 0.5 | Z15: =IF(W15<>"",AN15,"") -> 0.4 | ... AD15: =IF(AA15<>"",AR15,"") -> 0 | AG15: 0.6 | AH15: 2 | AI15: 1 | AJ15: 1 | AK15: =0.8*AJ15 -> 0.8 | AL15: =AJ15*0 -> 0 | AM15: 0.5 | AN15: 0.4 | AO15: 0 | AP15: 1
G16: =C5&" Tidal" -> Industry Tidal | H16: INDTID | I16: =$C$5&" "&$E$5&" "&RIGHT(G16,LEN(G16)-FIND(" ",G16)) -> Industry Space heating Tidal | J16: no | K16: =$D$5&$F$5&RIGHT(H16,3)&$B$5 -> IND-SHTIDExt | L16: =IF(J16="Yes",K16,"") | O16: =IF(J16="Yes",I16,"") | P16: =L16 | Q16: =IF(J16="yes",LEFT(P16,3)&"-"&MID(P16,7,3),"") | R16: =LEFT(P16,6) | S16: =IF(P16<>"",AG16,"") | T16: =IF(Q16<>"",AH16,"") | U16: =IF(R16<>"",AI16,"") | V16: =IF(S16<>"",AJ16,"") | W16: =IF(T16<>"",AK16,"") | X16: =IF(U16<>"",AL16,"") | Y16: =IF(V16<>"",AM16,"") | Z16: =IF(W16<>"",AN16,"") | ... AD16: =IF(AA16<>"",AR16,"") | AG16: 0.6 | AH16: 2 | AI16: 1 | AJ16: 1 | AK16: =0.8*AJ16 -> 0.8 | AL16: =AJ16*0 -> 0 | AM16: 0.5 | AN16: 0.4 | AO16: 0 | AP16: 1
G17: =C5&" Electricity" -> Industry Electricity | H17: INDELC | I17: =$C$5&" "&$E$5&" "&RIGHT(G17,LEN(G17)-FIND(" ",G17)) -> Industry Space heating Electricity | J17: yes | K17: =$D$5&$F$5&RIGHT(H17,3)&$B$5 -> IND-SHELCExt | L17: =IF(J17="Yes",K17,"") -> IND-SHELCExt | O17: =IF(J17="Yes",I17,"") -> Industry Space heating Electricity | P17: =L17 -> IND-SHELCExt | Q17: =IF(J17="yes",LEFT(P17,3)&"-"&MID(P17,7,3),"") -> IND-ELC | R17: =LEFT(P17,6) -> IND-SH | S17: =IF(P17<>"",AG17,"") -> 0.6 | T17: =IF(Q17<>"",AH17,"") -> 2 | U17: =IF(R17<>"",AI17,"") -> 1 | V17: =IF(S17<>"",AJ17,"") -> 1 | W17: =IF(T17<>"",AK17,"") -> 0.8 | X17: =IF(U17<>"",AL17,"") -> 0 | Y17: =IF(V17<>"",AM17,"") -> 0.5 | Z17: =IF(W17<>"",AN17,"") -> 0.4 | ... AD17: =IF(AA17<>"",AR17,"") -> 0 | AG17: 0.6 | AH17: 2 | AI17: 1 | AJ17: 1 | AK17: =0.8*AJ17 -> 0.8 | AL17: =AJ17*0 -> 0 | AM17: 0.5 | AN17: 0.4 | AO17: 0 | AP17: 1
I18: =$C$5&" "&$E$6&" "&RIGHT(G5,LEN(G5)-FIND(" ",G5)) -> Industry Water heating Coal | J18: yes | K18: =$D$5&$F$6&RIGHT(H5,3)&$B$5 -> IND-WHCOAExt | L18: =IF(J18="Yes",K18,"") -> IND-WHCOAExt | O18: =IF(J18="Yes",I18,"") -> Industry Water heating Coal | P18: =L18 -> IND-WHCOAExt | Q18: =IF(J18="yes",LEFT(P18,3)&"-"&MID(P18,7,3),"") -> IND-COA | R18: =LEFT(P18,6) -> IND-WH | S18: =IF(P18<>"",AG18,"") -> 0.6 | T18: =IF(Q18<>"",AH18,"") -> 2 | U18: =IF(R18<>"",AI18,"") -> 1 | V18: =IF(S18<>"",AJ18,"") -> 1 | W18: =IF(T18<>"",AK18,"") -> 0.8 | X18: =IF(U18<>"",AL18,"") -> 0 | Y18: =IF(V18<>"",AM18,"") -> 0.5 | Z18: =IF(W18<>"",AN18,"") -> 0.4 | ... AD18: =IF(AA18<>"",AR18,"") -> 0 | AG18: 0.6 | AH18: 2 | AI18: 1 | AJ18: 1 | AK18: =0.8*AJ18 -> 0.8 | AL18: =AJ18*0 -> 0 | AM18: 0.5 | AN18: 0.4 | AO18: 0 | AP18: 1
I19: =$C$5&" "&$E$6&" "&RIGHT(G6,LEN(G6)-FIND(" ",G6)) -> Industry Water heating Lignite | J19: yes | K19: =$D$5&$F$6&RIGHT(H6,3)&$B$5 -> IND-WHCOLExt | L19: =IF(J19="Yes",K19,"") -> IND-WHCOLExt | O19: =IF(J19="Yes",I19,"") -> Industry Water heating Lignite | P19: =L19 -> IND-WHCOLExt | Q19: =IF(J19="yes",LEFT(P19,3)&"-"&MID(P19,7,3),"") -> IND-COL | R19: =LEFT(P19,6) -> IND-WH | S19: =IF(P19<>"",AG19,"") -> 0.6 | T19: =IF(Q19<>"",AH19,"") -> 2 | U19: =IF(R19<>"",AI19,"") -> 1 | V19: =IF(S19<>"",AJ19,"") -> 1 | W19: =IF(T19<>"",AK19,"") -> 0.8 | X19: =IF(U19<>"",AL19,"") -> 0 | Y19: =IF(V19<>"",AM19,"") -> 0.5 | Z19: =IF(W19<>"",AN19,"") -> 0.4 | ... AD19: =IF(AA19<>"",AR19,"") -> 0 | AG19: 0.6 | AH19: 2 | AI19: 1 | AJ19: 1 | AK19: =0.8*AJ19 -> 0.8 | AL19: =AJ19*0 -> 0 | AM19: 0.5 | AN19: 0.4 | AO19: 0 | AP19: 1
I20: =$C$5&" "&$E$6&" "&RIGHT(G7,LEN(G7)-FIND(" ",G7)) -> Industry Water heating Crude oil | J20: yes | K20: =$D$5&$F$6&RIGHT(H7,3)&$B$5 -> IND-WHOILExt | L20: =IF(J20="Yes",K20,"") -> IND-WHOILExt | O20: =IF(J20="Yes",I20,"") -> Industry Water heating Crude oil | P20: =L20 -> IND-WHOILExt | Q20: =IF(J20="yes",LEFT(P20,3)&"-"&MID(P20,7,3),"") -> IND-OIL | R20: =LEFT(P20,6) -> IND-WH | S20: =IF(P20<>"",AG20,"") -> 0.6 | T20: =IF(Q20<>"",AH20,"") -> 2 | U20: =IF(R20<>"",AI20,"") -> 1 | V20: =IF(S20<>"",AJ20,"") -> 1 | W20: =IF(T20<>"",AK20,"") -> 0.8 | X20: =IF(U20<>"",AL20,"") -> 0 | Y20: =IF(V20<>"",AM20,"") -> 0.5 | Z20: =IF(W20<>"",AN20,"") -> 0.4 | ... AD20: =IF(AA20<>"",AR20,"") -> 0 | AG20: 0.6 | AH20: 2 | AI20: 1 | AJ20: 1 | AK20: =0.8*AJ20 -> 0.8 | AL20: =AJ20*0 -> 0 | AM20: 0.5 | AN20: 0.4 | AO20: 0 | AP20: 1
I21: =$C$5&" "&$E$6&" "&RIGHT(G8,LEN(G8)-FIND(" ",G8)) -> Industry Water heating Natural Gas | J21: no | K21: =$D$5&$F$6&RIGHT(H8,3)&$B$5 -> IND-WHNGAExt | L21: =IF(J21="Yes",K21,"") | O21: =IF(J21="Yes",I21,"") | P21: =L21 | Q21: =IF(J21="yes",LEFT(P21,3)&"-"&MID(P21,7,3),"") | R21: =LEFT(P21,6) | S21: =IF(P21<>"",AG21,"") | T21: =IF(Q21<>"",AH21,"") | U21: =IF(R21<>"",AI21,"") | V21: =IF(S21<>"",AJ21,"") | W21: =IF(T21<>"",AK21,"") | X21: =IF(U21<>"",AL21,"") | Y21: =IF(V21<>"",AM21,"") | Z21: =IF(W21<>"",AN21,"") | ... AD21: =IF(AA21<>"",AR21,"") | AG21: 0.6 | AH21: 2 | AI21: 1 | AJ21: 1 | AK21: =0.8*AJ21 -> 0.8 | AL21: =AJ21*0 -> 0 | AM21: 0.5 | AN21: 0.4 | AO21: 0 | AP21: 1
I22: =$C$5&" "&$E$6&" "&RIGHT(G9,LEN(G9)-FIND(" ",G9)) -> Industry Water heating Hydro | J22: no | K22: =$D$5&$F$6&RIGHT(H9,3)&$B$5 -> IND-WHHYDExt | L22: =IF(J22="Yes",K22,"") | O22: =IF(J22="Yes",I22,"") | P22: =L22 | Q22: =IF(J22="yes",LEFT(P22,3)&"-"&MID(P22,7,3),"") | R22: =LEFT(P22,6) | S22: =IF(P22<>"",AG22,"") | T22: =IF(Q22<>"",AH22,"") | U22: =IF(R22<>"",AI22,"") | V22: =IF(S22<>"",AJ22,"") | W22: =IF(T22<>"",AK22,"") | X22: =IF(U22<>"",AL22,"") | Y22: =IF(V22<>"",AM22,"") | Z22: =IF(W22<>"",AN22,"") | ... AD22: =IF(AA22<>"",AR22,"") | AG22: 0.6 | AH22: 2 | AI22: 1 | AJ22: 1 | AK22: =0.8*AJ22 -> 0.8 | AL22: =AJ22*0 -> 0 | AM22: 0.5 | AN22: 0.4 | AO22: 0 | AP22: 1
I23: =$C$5&" "&$E$6&" "&RIGHT(G10,LEN(G10)-FIND(" ",G10)) -> Industry Water heating Geothermal | J23: yes | K23: =$D$5&$F$6&RIGHT(H10,3)&$B$5 -> IND-WHGEOExt | L23: =IF(J23="Yes",K23,"") -> IND-WHGEOExt | O23: =IF(J23="Yes",I23,"") -> Industry Water heating Geothermal | P23: =L23 -> IND-WHGEOExt | Q23: =IF(J23="yes",LEFT(P23,3)&"-"&MID(P23,7,3),"") -> IND-GEO | R23: =LEFT(P23,6) -> IND-WH | S23: =IF(P23<>"",AG23,"") -> 0.6 | T23: =IF(Q23<>"",AH23,"") -> 2 | U23: =IF(R23<>"",AI23,"") -> 1 | V23: =IF(S23<>"",AJ23,"") -> 1 | W23: =IF(T23<>"",AK23,"") -> 0.8 | X23: =IF(U23<>"",AL23,"") -> 0 | Y23: =IF(V23<>"",AM23,"") -> 0.5 | Z23: =IF(W23<>"",AN23,"") -> 0.4 | ... AD23: =IF(AA23<>"",AR23,"") -> 0 | AG23: 0.6 | AH23: 2 | AI23: 1 | AJ23: 1 | AK23: =0.8*AJ23 -> 0.8 | AL23: =AJ23*0 -> 0 | AM23: 0.5 | AN23: 0.4 | AO23: 0 | AP23: 1
I24: =$C$5&" "&$E$6&" "&RIGHT(G11,LEN(G11)-FIND(" ",G11)) -> Industry Water heating Solar | J24: yes | K24: =$D$5&$F$6&RIGHT(H11,3)&$B$5 -> IND-WHSOLExt | L24: =IF(J24="Yes",K24,"") -> IND-WHSOLExt | O24: =IF(J24="Yes",I24,"") -> Industry Water heating Solar | P24: =L24 -> IND-WHSOLExt | Q24: =IF(J24="yes",LEFT(P24,3)&"-"&MID(P24,7,3),"") -> IND-SOL | R24: =LEFT(P24,6) -> IND-WH | S24: =IF(P24<>"",AG24,"") -> 0.6 | T24: =IF(Q24<>"",AH24,"") -> 2 | U24: =IF(R24<>"",AI24,"") -> 1 | V24: =IF(S24<>"",AJ24,"") -> 1 | W24: =IF(T24<>"",AK24,"") -> 0.8 | X24: =IF(U24<>"",AL24,"") -> 0 | Y24: =IF(V24<>"",AM24,"") -> 0.5 | Z24: =IF(W24<>"",AN24,"") -> 0.4 | ... AD24: =IF(AA24<>"",AR24,"") -> 0 | AG24: 0.6 | AH24: 2 | AI24: 1 | AJ24: 1 | AK24: =0.8*AJ24 -> 0.8 | AL24: =AJ24*0 -> 0 | AM24: 0.5 | AN24: 0.4 | AO24: 0 | AP24: 1
I25: =$C$5&" "&$E$6&" "&RIGHT(G12,LEN(G12)-FIND(" ",G12)) -> Industry Water heating Wind | J25: no | K25: =$D$5&$F$6&RIGHT(H12,3)&$B$5 -> IND-WHWINExt | L25: =IF(J25="Yes",K25,"") | O25: =IF(J25="Yes",I25,"") | P25: =L25 | Q25: =IF(J25="yes",LEFT(P25,3)&"-"&MID(P25,7,3),"") | R25: =LEFT(P25,6) | S25: =IF(P25<>"",AG25,"") | T25: =IF(Q25<>"",AH25,"") | U25: =IF(R25<>"",AI25,"") | V25: =IF(S25<>"",AJ25,"") | W25: =IF(T25<>"",AK25,"") | X25: =IF(U25<>"",AL25,"") | Y25: =IF(V25<>"",AM25,"") | Z25: =IF(W25<>"",AN25,"") | ... AD25: =IF(AA25<>"",AR25,"") | AG25: 0.6 | AH25: 2 | AI25: 1 | AJ25: 1 | AK25: =0.8*AJ25 -> 0.8 | AL25: =AJ25*0 -> 0 | AM25: 0.5 | AN25: 0.4 | AO25: 0 | AP25: 1
I26: =$C$5&" "&$E$6&" "&RIGHT(G13,LEN(G13)-FIND(" ",G13)) -> Industry Water heating Bio Liquids | J26: no | K26: =$D$5&$F$6&RIGHT(H13,3)&$B$5 -> IND-WHBILExt | L26: =IF(J26="Yes",K26,"") | O26: =IF(J26="Yes",I26,"") | P26: =L26 | Q26: =IF(J26="yes",LEFT(P26,3)&"-"&MID(P26,7,3),"") | R26: =LEFT(P26,6) | S26: =IF(P26<>"",AG26,"") | T26: =IF(Q26<>"",AH26,"") | U26: =IF(R26<>"",AI26,"") | V26: =IF(S26<>"",AJ26,"") | W26: =IF(T26<>"",AK26,"") | X26: =IF(U26<>"",AL26,"") | Y26: =IF(V26<>"",AM26,"") | Z26: =IF(W26<>"",AN26,"") | ... AD26: =IF(AA26<>"",AR26,"") | AG26: 0.6 | AH26: 2 | AI26: 1 | AJ26: 1 | AK26: =0.8*AJ26 -> 0.8 | AL26: =AJ26*0 -> 0 | AM26: 0.5 | AN26: 0.4 | AO26: 0 | AP26: 1
I27: =$C$5&" "&$E$6&" "&RIGHT(G14,LEN(G14)-FIND(" ",G14)) -> Industry Water heating Biogas | J27: no | K27: =$D$5&$F$6&RIGHT(H14,3)&$B$5 -> IND-WHBIGExt | L27: =IF(J27="Yes",K27,"") | O27: =IF(J27="Yes",I27,"") | P27: =L27 | Q27: =IF(J27="yes",LEFT(P27,3)&"-"&MID(P27,7,3),"") | R27: =LEFT(P27,6) | S27: =IF(P27<>"",AG27,"") | T27: =IF(Q27<>"",AH27,"") | U27: =IF(R27<>"",AI27,"") | V27: =IF(S27<>"",AJ27,"") | W27: =IF(T27<>"",AK27,"") | X27: =IF(U27<>"",AL27,"") | Y27: =IF(V27<>"",AM27,"") | Z27: =IF(W27<>"",AN27,"") | ... AD27: =IF(AA27<>"",AR27,"") | AG27: 0.6 | AH27: 2 | AI27: 1 | AJ27: 1 | AK27: =0.8*AJ27 -> 0.8 | AL27: =AJ27*0 -> 0 | AM27: 0.5 | AN27: 0.4 | AO27: 0 | AP27: 1
I28: =$C$5&" "&$E$6&" "&RIGHT(G15,LEN(G15)-FIND(" ",G15)) -> Industry Water heating Wood | J28: yes | K28: =$D$5&$F$6&RIGHT(H15,3)&$B$5 -> IND-WHWODExt | L28: =IF(J28="Yes",K28,"") -> IND-WHWODExt | O28: =IF(J28="Yes",I28,"") -> Industry Water heating Wood | P28: =L28 -> IND-WHWODExt | Q28: =IF(J28="yes",LEFT(P28,3)&"-"&MID(P28,7,3),"") -> IND-WOD | R28: =LEFT(P28,6) -> IND-WH | S28: =IF(P28<>"",AG28,"") -> 0.6 | T28: =IF(Q28<>"",AH28,"") -> 2 | U28: =IF(R28<>"",AI28,"") -> 1 | V28: =IF(S28<>"",AJ28,"") -> 1 | W28: =IF(T28<>"",AK28,"") -> 0.8 | X28: =IF(U28<>"",AL28,"") -> 0 | Y28: =IF(V28<>"",AM28,"") -> 0.5 | Z28: =IF(W28<>"",AN28,"") -> 0.4 | ... AD28: =IF(AA28<>"",AR28,"") -> 0 | AG28: 0.6 | AH28: 2 | AI28: 1 | AJ28: 1 | AK28: =0.8*AJ28 -> 0.8 | AL28: =AJ28*0 -> 0 | AM28: 0.5 | AN28: 0.4 | AO28: 0 | AP28: 1
I29: =$C$5&" "&$E$6&" "&RIGHT(G16,LEN(G16)-FIND(" ",G16)) -> Industry Water heating Tidal | J29: no | K29: =$D$5&$F$6&RIGHT(H16,3)&$B$5 -> IND-WHTIDExt | L29: =IF(J29="Yes",K29,"") | O29: =IF(J29="Yes",I29,"") | P29: =L29 | Q29: =IF(J29="yes",LEFT(P29,3)&"-"&MID(P29,7,3),"") | R29: =LEFT(P29,6) | S29: =IF(P29<>"",AG29,"") | T29: =IF(Q29<>"",AH29,"") | U29: =IF(R29<>"",AI29,"") | V29: =IF(S29<>"",AJ29,"") | W29: =IF(T29<>"",AK29,"") | X29: =IF(U29<>"",AL29,"") | Y29: =IF(V29<>"",AM29,"") | Z29: =IF(W29<>"",AN29,"") | ... AD29: =IF(AA29<>"",AR29,"") | AG29: 0.6 | AH29: 2 | AI29: 1 | AJ29: 1 | AK29: =0.8*AJ29 -> 0.8 | AL29: =AJ29*0 -> 0 | AM29: 0.5 | AN29: 0.4 | AO29: 0 | AP29: 1
I30: =$C$5&" "&$E$6&" "&RIGHT(G17,LEN(G17)-FIND(" ",G17)) -> Industry Water heating Electricity | J30: yes | K30: =$D$5&$F$6&RIGHT(H17,3)&$B$5 -> IND-WHELCExt | L30: =IF(J30="Yes",K30,"") -> IND-WHELCExt | O30: =IF(J30="Yes",I30,"") -> Industry Water heating Electricity | P30: =L30 -> IND-WHELCExt | Q30: =IF(J30="yes",LEFT(P30,3)&"-"&MID(P30,7,3),"") -> IND-ELC | R30: =LEFT(P30,6) -> IND-WH | S30: =IF(P30<>"",AG30,"") -> 0.6 | T30: =IF(Q30<>"",AH30,"") -> 2 | U30: =IF(R30<>"",AI30,"") -> 1 | V30: =IF(S30<>"",AJ30,"") -> 1 | W30: =IF(T30<>"",AK30,"") -> 0.8 | X30: =IF(U30<>"",AL30,"") -> 0 | Y30: =IF(V30<>"",AM30,"") -> 0.5 | Z30: =IF(W30<>"",AN30,"") -> 0.4 | ... AD30: =IF(AA30<>"",AR30,"") -> 0 | AG30: 0.6 | AH30: 2 | AI30: 1 | AJ30: 1 | AK30: =0.8*AJ30 -> 0.8 | AL30: =AJ30*0 -> 0 | AM30: 0.5 | AN30: 0.4 | AO30: 0 | AP30: 1
I31: =$C$5&" "&$E$7&" "&RIGHT(G5,LEN(G5)-FIND(" ",G5)) -> Industry High temperature process heat Coal | J31: yes | K31: =$D$5&$F$7&RIGHT(H5,3)&$B$5 -> IND-PHCOAExt | L31: =IF(J31="Yes",K31,"") -> IND-PHCOAExt | O31: =IF(J31="Yes",I31,"") -> Industry High temperature process heat Coal | P31: =L31 -> IND-PHCOAExt | Q31: =IF(J31="yes",LEFT(P31,3)&"-"&MID(P31,7,3),"") -> IND-COA | R31: =LEFT(P31,6) -> IND-PH | S31: =IF(P31<>"",AG31,"") -> 0.6 | T31: =IF(Q31<>"",AH31,"") -> 2 | U31: =IF(R31<>"",AI31,"") -> 1 | V31: =IF(S31<>"",AJ31,"") -> 1 | W31: =IF(T31<>"",AK31,"") -> 0.8 | X31: =IF(U31<>"",AL31,"") -> 0 | Y31: =IF(V31<>"",AM31,"") -> 0.5 | Z31: =IF(W31<>"",AN31,"") -> 0.4 | ... AD31: =IF(AA31<>"",AR31,"") -> 0 | AG31: 0.6 | AH31: 2 | AI31: 1 | AJ31: 1 | AK31: =0.8*AJ31 -> 0.8 | AL31: =AJ31*0 -> 0 | AM31: 0.5 | AN31: 0.4 | AO31: 0 | AP31: 1
I32: =$C$5&" "&$E$7&" "&RIGHT(G6,LEN(G6)-FIND(" ",G6)) -> Industry High temperature process heat Lignite | J32: yes | K32: =$D$5&$F$7&RIGHT(H6,3)&$B$5 -> IND-PHCOLExt | L32: =IF(J32="Yes",K32,"") -> IND-PHCOLExt | O32: =IF(J32="Yes",I32,"") -> Industry High temperature process heat Lignite | P32: =L32 -> IND-PHCOLExt | Q32: =IF(J32="yes",LEFT(P32,3)&"-"&MID(P32,7,3),"") -> IND-COL | R32: =LEFT(P32,6) -> IND-PH | S32: =IF(P32<>"",AG32,"") -> 0.6 | T32: =IF(Q32<>"",AH32,"") -> 2 | U32: =IF(R32<>"",AI32,"") -> 1 | V32: =IF(S32<>"",AJ32,"") -> 1 | W32: =IF(T32<>"",AK32,"") -> 0.8 | X32: =IF(U32<>"",AL32,"") -> 0 | Y32: =IF(V32<>"",AM32,"") -> 0.5 | Z32: =IF(W32<>"",AN32,"") -> 0.4 | ... AD32: =IF(AA32<>"",AR32,"") -> 0 | AG32: 0.6 | AH32: 2 | AI32: 1 | AJ32: 1 | AK32: =0.8*AJ32 -> 0.8 | AL32: =AJ32*0 -> 0 | AM32: 0.5 | AN32: 0.4 | AO32: 0 | AP32: 1
I33: =$C$5&" "&$E$7&" "&RIGHT(G7,LEN(G7)-FIND(" ",G7)) -> Industry High temperature process heat Crude oil | J33: yes | K33: =$D$5&$F$7&RIGHT(H7,3)&$B$5 -> IND-PHOILExt | L33: =IF(J33="Yes",K33,"") -> IND-PHOILExt | O33: =IF(J33="Yes",I33,"") -> Industry High temperature process heat Crude oil | P33: =L33 -> IND-PHOILExt | Q33: =IF(J33="yes",LEFT(P33,3)&"-"&MID(P33,7,3),"") -> IND-OIL | R33: =LEFT(P33,6) -> IND-PH | S33: =IF(P33<>"",AG33,"") -> 0.6 | T33: =IF(Q33<>"",AH33,"") -> 2 | U33: =IF(R33<>"",AI33,"") -> 1 | V33: =IF(S33<>"",AJ33,"") -> 1 | W33: =IF(T33<>"",AK33,"") -> 0.8 | X33: =IF(U33<>"",AL33,"") -> 0 | Y33: =IF(V33<>"",AM33,"") -> 0.5 | Z33: =IF(W33<>"",AN33,"") -> 0.4 | ... AD33: =IF(AA33<>"",AR33,"") -> 0 | AG33: 0.6 | AH33: 2 | AI33: 1 | AJ33: 1 | AK33: =0.8*AJ33 -> 0.8 | AL33: =AJ33*0 -> 0 | AM33: 0.5 | AN33: 0.4 | AO33: 0 | AP33: 1
I34: =$C$5&" "&$E$7&" "&RIGHT(G8,LEN(G8)-FIND(" ",G8)) -> Industry High temperature process heat Natural Gas | J34: no | K34: =$D$5&$F$7&RIGHT(H8,3)&$B$5 -> IND-PHNGAExt | L34: =IF(J34="Yes",K34,"") | O34: =IF(J34="Yes",I34,"") | P34: =L34 | Q34: =IF(J34="yes",LEFT(P34,3)&"-"&MID(P34,7,3),"") | R34: =LEFT(P34,6) | S34: =IF(P34<>"",AG34,"") | T34: =IF(Q34<>"",AH34,"") | U34: =IF(R34<>"",AI34,"") | V34: =IF(S34<>"",AJ34,"") | W34: =IF(T34<>"",AK34,"") | X34: =IF(U34<>"",AL34,"") | Y34: =IF(V34<>"",AM34,"") | Z34: =IF(W34<>"",AN34,"") | ... AD34: =IF(AA34<>"",AR34,"") | AG34: 0.6 | AH34: 2 | AI34: 1 | AJ34: 1 | AK34: =0.8*AJ34 -> 0.8 | AL34: =AJ34*0 -> 0 | AM34: 0.5 | AN34: 0.4 | AO34: 0 | AP34: 1
I35: =$C$5&" "&$E$7&" "&RIGHT(G9,LEN(G9)-FIND(" ",G9)) -> Industry High temperature process heat Hydro | J35: no | K35: =$D$5&$F$7&RIGHT(H9,3)&$B$5 -> IND-PHHYDExt | L35: =IF(J35="Yes",K35,"") | O35: =IF(J35="Yes",I35,"") | P35: =L35 | Q35: =IF(J35="yes",LEFT(P35,3)&"-"&MID(P35,7,3),"") | R35: =LEFT(P35,6) | S35: =IF(P35<>"",AG35,"") | T35: =IF(Q35<>"",AH35,"") | U35: =IF(R35<>"",AI35,"") | V35: =IF(S35<>"",AJ35,"") | W35: =IF(T35<>"",AK35,"") | X35: =IF(U35<>"",AL35,"") | Y35: =IF(V35<>"",AM35,"") | Z35: =IF(W35<>"",AN35,"") | ... AD35: =IF(AA35<>"",AR35,"") | AG35: 0.6 | AH35: 2 | AI35: 1 | AJ35: 1 | AK35: =0.8*AJ35 -> 0.8 | AL35: =AJ35*0 -> 0 | AM35: 0.5 | AN35: 0.4 | AO35: 0 | AP35: 1
I36: =$C$5&" "&$E$7&" "&RIGHT(G10,LEN(G10)-FIND(" ",G10)) -> Industry High temperature process heat Geothermal | J36: no | K36: =$D$5&$F$7&RIGHT(H10,3)&$B$5 -> IND-PHGEOExt | L36: =IF(J36="Yes",K36,"") | O36: =IF(J36="Yes",I36,"") | P36: =L36 | Q36: =IF(J36="yes",LEFT(P36,3)&"-"&MID(P36,7,3),"") | R36: =LEFT(P36,6) | S36: =IF(P36<>"",AG36,"") | T36: =IF(Q36<>"",AH36,"") | U36: =IF(R36<>"",AI36,"") | V36: =IF(S36<>"",AJ36,"") | W36: =IF(T36<>"",AK36,"") | X36: =IF(U36<>"",AL36,"") | Y36: =IF(V36<>"",AM36,"") | Z36: =IF(W36<>"",AN36,"") | ... AD36: =IF(AA36<>"",AR36,"") | AG36: 0.6 | AH36: 2 | AI36: 1 | AJ36: 1 | AK36: =0.8*AJ36 -> 0.8 | AL36: =AJ36*0 -> 0 | AM36: 0.5 | AN36: 0.4 | AO36: 0 | AP36: 1
I37: =$C$5&" "&$E$7&" "&RIGHT(G11,LEN(G11)-FIND(" ",G11)) -> Industry High temperature process heat Solar | J37: no | K37: =$D$5&$F$7&RIGHT(H11,3)&$B$5 -> IND-PHSOLExt | L37: =IF(J37="Yes",K37,"") | O37: =IF(J37="Yes",I37,"") | P37: =L37 | Q37: =IF(J37="yes",LEFT(P37,3)&"-"&MID(P37,7,3),"") | R37: =LEFT(P37,6) | S37: =IF(P37<>"",AG37,"") | T37: =IF(Q37<>"",AH37,"") | U37: =IF(R37<>"",AI37,"") | V37: =IF(S37<>"",AJ37,"") | W37: =IF(T37<>"",AK37,"") | X37: =IF(U37<>"",AL37,"") | Y37: =IF(V37<>"",AM37,"") | Z37: =IF(W37<>"",AN37,"") | ... AD37: =IF(AA37<>"",AR37,"") | AG37: 0.6 | AH37: 2 | AI37: 1 | AJ37: 1 | AK37: =0.8*AJ37 -> 0.8 | AL37: =AJ37*0 -> 0 | AM37: 0.5 | AN37: 0.4 | AO37: 0 | AP37: 1
I38: =$C$5&" "&$E$7&" "&RIGHT(G12,LEN(G12)-FIND(" ",G12)) -> Industry High temperature process heat Wind | J38: no | K38: =$D$5&$F$7&RIGHT(H12,3)&$B$5 -> IND-PHWINExt | L38: =IF(J38="Yes",K38,"") | O38: =IF(J38="Yes",I38,"") | P38: =L38 | Q38: =IF(J38="yes",LEFT(P38,3)&"-"&MID(P38,7,3),"") | R38: =LEFT(P38,6) | S38: =IF(P38<>"",AG38,"") | T38: =IF(Q38<>"",AH38,"") | U38: =IF(R38<>"",AI38,"") | V38: =IF(S38<>"",AJ38,"") | W38: =IF(T38<>"",AK38,"") | X38: =IF(U38<>"",AL38,"") | Y38: =IF(V38<>"",AM38,"") | Z38: =IF(W38<>"",AN38,"") | ... AD38: =IF(AA38<>"",AR38,"") | AG38: 0.6 | AH38: 2 | AI38: 1 | AJ38: 1 | AK38: =0.8*AJ38 -> 0.8 | AL38: =AJ38*0 -> 0 | AM38: 0.5 | AN38: 0.4 | AO38: 0 | AP38: 1
I39: =$C$5&" "&$E$7&" "&RIGHT(G13,LEN(G13)-FIND(" ",G13)) -> Industry High temperature process heat Bio Liquids | J39: no | K39: =$D$5&$F$7&RIGHT(H13,3)&$B$5 -> IND-PHBILExt | L39: =IF(J39="Yes",K39,"") | O39: =IF(J39="Yes",I39,"") | P39: =L39 | Q39: =IF(J39="yes",LEFT(P39,3)&"-"&MID(P39,7,3),"") | R39: =LEFT(P39,6) | S39: =IF(P39<>"",AG39,"") | T39: =IF(Q39<>"",AH39,"") | U39: =IF(R39<>"",AI39,"") | V39: =IF(S39<>"",AJ39,"") | W39: =IF(T39<>"",AK39,"") | X39: =IF(U39<>"",AL39,"") | Y39: =IF(V39<>"",AM39,"") | Z39: =IF(W39<>"",AN39,"") | ... AD39: =IF(AA39<>"",AR39,"") | AG39: 0.6 | AH39: 2 | AI39: 1 | AJ39: 1 | AK39: =0.8*AJ39 -> 0.8 | AL39: =AJ39*0 -> 0 | AM39: 0.5 | AN39: 0.4 | AO39: 0 | AP39: 1
I40: =$C$5&" "&$E$7&" "&RIGHT(G14,LEN(G14)-FIND(" ",G14)) -> Industry High temperature process heat Biogas | J40: no | K40: =$D$5&$F$7&RIGHT(H14,3)&$B$5 -> IND-PHBIGExt | L40: =IF(J40="Yes",K40,"") | O40: =IF(J40="Yes",I40,"") | P40: =L40 | Q40: =IF(J40="yes",LEFT(P40,3)&"-"&MID(P40,7,3),"") | R40: =LEFT(P40,6) | S40: =IF(P40<>"",AG40,"") | T40: =IF(Q40<>"",AH40,"") | U40: =IF(R40<>"",AI40,"") | V40: =IF(S40<>"",AJ40,"") | W40: =IF(T40<>"",AK40,"") | X40: =IF(U40<>"",AL40,"") | Y40: =IF(V40<>"",AM40,"") | Z40: =IF(W40<>"",AN40,"") | ... AD40: =IF(AA40<>"",AR40,"") | AG40: 0.6 | AH40: 2 | AI40: 1 | AJ40: 1 | AK40: =0.8*AJ40 -> 0.8 | AL40: =AJ40*0 -> 0 | AM40: 0.5 | AN40: 0.4 | AO40: 0 | AP40: 1
I41: =$C$5&" "&$E$7&" "&RIGHT(G15,LEN(G15)-FIND(" ",G15)) -> Industry High temperature process heat Wood | J41: no | K41: =$D$5&$F$7&RIGHT(H15,3)&$B$5 -> IND-PHWODExt | L41: =IF(J41="Yes",K41,"") | O41: =IF(J41="Yes",I41,"") | P41: =L41 | Q41: =IF(J41="yes",LEFT(P41,3)&"-"&MID(P41,7,3),"") | R41: =LEFT(P41,6) | S41: =IF(P41<>"",AG41,"") | T41: =IF(Q41<>"",AH41,"") | U41: =IF(R41<>"",AI41,"") | V41: =IF(S41<>"",AJ41,"") | W41: =IF(T41<>"",AK41,"") | X41: =IF(U41<>"",AL41,"") | Y41: =IF(V41<>"",AM41,"") | Z41: =IF(W41<>"",AN41,"") | ... AD41: =IF(AA41<>"",AR41,"") | AG41: 0.6 | AH41: 2 | AI41: 1 | AJ41: 1 | AK41: =0.8*AJ41 -> 0.8 | AL41: =AJ41*0 -> 0 | AM41: 0.5 | AN41: 0.4 | AO41: 0 | AP41: 1
I42: =$C$5&" "&$E$7&" "&RIGHT(G16,LEN(G16)-FIND(" ",G16)) -> Industry High temperature process heat Tidal | J42: no | K42: =$D$5&$F$7&RIGHT(H16,3)&$B$5 -> IND-PHTIDExt | L42: =IF(J42="Yes",K42,"") | O42: =IF(J42="Yes",I42,"") | P42: =L42 | Q42: =IF(J42="yes",LEFT(P42,3)&"-"&MID(P42,7,3),"") | R42: =LEFT(P42,6) | S42: =IF(P42<>"",AG42,"") | T42: =IF(Q42<>"",AH42,"") | U42: =IF(R42<>"",AI42,"") | V42: =IF(S42<>"",AJ42,"") | W42: =IF(T42<>"",AK42,"") | X42: =IF(U42<>"",AL42,"") | Y42: =IF(V42<>"",AM42,"") | Z42: =IF(W42<>"",AN42,"") | ... AD42: =IF(AA42<>"",AR42,"") | AG42: 0.6 | AH42: 2 | AI42: 1 | AJ42: 1 | AK42: =0.8*AJ42 -> 0.8 | AL42: =AJ42*0 -> 0 | AM42: 0.5 | AN42: 0.4 | AO42: 0 | AP42: 1
I43: =$C$5&" "&$E$7&" "&RIGHT(G17,LEN(G17)-FIND(" ",G17)) -> Industry High temperature process heat Electricity | J43: yes | K43: =$D$5&$F$7&RIGHT(H17,3)&$B$5 -> IND-PHELCExt | L43: =IF(J43="Yes",K43,"") -> IND-PHELCExt | O43: =IF(J43="Yes",I43,"") -> Industry High temperature process heat Electricity | P43: =L43 -> IND-PHELCExt | Q43: =IF(J43="yes",LEFT(P43,3)&"-"&MID(P43,7,3),"") -> IND-ELC | R43: =LEFT(P43,6) -> IND-PH | S43: =IF(P43<>"",AG43,"") -> 0.6 | T43: =IF(Q43<>"",AH43,"") -> 2 | U43: =IF(R43<>"",AI43,"") -> 1 | V43: =IF(S43<>"",AJ43,"") -> 1 | W43: =IF(T43<>"",AK43,"") -> 0.8 | X43: =IF(U43<>"",AL43,"") -> 0 | Y43: =IF(V43<>"",AM43,"") -> 0.5 | Z43: =IF(W43<>"",AN43,"") -> 0.4 | ... AD43: =IF(AA43<>"",AR43,"") -> 0 | AG43: 0.6 | AH43: 2 | AI43: 1 | AJ43: 1 | AK43: =0.8*AJ43 -> 0.8 | AL43: =AJ43*0 -> 0 | AM43: 0.5 | AN43: 0.4 | AO43: 0 | AP43: 1
I44: =$C$5&" "&$E$8&" "&RIGHT(G5,LEN(G5)-FIND(" ",G5)) -> Industry Lighting Coal | J44: no | K44: =$D$5&$F$8&RIGHT(H5,3)&$B$5 -> IND-LTCOAExt | L44: =IF(J44="Yes",K44,"") | O44: =IF(J44="Yes",I44,"") | P44: =L44 | Q44: =IF(J44="yes",LEFT(P44,3)&"-"&MID(P44,7,3),"") | R44: =LEFT(P44,6) | S44: =IF(P44<>"",AG44,"") | T44: =IF(Q44<>"",AH44,"") | U44: =IF(R44<>"",AI44,"") | V44: =IF(S44<>"",AJ44,"") | W44: =IF(T44<>"",AK44,"") | X44: =IF(U44<>"",AL44,"") | Y44: =IF(V44<>"",AM44,"") | Z44: =IF(W44<>"",AN44,"") | ... AD44: =IF(AA44<>"",AR44,"") | AG44: 0.6 | AH44: 2 | AI44: 1 | AJ44: 1 | AK44: =0.8*AJ44 -> 0.8 | AL44: =AJ44*0 -> 0 | AM44: 0.5 | AN44: 0.4 | AO44: 0 | AP44: 1
I45: =$C$5&" "&$E$8&" "&RIGHT(G6,LEN(G6)-FIND(" ",G6)) -> Industry Lighting Lignite | J45: no | K45: =$D$5&$F$8&RIGHT(H6,3)&$B$5 -> IND-LTCOLExt | L45: =IF(J45="Yes",K45,"") | O45: =IF(J45="Yes",I45,"") | P45: =L45 | Q45: =IF(J45="yes",LEFT(P45,3)&"-"&MID(P45,7,3),"") | R45: =LEFT(P45,6) | S45: =IF(P45<>"",AG45,"") | T45: =IF(Q45<>"",AH45,"") | U45: =IF(R45<>"",AI45,"") | V45: =IF(S45<>"",AJ45,"") | W45: =IF(T45<>"",AK45,"") | X45: =IF(U45<>"",AL45,"") | Y45: =IF(V45<>"",AM45,"") | Z45: =IF(W45<>"",AN45,"") | ... AD45: =IF(AA45<>"",AR45,"") | AG45: 0.6 | AH45: 2 | AI45: 1 | AJ45: 1 | AK45: =0.8*AJ45 -> 0.8 | AL45: =AJ45*0 -> 0 | AM45: 0.5 | AN45: 0.4 | AO45: 0 | AP45: 1
I46: =$C$5&" "&$E$8&" "&RIGHT(G7,LEN(G7)-FIND(" ",G7)) -> Industry Lighting Crude oil | J46: no | K46: =$D$5&$F$8&RIGHT(H7,3)&$B$5 -> IND-LTOILExt | L46: =IF(J46="Yes",K46,"") | O46: =IF(J46="Yes",I46,"") | P46: =L46 | Q46: =IF(J46="yes",LEFT(P46,3)&"-"&MID(P46,7,3),"") | R46: =LEFT(P46,6) | S46: =IF(P46<>"",AG46,"") | T46: =IF(Q46<>"",AH46,"") | U46: =IF(R46<>"",AI46,"") | V46: =IF(S46<>"",AJ46,"") | W46: =IF(T46<>"",AK46,"") | X46: =IF(U46<>"",AL46,"") | Y46: =IF(V46<>"",AM46,"") | Z46: =IF(W46<>"",AN46,"") | ... AD46: =IF(AA46<>"",AR46,"") | AG46: 0.6 | AH46: 2 | AI46: 1 | AJ46: 1 | AK46: =0.8*AJ46 -> 0.8 | AL46: =AJ46*0 -> 0 | AM46: 0.5 | AN46: 0.4 | AO46: 0 | AP46: 1
I47: =$C$5&" "&$E$8&" "&RIGHT(G8,LEN(G8)-FIND(" ",G8)) -> Industry Lighting Natural Gas | J47: no | K47: =$D$5&$F$8&RIGHT(H8,3)&$B$5 -> IND-LTNGAExt | L47: =IF(J47="Yes",K47,"") | O47: =IF(J47="Yes",I47,"") | P47: =L47 | Q47: =IF(J47="yes",LEFT(P47,3)&"-"&MID(P47,7,3),"") | R47: =LEFT(P47,6) | S47: =IF(P47<>"",AG47,"") | T47: =IF(Q47<>"",AH47,"") | U47: =IF(R47<>"",AI47,"") | V47: =IF(S47<>"",AJ47,"") | W47: =IF(T47<>"",AK47,"") | X47: =IF(U47<>"",AL47,"") | Y47: =IF(V47<>"",AM47,"") | Z47: =IF(W47<>"",AN47,"") | ... AD47: =IF(AA47<>"",AR47,"") | AG47: 0.6 | AH47: 2 | AI47: 1 | AJ47: 1 | AK47: =0.8*AJ47 -> 0.8 | AL47: =AJ47*0 -> 0 | AM47: 0.5 | AN47: 0.4 | AO47: 0 | AP47: 1
I48: =$C$5&" "&$E$8&" "&RIGHT(G9,LEN(G9)-FIND(" ",G9)) -> Industry Lighting Hydro | J48: no | K48: =$D$5&$F$8&RIGHT(H9,3)&$B$5 -> IND-LTHYDExt | L48: =IF(J48="Yes",K48,"") | O48: =IF(J48="Yes",I48,"") | P48: =L48 | Q48: =IF(J48="yes",LEFT(P48,3)&"-"&MID(P48,7,3),"") | R48: =LEFT(P48,6) | S48: =IF(P48<>"",AG48,"") | T48: =IF(Q48<>"",AH48,"") | U48: =IF(R48<>"",AI48,"") | V48: =IF(S48<>"",AJ48,"") | W48: =IF(T48<>"",AK48,"") | X48: =IF(U48<>"",AL48,"") | Y48: =IF(V48<>"",AM48,"") | Z48: =IF(W48<>"",AN48,"") | ... AD48: =IF(AA48<>"",AR48,"") | AG48: 0.6 | AH48: 2 | AI48: 1 | AJ48: 1 | AK48: =0.8*AJ48 -> 0.8 | AL48: =AJ48*0 -> 0 | AM48: 0.5 | AN48: 0.4 | AO48: 0 | AP48: 1
I49: =$C$5&" "&$E$8&" "&RIGHT(G10,LEN(G10)-FIND(" ",G10)) -> Industry Lighting Geothermal | J49: no | K49: =$D$5&$F$8&RIGHT(H10,3)&$B$5 -> IND-LTGEOExt | L49: =IF(J49="Yes",K49,"") | O49: =IF(J49="Yes",I49,"") | P49: =L49 | Q49: =IF(J49="yes",LEFT(P49,3)&"-"&MID(P49,7,3),"") | R49: =LEFT(P49,6) | S49: =IF(P49<>"",AG49,"") | T49: =IF(Q49<>"",AH49,"") | U49: =IF(R49<>"",AI49,"") | V49: =IF(S49<>"",AJ49,"") | W49: =IF(T49<>"",AK49,"") | X49: =IF(U49<>"",AL49,"") | Y49: =IF(V49<>"",AM49,"") | Z49: =IF(W49<>"",AN49,"") | ... AD49: =IF(AA49<>"",AR49,"") | AG49: 0.6 | AH49: 2 | AI49: 1 | AJ49: 1 | AK49: =0.8*AJ49 -> 0.8 | AL49: =AJ49*0 -> 0 | AM49: 0.5 | AN49: 0.4 | AO49: 0 | AP49: 1
I50: =$C$5&" "&$E$8&" "&RIGHT(G11,LEN(G11)-FIND(" ",G11)) -> Industry Lighting Solar | J50: no | K50: =$D$5&$F$8&RIGHT(H11,3)&$B$5 -> IND-LTSOLExt | L50: =IF(J50="Yes",K50,"") | O50: =IF(J50="Yes",I50,"") | P50: =L50 | Q50: =IF(J50="yes",LEFT(P50,3)&"-"&MID(P50,7,3),"") | R50: =LEFT(P50,6) | S50: =IF(P50<>"",AG50,"") | T50: =IF(Q50<>"",AH50,"") | U50: =IF(R50<>"",AI50,"") | V50: =IF(S50<>"",AJ50,"") | W50: =IF(T50<>"",AK50,"") | X50: =IF(U50<>"",AL50,"") | Y50: =IF(V50<>"",AM50,"") | Z50: =IF(W50<>"",AN50,"") | ... AD50: =IF(AA50<>"",AR50,"") | AG50: 0.6 | AH50: 2 | AI50: 1 | AJ50: 1 | AK50: =0.8*AJ50 -> 0.8 | AL50: =AJ50*0 -> 0 | AM50: 0.5 | AN50: 0.4 | AO50: 0 | AP50: 1
I51: =$C$5&" "&$E$8&" "&RIGHT(G12,LEN(G12)-FIND(" ",G12)) -> Industry Lighting Wind | J51: no | K51: =$D$5&$F$8&RIGHT(H12,3)&$B$5 -> IND-LTWINExt | L51: =IF(J51="Yes",K51,"") | O51: =IF(J51="Yes",I51,"") | P51: =L51 | Q51: =IF(J51="yes",LEFT(P51,3)&"-"&MID(P51,7,3),"") | R51: =LEFT(P51,6) | S51: =IF(P51<>"",AG51,"") | T51: =IF(Q51<>"",AH51,"") | U51: =IF(R51<>"",AI51,"") | V51: =IF(S51<>"",AJ51,"") | W51: =IF(T51<>"",AK51,"") | X51: =IF(U51<>"",AL51,"") | Y51: =IF(V51<>"",AM51,"") | Z51: =IF(W51<>"",AN51,"") | ... AD51: =IF(AA51<>"",AR51,"") | AG51: 0.6 | AH51: 2 | AI51: 1 | AJ51: 1 | AK51: =0.8*AJ51 -> 0.8 | AL51: =AJ51*0 -> 0 | AM51: 0.5 | AN51: 0.4 | AO51: 0 | AP51: 1
I52: =$C$5&" "&$E$8&" "&RIGHT(G13,LEN(G13)-FIND(" ",G13)) -> Industry Lighting Bio Liquids | J52: no | K52: =$D$5&$F$8&RIGHT(H13,3)&$B$5 -> IND-LTBILExt | L52: =IF(J52="Yes",K52,"") | O52: =IF(J52="Yes",I52,"") | P52: =L52 | Q52: =IF(J52="yes",LEFT(P52,3)&"-"&MID(P52,7,3),"") | R52: =LEFT(P52,6) | S52: =IF(P52<>"",AG52,"") | T52: =IF(Q52<>"",AH52,"") | U52: =IF(R52<>"",AI52,"") | V52: =IF(S52<>"",AJ52,"") | W52: =IF(T52<>"",AK52,"") | X52: =IF(U52<>"",AL52,"") | Y52: =IF(V52<>"",AM52,"") | Z52: =IF(W52<>"",AN52,"") | ... AD52: =IF(AA52<>"",AR52,"") | AG52: 0.6 | AH52: 2 | AI52: 1 | AJ52: 1 | AK52: =0.8*AJ52 -> 0.8 | AL52: =AJ52*0 -> 0 | AM52: 0.5 | AN52: 0.4 | AO52: 0 | AP52: 1
I53: =$C$5&" "&$E$8&" "&RIGHT(G14,LEN(G14)-FIND(" ",G14)) -> Industry Lighting Biogas | J53: no | K53: =$D$5&$F$8&RIGHT(H14,3)&$B$5 -> IND-LTBIGExt | L53: =IF(J53="Yes",K53,"") | O53: =IF(J53="Yes",I53,"") | P53: =L53 | Q53: =IF(J53="yes",LEFT(P53,3)&"-"&MID(P53,7,3),"") | R53: =LEFT(P53,6) | S53: =IF(P53<>"",AG53,"") | T53: =IF(Q53<>"",AH53,"") | U53: =IF(R53<>"",AI53,"") | V53: =IF(S53<>"",AJ53,"") | W53: =IF(T53<>"",AK53,"") | X53: =IF(U53<>"",AL53,"") | Y53: =IF(V53<>"",AM53,"") | Z53: =IF(W53<>"",AN53,"") | ... AD53: =IF(AA53<>"",AR53,"") | AG53: 0.6 | AH53: 2 | AI53: 1 | AJ53: 1 | AK53: =0.8*AJ53 -> 0.8 | AL53: =AJ53*0 -> 0 | AM53: 0.5 | AN53: 0.4 | AO53: 0 | AP53: 1
I54: =$C$5&" "&$E$8&" "&RIGHT(G15,LEN(G15)-FIND(" ",G15)) -> Industry Lighting Wood | J54: no | K54: =$D$5&$F$8&RIGHT(H15,3)&$B$5 -> IND-LTWODExt | L54: =IF(J54="Yes",K54,"") | O54: =IF(J54="Yes",I54,"") | P54: =L54 | Q54: =IF(J54="yes",LEFT(P54,3)&"-"&MID(P54,7,3),"") | R54: =LEFT(P54,6) | S54: =IF(P54<>"",AG54,"") | T54: =IF(Q54<>"",AH54,"") | U54: =IF(R54<>"",AI54,"") | V54: =IF(S54<>"",AJ54,"") | W54: =IF(T54<>"",AK54,"") | X54: =IF(U54<>"",AL54,"") | Y54: =IF(V54<>"",AM54,"") | Z54: =IF(W54<>"",AN54,"") | ... AD54: =IF(AA54<>"",AR54,"") | AG54: 0.6 | AH54: 2 | AI54: 1 | AJ54: 1 | AK54: =0.8*AJ54 -> 0.8 | AL54: =AJ54*0 -> 0 | AM54: 0.5 | AN54: 0.4 | AO54: 0 | AP54: 1
I55: =$C$5&" "&$E$8&" "&RIGHT(G16,LEN(G16)-FIND(" ",G16)) -> Industry Lighting Tidal | J55: no | K55: =$D$5&$F$8&RIGHT(H16,3)&$B$5 -> IND-LTTIDExt | L55: =IF(J55="Yes",K55,"") | O55: =IF(J55="Yes",I55,"") | P55: =L55 | Q55: =IF(J55="yes",LEFT(P55,3)&"-"&MID(P55,7,3),"") | R55: =LEFT(P55,6) | S55: =IF(P55<>"",AG55,"") | T55: =IF(Q55<>"",AH55,"") | U55: =IF(R55<>"",AI55,"") | V55: =IF(S55<>"",AJ55,"") | W55: =IF(T55<>"",AK55,"") | X55: =IF(U55<>"",AL55,"") | Y55: =IF(V55<>"",AM55,"") | Z55: =IF(W55<>"",AN55,"") | ... AD55: =IF(AA55<>"",AR55,"") | AG55: 0.6 | AH55: 2 | AI55: 1 | AJ55: 1 | AK55: =0.8*AJ55 -> 0.8 | AL55: =AJ55*0 -> 0 | AM55: 0.5 | AN55: 0.4 | AO55: 0 | AP55: 1
I56: =$C$5&" "&$E$8&" "&RIGHT(G17,LEN(G17)-FIND(" ",G17)) -> Industry Lighting Electricity | J56: yes | K56: =$D$5&$F$8&RIGHT(H17,3)&$B$5 -> IND-LTELCExt | L56: =IF(J56="Yes",K56,"") -> IND-LTELCExt | O56: =IF(J56="Yes",I56,"") -> Industry Lighting Electricity | P56: =L56 -> IND-LTELCExt | Q56: =IF(J56="yes",LEFT(P56,3)&"-"&MID(P56,7,3),"") -> IND-ELC | R56: =LEFT(P56,6) -> IND-LT | S56: =IF(P56<>"",AG56,"") -> 0.6 | T56: =IF(Q56<>"",AH56,"") -> 2 | U56: =IF(R56<>"",AI56,"") -> 1 | V56: =IF(S56<>"",AJ56,"") -> 1 | W56: =IF(T56<>"",AK56,"") -> 0.8 | X56: =IF(U56<>"",AL56,"") -> 0 | Y56: =IF(V56<>"",AM56,"") -> 0.5 | Z56: =IF(W56<>"",AN56,"") -> 0.4 | ... AD56: =IF(AA56<>"",AR56,"") -> 0 | AG56: 0.6 | AH56: 2 | AI56: 1 | AJ56: 1 | AK56: =0.8*AJ56 -> 0.8 | AL56: =AJ56*0 -> 0 | AM56: 0.5 | AN56: 0.4 | AO56: 0 | AP56: 1
I57: =$C$5&" "&$E$9&" "&RIGHT(G5,LEN(G5)-FIND(" ",G5)) -> Industry Air conditioning Coal | J57: no | K57: =$D$5&$F$9&RIGHT(H5,3)&$B$5 -> IND-ACCOAExt | L57: =IF(J57="Yes",K57,"") | O57: =IF(J57="Yes",I57,"") | P57: =L57 | Q57: =IF(J57="yes",LEFT(P57,3)&"-"&MID(P57,7,3),"") | R57: =LEFT(P57,6) | S57: =IF(P57<>"",AG57,"") | T57: =IF(Q57<>"",AH57,"") | U57: =IF(R57<>"",AI57,"") | V57: =IF(S57<>"",AJ57,"") | W57: =IF(T57<>"",AK57,"") | X57: =IF(U57<>"",AL57,"") | Y57: =IF(V57<>"",AM57,"") | Z57: =IF(W57<>"",AN57,"") | ... AD57: =IF(AA57<>"",AR57,"") | AG57: 0.6 | AH57: 2 | AI57: 1 | AJ57: 1 | AK57: =0.8*AJ57 -> 0.8 | AL57: =AJ57*0 -> 0 | AM57: 0.5 | AN57: 0.4 | AO57: 0 | AP57: 1
I58: =$C$5&" "&$E$9&" "&RIGHT(G6,LEN(G6)-FIND(" ",G6)) -> Industry Air conditioning Lignite | J58: no | K58: =$D$5&$F$9&RIGHT(H6,3)&$B$5 -> IND-ACCOLExt | L58: =IF(J58="Yes",K58,"") | O58: =IF(J58="Yes",I58,"") | P58: =L58 | Q58: =IF(J58="yes",LEFT(P58,3)&"-"&MID(P58,7,3),"") | R58: =LEFT(P58,6) | S58: =IF(P58<>"",AG58,"") | T58: =IF(Q58<>"",AH58,"") | U58: =IF(R58<>"",AI58,"") | V58: =IF(S58<>"",AJ58,"") | W58: =IF(T58<>"",AK58,"") | X58: =IF(U58<>"",AL58,"") | Y58: =IF(V58<>"",AM58,"") | Z58: =IF(W58<>"",AN58,"") | ... AD58: =IF(AA58<>"",AR58,"") | AG58: 0.6 | AH58: 2 | AI58: 1 | AJ58: 1 | AK58: =0.8*AJ58 -> 0.8 | AL58: =AJ58*0 -> 0 | AM58: 0.5 | AN58: 0.4 | AO58: 0 | AP58: 1
I59: =$C$5&" "&$E$9&" "&RIGHT(G7,LEN(G7)-FIND(" ",G7)) -> Industry Air conditioning Crude oil | J59: no | K59: =$D$5&$F$9&RIGHT(H7,3)&$B$5 -> IND-ACOILExt | L59: =IF(J59="Yes",K59,"") | O59: =IF(J59="Yes",I59,"") | P59: =L59 | Q59: =IF(J59="yes",LEFT(P59,3)&"-"&MID(P59,7,3),"") | R59: =LEFT(P59,6) | S59: =IF(P59<>"",AG59,"") | T59: =IF(Q59<>"",AH59,"") | U59: =IF(R59<>"",AI59,"") | V59: =IF(S59<>"",AJ59,"") | W59: =IF(T59<>"",AK59,"") | X59: =IF(U59<>"",AL59,"") | Y59: =IF(V59<>"",AM59,"") | Z59: =IF(W59<>"",AN59,"") | ... AD59: =IF(AA59<>"",AR59,"") | AG59: 0.6 | AH59: 2 | AI59: 1 | AJ59: 1 | AK59: =0.8*AJ59 -> 0.8 | AL59: =AJ59*0 -> 0 | AM59: 0.5 | AN59: 0.4 | AO59: 0 | AP59: 1
I60: =$C$5&" "&$E$9&" "&RIGHT(G8,LEN(G8)-FIND(" ",G8)) -> Industry Air conditioning Natural Gas | J60: no | K60: =$D$5&$F$9&RIGHT(H8,3)&$B$5 -> IND-ACNGAExt | L60: =IF(J60="Yes",K60,"") | O60: =IF(J60="Yes",I60,"") | P60: =L60 | Q60: =IF(J60="yes",LEFT(P60,3)&"-"&MID(P60,7,3),"") | R60: =LEFT(P60,6) | S60: =IF(P60<>"",AG60,"") | T60: =IF(Q60<>"",AH60,"") | U60: =IF(R60<>"",AI60,"") | V60: =IF(S60<>"",AJ60,"") | W60: =IF(T60<>"",AK60,"") | X60: =IF(U60<>"",AL60,"") | Y60: =IF(V60<>"",AM60,"") | Z60: =IF(W60<>"",AN60,"") | ... AD60: =IF(AA60<>"",AR60,"") | AG60: 0.6 | AH60: 2 | AI60: 1 | AJ60: 1 | AK60: =0.8*AJ60 -> 0.8 | AL60: =AJ60*0 -> 0 | AM60: 0.5 | AN60: 0.4 | AO60: 0 | AP60: 1
I61: =$C$5&" "&$E$9&" "&RIGHT(G9,LEN(G9)-FIND(" ",G9)) -> Industry Air conditioning Hydro | J61: no | K61: =$D$5&$F$9&RIGHT(H9,3)&$B$5 -> IND-ACHYDExt | L61: =IF(J61="Yes",K61,"") | O61: =IF(J61="Yes",I61,"") | P61: =L61 | Q61: =IF(J61="yes",LEFT(P61,3)&"-"&MID(P61,7,3),"") | R61: =LEFT(P61,6) | S61: =IF(P61<>"",AG61,"") | T61: =IF(Q61<>"",AH61,"") | U61: =IF(R61<>"",AI61,"") | V61: =IF(S61<>"",AJ61,"") | W61: =IF(T61<>"",AK61,"") | X61: =IF(U61<>"",AL61,"") | Y61: =IF(V61<>"",AM61,"") | Z61: =IF(W61<>"",AN61,"") | ... AD61: =IF(AA61<>"",AR61,"") | AG61: 0.6 | AH61: 2 | AI61: 1 | AJ61: 1 | AK61: =0.8*AJ61 -> 0.8 | AL61: =AJ61*0 -> 0 | AM61: 0.5 | AN61: 0.4 | AO61: 0 | AP61: 1
I62: =$C$5&" "&$E$9&" "&RIGHT(G10,LEN(G10)-FIND(" ",G10)) -> Industry Air conditioning Geothermal | J62: no | K62: =$D$5&$F$9&RIGHT(H10,3)&$B$5 -> IND-ACGEOExt | L62: =IF(J62="Yes",K62,"") | O62: =IF(J62="Yes",I62,"") | P62: =L62 | Q62: =IF(J62="yes",LEFT(P62,3)&"-"&MID(P62,7,3),"") | R62: =LEFT(P62,6) | S62: =IF(P62<>"",AG62,"") | T62: =IF(Q62<>"",AH62,"") | U62: =IF(R62<>"",AI62,"") | V62: =IF(S62<>"",AJ62,"") | W62: =IF(T62<>"",AK62,"") | X62: =IF(U62<>"",AL62,"") | Y62: =IF(V62<>"",AM62,"") | Z62: =IF(W62<>"",AN62,"") | ... AD62: =IF(AA62<>"",AR62,"") | AG62: 0.6 | AH62: 2 | AI62: 1 | AJ62: 1 | AK62: =0.8*AJ62 -> 0.8 | AL62: =AJ62*0 -> 0 | AM62: 0.5 | AN62: 0.4 | AO62: 0 | AP62: 1
I63: =$C$5&" "&$E$9&" "&RIGHT(G11,LEN(G11)-FIND(" ",G11)) -> Industry Air conditioning Solar | J63: no | K63: =$D$5&$F$9&RIGHT(H11,3)&$B$5 -> IND-ACSOLExt | L63: =IF(J63="Yes",K63,"") | O63: =IF(J63="Yes",I63,"") | P63: =L63 | Q63: =IF(J63="yes",LEFT(P63,3)&"-"&MID(P63,7,3),"") | R63: =LEFT(P63,6) | S63: =IF(P63<>"",AG63,"") | T63: =IF(Q63<>"",AH63,"") | U63: =IF(R63<>"",AI63,"") | V63: =IF(S63<>"",AJ63,"") | W63: =IF(T63<>"",AK63,"") | X63: =IF(U63<>"",AL63,"") | Y63: =IF(V63<>"",AM63,"") | Z63: =IF(W63<>"",AN63,"") | ... AD63: =IF(AA63<>"",AR63,"") | AG63: 0.6 | AH63: 2 | AI63: 1 | AJ63: 1 | AK63: =0.8*AJ63 -> 0.8 | AL63: =AJ63*0 -> 0 | AM63: 0.5 | AN63: 0.4 | AO63: 0 | AP63: 1
I64: =$C$5&" "&$E$9&" "&RIGHT(G12,LEN(G12)-FIND(" ",G12)) -> Industry Air conditioning Wind | J64: no | K64: =$D$5&$F$9&RIGHT(H12,3)&$B$5 -> IND-ACWINExt | L64: =IF(J64="Yes",K64,"") | O64: =IF(J64="Yes",I64,"") | P64: =L64 | Q64: =IF(J64="yes",LEFT(P64,3)&"-"&MID(P64,7,3),"") | R64: =LEFT(P64,6) | S64: =IF(P64<>"",AG64,"") | T64: =IF(Q64<>"",AH64,"") | U64: =IF(R64<>"",AI64,"") | V64: =IF(S64<>"",AJ64,"") | W64: =IF(T64<>"",AK64,"") | X64: =IF(U64<>"",AL64,"") | Y64: =IF(V64<>"",AM64,"") | Z64: =IF(W64<>"",AN64,"") | ... AD64: =IF(AA64<>"",AR64,"") | AG64: 0.6 | AH64: 2 | AI64: 1 | AJ64: 1 | AK64: =0.8*AJ64 -> 0.8 | AL64: =AJ64*0 -> 0 | AM64: 0.5 | AN64: 0.4 | AO64: 0 | AP64: 1
I65: =$C$5&" "&$E$9&" "&RIGHT(G13,LEN(G13)-FIND(" ",G13)) -> Industry Air conditioning Bio Liquids | J65: no | K65: =$D$5&$F$9&RIGHT(H13,3)&$B$5 -> IND-ACBILExt | L65: =IF(J65="Yes",K65,"") | O65: =IF(J65="Yes",I65,"") | P65: =L65 | Q65: =IF(J65="yes",LEFT(P65,3)&"-"&MID(P65,7,3),"") | R65: =LEFT(P65,6) | S65: =IF(P65<>"",AG65,"") | T65: =IF(Q65<>"",AH65,"") | U65: =IF(R65<>"",AI65,"") | V65: =IF(S65<>"",AJ65,"") | W65: =IF(T65<>"",AK65,"") | X65: =IF(U65<>"",AL65,"") | Y65: =IF(V65<>"",AM65,"") | Z65: =IF(W65<>"",AN65,"") | ... AD65: =IF(AA65<>"",AR65,"") | AG65: 0.6 | AH65: 2 | AI65: 1 | AJ65: 1 | AK65: =0.8*AJ65 -> 0.8 | AL65: =AJ65*0 -> 0 | AM65: 0.5 | AN65: 0.4 | AO65: 0 | AP65: 1
I66: =$C$5&" "&$E$9&" "&RIGHT(G14,LEN(G14)-FIND(" ",G14)) -> Industry Air conditioning Biogas | J66: no | K66: =$D$5&$F$9&RIGHT(H14,3)&$B$5 -> IND-ACBIGExt | L66: =IF(J66="Yes",K66,"") | O66: =IF(J66="Yes",I66,"") | P66: =L66 | Q66: =IF(J66="yes",LEFT(P66,3)&"-"&MID(P66,7,3),"") | R66: =LEFT(P66,6) | S66: =IF(P66<>"",AG66,"") | T66: =IF(Q66<>"",AH66,"") | U66: =IF(R66<>"",AI66,"") | V66: =IF(S66<>"",AJ66,"") | W66: =IF(T66<>"",AK66,"") | X66: =IF(U66<>"",AL66,"") | Y66: =IF(V66<>"",AM66,"") | Z66: =IF(W66<>"",AN66,"") | ... AD66: =IF(AA66<>"",AR66,"") | AG66: 0.6 | AH66: 2 | AI66: 1 | AJ66: 1 | AK66: =0.8*AJ66 -> 0.8 | AL66: =AJ66*0 -> 0 | AM66: 0.5 | AN66: 0.4 | AO66: 0 | AP66: 1
I67: =$C$5&" "&$E$9&" "&RIGHT(G15,LEN(G15)-FIND(" ",G15)) -> Industry Air conditioning Wood | J67: no | K67: =$D$5&$F$9&RIGHT(H15,3)&$B$5 -> IND-ACWODExt | L67: =IF(J67="Yes",K67,"") | O67: =IF(J67="Yes",I67,"") | P67: =L67 | Q67: =IF(J67="yes",LEFT(P67,3)&"-"&MID(P67,7,3),"") | R67: =LEFT(P67,6) | S67: =IF(P67<>"",AG67,"") | T67: =IF(Q67<>"",AH67,"") | U67: =IF(R67<>"",AI67,"") | V67: =IF(S67<>"",AJ67,"") | W67: =IF(T67<>"",AK67,"") | X67: =IF(U67<>"",AL67,"") | Y67: =IF(V67<>"",AM67,"") | Z67: =IF(W67<>"",AN67,"") | ... AD67: =IF(AA67<>"",AR67,"") | AG67: 0.6 | AH67: 2 | AI67: 1 | AJ67: 1 | AK67: =0.8*AJ67 -> 0.8 | AL67: =AJ67*0 -> 0 | AM67: 0.5 | AN67: 0.4 | AO67: 0 | AP67: 1
I68: =$C$5&" "&$E$9&" "&RIGHT(G16,LEN(G16)-FIND(" ",G16)) -> Industry Air conditioning Tidal | J68: no | K68: =$D$5&$F$9&RIGHT(H16,3)&$B$5 -> IND-ACTIDExt | L68: =IF(J68="Yes",K68,"") | O68: =IF(J68="Yes",I68,"") | P68: =L68 | Q68: =IF(J68="yes",LEFT(P68,3)&"-"&MID(P68,7,3),"") | R68: =LEFT(P68,6) | S68: =IF(P68<>"",AG68,"") | T68: =IF(Q68<>"",AH68,"") | U68: =IF(R68<>"",AI68,"") | V68: =IF(S68<>"",AJ68,"") | W68: =IF(T68<>"",AK68,"") | X68: =IF(U68<>"",AL68,"") | Y68: =IF(V68<>"",AM68,"") | Z68: =IF(W68<>"",AN68,"") | ... AD68: =IF(AA68<>"",AR68,"") | AG68: 0.6 | AH68: 2 | AI68: 1 | AJ68: 1 | AK68: =0.8*AJ68 -> 0.8 | AL68: =AJ68*0 -> 0 | AM68: 0.5 | AN68: 0.4 | AO68: 0 | AP68: 1
I69: =$C$5&" "&$E$9&" "&RIGHT(G17,LEN(G17)-FIND(" ",G17)) -> Industry Air conditioning Electricity | J69: yes | K69: =$D$5&$F$9&RIGHT(H17,3)&$B$5 -> IND-ACELCExt | L69: =IF(J69="Yes",K69,"") -> IND-ACELCExt | O69: =IF(J69="Yes",I69,"") -> Industry Air conditioning Electricity | P69: =L69 -> IND-ACELCExt | Q69: =IF(J69="yes",LEFT(P69,3)&"-"&MID(P69,7,3),"") -> IND-ELC | R69: =LEFT(P69,6) -> IND-AC | S69: =IF(P69<>"",AG69,"") -> 0.6 | T69: =IF(Q69<>"",AH69,"") -> 2 | U69: =IF(R69<>"",AI69,"") -> 1 | V69: =IF(S69<>"",AJ69,"") -> 1 | W69: =IF(T69<>"",AK69,"") -> 0.8 | X69: =IF(U69<>"",AL69,"") -> 0 | Y69: =IF(V69<>"",AM69,"") -> 0.5 | Z69: =IF(W69<>"",AN69,"") -> 0.4 | ... AD69: =IF(AA69<>"",AR69,"") -> 0 | AG69: 0.6 | AH69: 2 | AI69: 1 | AJ69: 1 | AK69: =0.8*AJ69 -> 0.8 | AL69: =AJ69*0 -> 0 | AM69: 0.5 | AN69: 0.4 | AO69: 0 | AP69: 1
I70: =$C$5&" "&$E$10&" "&RIGHT(G5,LEN(G5)-FIND(" ",G5)) -> Industry Electrical and ICT equipments Coal | J70: no | K70: =$D$5&$F$10&RIGHT(H5,3)&$B$5 -> IND-EQCOAExt | L70: =IF(J70="Yes",K70,"") | O70: =IF(J70="Yes",I70,"") | P70: =L70 | Q70: =IF(J70="yes",LEFT(P70,3)&"-"&MID(P70,7,3),"") | R70: =LEFT(P70,6) | S70: =IF(P70<>"",AG70,"") | T70: =IF(Q70<>"",AH70,"") | U70: =IF(R70<>"",AI70,"") | V70: =IF(S70<>"",AJ70,"") | W70: =IF(T70<>"",AK70,"") | X70: =IF(U70<>"",AL70,"") | Y70: =IF(V70<>"",AM70,"") | Z70: =IF(W70<>"",AN70,"") | ... AD70: =IF(AA70<>"",AR70,"") | AG70: 0.6 | AH70: 2 | AI70: 1 | AJ70: 1 | AK70: =0.8*AJ70 -> 0.8 | AL70: =AJ70*0 -> 0 | AM70: 0.5 | AN70: 0.4 | AO70: 0 | AP70: 1
I71: =$C$5&" "&$E$10&" "&RIGHT(G6,LEN(G6)-FIND(" ",G6)) -> Industry Electrical and ICT equipments Lignite | J71: no | K71: =$D$5&$F$10&RIGHT(H6,3)&$B$5 -> IND-EQCOLExt | L71: =IF(J71="Yes",K71,"") | O71: =IF(J71="Yes",I71,"") | P71: =L71 | Q71: =IF(J71="yes",LEFT(P71,3)&"-"&MID(P71,7,3),"") | R71: =LEFT(P71,6) | S71: =IF(P71<>"",AG71,"") | T71: =IF(Q71<>"",AH71,"") | U71: =IF(R71<>"",AI71,"") | V71: =IF(S71<>"",AJ71,"") | W71: =IF(T71<>"",AK71,"") | X71: =IF(U71<>"",AL71,"") | Y71: =IF(V71<>"",AM71,"") | Z71: =IF(W71<>"",AN71,"") | ... AD71: =IF(AA71<>"",AR71,"") | AG71: 0.6 | AH71: 2 | AI71: 1 | AJ71: 1 | AK71: =0.8*AJ71 -> 0.8 | AL71: =AJ71*0 -> 0 | AM71: 0.5 | AN71: 0.4 | AO71: 0 | AP71: 1
I72: =$C$5&" "&$E$10&" "&RIGHT(G7,LEN(G7)-FIND(" ",G7)) -> Industry Electrical and ICT equipments Crude oil | J72: no | K72: =$D$5&$F$10&RIGHT(H7,3)&$B$5 -> IND-EQOILExt | L72: =IF(J72="Yes",K72,"") | O72: =IF(J72="Yes",I72,"") | P72: =L72 | Q72: =IF(J72="yes",LEFT(P72,3)&"-"&MID(P72,7,3),"") | R72: =LEFT(P72,6) | S72: =IF(P72<>"",AG72,"") | T72: =IF(Q72<>"",AH72,"") | U72: =IF(R72<>"",AI72,"") | V72: =IF(S72<>"",AJ72,"") | W72: =IF(T72<>"",AK72,"") | X72: =IF(U72<>"",AL72,"") | Y72: =IF(V72<>"",AM72,"") | Z72: =IF(W72<>"",AN72,"") | ... AD72: =IF(AA72<>"",AR72,"") | AG72: 0.6 | AH72: 2 | AI72: 1 | AJ72: 1 | AK72: =0.8*AJ72 -> 0.8 | AL72: =AJ72*0 -> 0 | AM72: 0.5 | AN72: 0.4 | AO72: 0 | AP72: 1
I73: =$C$5&" "&$E$10&" "&RIGHT(G8,LEN(G8)-FIND(" ",G8)) -> Industry Electrical and ICT equipments Natural Gas | J73: no | K73: =$D$5&$F$10&RIGHT(H8,3)&$B$5 -> IND-EQNGAExt | L73: =IF(J73="Yes",K73,"") | O73: =IF(J73="Yes",I73,"") | P73: =L73 | Q73: =IF(J73="yes",LEFT(P73,3)&"-"&MID(P73,7,3),"") | R73: =LEFT(P73,6) | S73: =IF(P73<>"",AG73,"") | T73: =IF(Q73<>"",AH73,"") | U73: =IF(R73<>"",AI73,"") | V73: =IF(S73<>"",AJ73,"") | W73: =IF(T73<>"",AK73,"") | X73: =IF(U73<>"",AL73,"") | Y73: =IF(V73<>"",AM73,"") | Z73: =IF(W73<>"",AN73,"") | ... AD73: =IF(AA73<>"",AR73,"") | AG73: 0.6 | AH73: 2 | AI73: 1 | AJ73: 1 | AK73: =0.8*AJ73 -> 0.8 | AL73: =AJ73*0 -> 0 | AM73: 0.5 | AN73: 0.4 | AO73: 0 | AP73: 1
I74: =$C$5&" "&$E$10&" "&RIGHT(G9,LEN(G9)-FIND(" ",G9)) -> Industry Electrical and ICT equipments Hydro | J74: no | K74: =$D$5&$F$10&RIGHT(H9,3)&$B$5 -> IND-EQHYDExt | L74: =IF(J74="Yes",K74,"") | O74: =IF(J74="Yes",I74,"") | P74: =L74 | Q74: =IF(J74="yes",LEFT(P74,3)&"-"&MID(P74,7,3),"") | R74: =LEFT(P74,6) | S74: =IF(P74<>"",AG74,"") | T74: =IF(Q74<>"",AH74,"") | U74: =IF(R74<>"",AI74,"") | V74: =IF(S74<>"",AJ74,"") | W74: =IF(T74<>"",AK74,"") | X74: =IF(U74<>"",AL74,"") | Y74: =IF(V74<>"",AM74,"") | Z74: =IF(W74<>"",AN74,"") | ... AD74: =IF(AA74<>"",AR74,"") | AG74: 0.6 | AH74: 2 | AI74: 1 | AJ74: 1 | AK74: =0.8*AJ74 -> 0.8 | AL74: =AJ74*0 -> 0 | AM74: 0.5 | AN74: 0.4 | AO74: 0 | AP74: 1
I75: =$C$5&" "&$E$10&" "&RIGHT(G10,LEN(G10)-FIND(" ",G10)) -> Industry Electrical and ICT equipments Geothermal | J75: no | K75: =$D$5&$F$10&RIGHT(H10,3)&$B$5 -> IND-EQGEOExt | L75: =IF(J75="Yes",K75,"") | O75: =IF(J75="Yes",I75,"") | P75: =L75 | Q75: =IF(J75="yes",LEFT(P75,3)&"-"&MID(P75,7,3),"") | R75: =LEFT(P75,6) | S75: =IF(P75<>"",AG75,"") | T75: =IF(Q75<>"",AH75,"") | U75: =IF(R75<>"",AI75,"") | V75: =IF(S75<>"",AJ75,"") | W75: =IF(T75<>"",AK75,"") | X75: =IF(U75<>"",AL75,"") | Y75: =IF(V75<>"",AM75,"") | Z75: =IF(W75<>"",AN75,"") | ... AD75: =IF(AA75<>"",AR75,"") | AG75: 0.6 | AH75: 2 | AI75: 1 | AJ75: 1 | AK75: =0.8*AJ75 -> 0.8 | AL75: =AJ75*0 -> 0 | AM75: 0.5 | AN75: 0.4 | AO75: 0 | AP75: 1
I76: =$C$5&" "&$E$10&" "&RIGHT(G11,LEN(G11)-FIND(" ",G11)) -> Industry Electrical and ICT equipments Solar | J76: no | K76: =$D$5&$F$10&RIGHT(H11,3)&$B$5 -> IND-EQSOLExt | L76: =IF(J76="Yes",K76,"") | O76: =IF(J76="Yes",I76,"") | P76: =L76 | Q76: =IF(J76="yes",LEFT(P76,3)&"-"&MID(P76,7,3),"") | R76: =LEFT(P76,6) | S76: =IF(P76<>"",AG76,"") | T76: =IF(Q76<>"",AH76,"") | U76: =IF(R76<>"",AI76,"") | V76: =IF(S76<>"",AJ76,"") | W76: =IF(T76<>"",AK76,"") | X76: =IF(U76<>"",AL76,"") | Y76: =IF(V76<>"",AM76,"") | Z76: =IF(W76<>"",AN76,"") | ... AD76: =IF(AA76<>"",AR76,"") | AG76: 0.6 | AH76: 2 | AI76: 1 | AJ76: 1 | AK76: =0.8*AJ76 -> 0.8 | AL76: =AJ76*0 -> 0 | AM76: 0.5 | AN76: 0.4 | AO76: 0 | AP76: 1
I77: =$C$5&" "&$E$10&" "&RIGHT(G12,LEN(G12)-FIND(" ",G12)) -> Industry Electrical and ICT equipments Wind | J77: no | K77: =$D$5&$F$10&RIGHT(H12,3)&$B$5 -> IND-EQWINExt | L77: =IF(J77="Yes",K77,"") | O77: =IF(J77="Yes",I77,"") | P77: =L77 | Q77: =IF(J77="yes",LEFT(P77,3)&"-"&MID(P77,7,3),"") | R77: =LEFT(P77,6) | S77: =IF(P77<>"",AG77,"") | T77: =IF(Q77<>"",AH77,"") | U77: =IF(R77<>"",AI77,"") | V77: =IF(S77<>"",AJ77,"") | W77: =IF(T77<>"",AK77,"") | X77: =IF(U77<>"",AL77,"") | Y77: =IF(V77<>"",AM77,"") | Z77: =IF(W77<>"",AN77,"") | ... AD77: =IF(AA77<>"",AR77,"") | AG77: 0.6 | AH77: 2 | AI77: 1 | AJ77: 1 | AK77: =0.8*AJ77 -> 0.8 | AL77: =AJ77*0 -> 0 | AM77: 0.5 | AN77: 0.4 | AO77: 0 | AP77: 1
I78: =$C$5&" "&$E$10&" "&RIGHT(G13,LEN(G13)-FIND(" ",G13)) -> Industry Electrical and ICT equipments Bio Liquids | J78: no | K78: =$D$5&$F$10&RIGHT(H13,3)&$B$5 -> IND-EQBILExt | L78: =IF(J78="Yes",K78,"") | O78: =IF(J78="Yes",I78,"") | P78: =L78 | Q78: =IF(J78="yes",LEFT(P78,3)&"-"&MID(P78,7,3),"") | R78: =LEFT(P78,6) | S78: =IF(P78<>"",AG78,"") | T78: =IF(Q78<>"",AH78,"") | U78: =IF(R78<>"",AI78,"") | V78: =IF(S78<>"",AJ78,"") | W78: =IF(T78<>"",AK78,"") | X78: =IF(U78<>"",AL78,"") | Y78: =IF(V78<>"",AM78,"") | Z78: =IF(W78<>"",AN78,"") | ... AD78: =IF(AA78<>"",AR78,"") | AG78: 0.6 | AH78: 2 | AI78: 1 | AJ78: 1 | AK78: =0.8*AJ78 -> 0.8 | AL78: =AJ78*0 -> 0 | AM78: 0.5 | AN78: 0.4 | AO78: 0 | AP78: 1
I79: =$C$5&" "&$E$10&" "&RIGHT(G14,LEN(G14)-FIND(" ",G14)) -> Industry Electrical and ICT equipments Biogas | J79: no | K79: =$D$5&$F$10&RIGHT(H14,3)&$B$5 -> IND-EQBIGExt | L79: =IF(J79="Yes",K79,"") | O79: =IF(J79="Yes",I79,"") | P79: =L79 | Q79: =IF(J79="yes",LEFT(P79,3)&"-"&MID(P79,7,3),"") | R79: =LEFT(P79,6) | S79: =IF(P79<>"",AG79,"") | T79: =IF(Q79<>"",AH79,"") | U79: =IF(R79<>"",AI79,"") | V79: =IF(S79<>"",AJ79,"") | W79: =IF(T79<>"",AK79,"") | X79: =IF(U79<>"",AL79,"") | Y79: =IF(V79<>"",AM79,"") | Z79: =IF(W79<>"",AN79,"") | ... AD79: =IF(AA79<>"",AR79,"") | AG79: 0.6 | AH79: 2 | AI79: 1 | AJ79: 1 | AK79: =0.8*AJ79 -> 0.8 | AL79: =AJ79*0 -> 0 | AM79: 0.5 | AN79: 0.4 | AO79: 0 | AP79: 1
I80: =$C$5&" "&$E$10&" "&RIGHT(G15,LEN(G15)-FIND(" ",G15)) -> Industry Electrical and ICT equipments Wood | J80: no | K80: =$D$5&$F$10&RIGHT(H15,3)&$B$5 -> IND-EQWODExt | L80: =IF(J80="Yes",K80,"") | O80: =IF(J80="Yes",I80,"") | P80: =L80 | Q80: =IF(J80="yes",LEFT(P80,3)&"-"&MID(P80,7,3),"") | R80: =LEFT(P80,6) | S80: =IF(P80<>"",AG80,"") | T80: =IF(Q80<>"",AH80,"") | U80: =IF(R80<>"",AI80,"") | V80: =IF(S80<>"",AJ80,"") | W80: =IF(T80<>"",AK80,"") | X80: =IF(U80<>"",AL80,"") | Y80: =IF(V80<>"",AM80,"") | Z80: =IF(W80<>"",AN80,"") | ... AD80: =IF(AA80<>"",AR80,"") | AG80: 0.6 | AH80: 2 | AI80: 1 | AJ80: 1 | AK80: =0.8*AJ80 -> 0.8 | AL80: =AJ80*0 -> 0 | AM80: 0.5 | AN80: 0.4 | AO80: 0 | AP80: 1
I81: =$C$5&" "&$E$10&" "&RIGHT(G16,LEN(G16)-FIND(" ",G16)) -> Industry Electrical and ICT equipments Tidal | J81: no | K81: =$D$5&$F$10&RIGHT(H16,3)&$B$5 -> IND-EQTIDExt | L81: =IF(J81="Yes",K81,"") | O81: =IF(J81="Yes",I81,"") | P81: =L81 | Q81: =IF(J81="yes",LEFT(P81,3)&"-"&MID(P81,7,3),"") | R81: =LEFT(P81,6) | S81: =IF(P81<>"",AG81,"") | T81: =IF(Q81<>"",AH81,"") | U81: =IF(R81<>"",AI81,"") | V81: =IF(S81<>"",AJ81,"") | W81: =IF(T81<>"",AK81,"") | X81: =IF(U81<>"",AL81,"") | Y81: =IF(V81<>"",AM81,"") | Z81: =IF(W81<>"",AN81,"") | ... AD81: =IF(AA81<>"",AR81,"") | AG81: 0.6 | AH81: 2 | AI81: 1 | AJ81: 1 | AK81: =0.8*AJ81 -> 0.8 | AL81: =AJ81*0 -> 0 | AM81: 0.5 | AN81: 0.4 | AO81: 0 | AP81: 1
I82: =$C$5&" "&$E$10&" "&RIGHT(G17,LEN(G17)-FIND(" ",G17)) -> Industry Electrical and ICT equipments Electricity | J82: yes | K82: =$D$5&$F$10&RIGHT(H17,3)&$B$5 -> IND-EQELCExt | L82: =IF(J82="Yes",K82,"") -> IND-EQELCExt | O82: =IF(J82="Yes",I82,"") -> Industry Electrical and ICT equipments Electricity | P82: =L82 -> IND-EQELCExt | Q82: =IF(J82="yes",LEFT(P82,3)&"-"&MID(P82,7,3),"") -> IND-ELC | R82: =LEFT(P82,6) -> IND-EQ | S82: =IF(P82<>"",AG82,"") -> 0.6 | T82: =IF(Q82<>"",AH82,"") -> 2 | U82: =IF(R82<>"",AI82,"") -> 1 | V82: =IF(S82<>"",AJ82,"") -> 1 | W82: =IF(T82<>"",AK82,"") -> 0.8 | X82: =IF(U82<>"",AL82,"") -> 0 | Y82: =IF(V82<>"",AM82,"") -> 0.5 | Z82: =IF(W82<>"",AN82,"") -> 0.4 | ... AD82: =IF(AA82<>"",AR82,"") -> 0 | AG82: 0.6 | AH82: 2 | AI82: 1 | AJ82: 1 | AK82: =0.8*AJ82 -> 0.8 | AL82: =AJ82*0 -> 0 | AM82: 0.5 | AN82: 0.4 | AO82: 0 | AP82: 1
